Workbook
Name Slicer_Date: #N/A
Name Slicer_Date1: #N/A
Name Slicer_Party: #N/A
Name Slicer_Party_Name: #N/A
Name Slicer_Party_Name1: #N/A
Name Slicer_Party_Name2: #N/A
Name Slicer_Person: #N/A
Name Slicer_Shipment_Number: #N/A

Sheet Billing
B1: Party Name | C1: Tiyaar | D1: Rate | E1: Total | G1: Billing
B2: =B49 -> BSC | C2: =SUMIFS(ledger!G:G, ledger!B:B, B2, ledger!E:E, "<>*RD*") / 1.0936 -> 232352.78 | D2: 10 | E2: =(SUMIFS(ledger!G:G, ledger!B:B, B2, ledger!E:E, "<>*RD*",ledger!D:D, "Silky") / 1.0936)*12 + (SUMIFS(ledger!G:G, ledger!B:B, B2, ledger!E:E, "<>*RD*",ledger!D:D, "Chamki") / 1.0936)*10 -> 2524052.7 | Q2: Billing Total
B3: =B50 -> Ejaz Sahab | C3: =SUMIFS(ledger!G:G, ledger!B:B, B3, ledger!E:E, "<>*RD*") / 1.0936 -> 105662.95 | D3: 10 | E3: =(SUMIFS(ledger!G:G, ledger!B:B, B3, ledger!E:E, "<>*RD*",ledger!D:D, "Silky") / 1.0936)*12 + (SUMIFS(ledger!G:G, ledger!B:B, B3, ledger!E:E, "<>*RD*",ledger!D:D, "Chamki") / 1.0936)*10 -> 1267955.4
B4: =B51 -> Arshad | C4: =SUMIFS(ledger!G:G, ledger!B:B, B4, ledger!E:E, "<>*RD*") / 1.0936 -> 193527.8 | D4: 10 | E4: =(SUMIFS(ledger!G:G, ledger!B:B, B4, ledger!E:E, "<>*RD*",ledger!D:D, "Silky") / 1.0936)*12 + (SUMIFS(ledger!G:G, ledger!B:B, B4, ledger!E:E, "<>*RD*",ledger!D:D, "Chamki") / 1.0936)*10 -> 2061914.8 | R4: Gaz | S4: Total Metres | T4: Total Chamki | U4: Total Super Silky | V4: Billing (Chamki/Crinkle) | W4: Billing (Super Chamki) | X4: Billing (Slub) | Y4: Billing (Satin) | Z4: Billing (Black-chamki) | AB4: Adjusted Bill | AC4: Amount Paid | AD4: Balance | AE4: Rate (Chamki) | AF4: Rate (Super Silky)
B5: =B52 -> Shehzad Kamoki | C5: =SUMIFS(ledger!G:G, ledger!B:B, B5, ledger!E:E, "<>*RD*") / 1.0936 -> 0 | D5: 10.5 | E5: =(SUMIFS(ledger!G:G, ledger!B:B, B5, ledger!E:E, "<>*RD*",ledger!D:D, "Silky") / 1.0936)*12 + (SUMIFS(ledger!G:G, ledger!B:B, B5, ledger!E:E, "<>*RD*",ledger!D:D, "Chamki") / 1.0936)*10.5 -> 0 | Q5: {=_xlfn.UNIQUE(Table1[Party Name])} -> BSC | R5: {=_xlfn.BYROW(B49,_xlfn.LAMBDA(_xlpm.party,SUMIFS(ledger!G:G,ledger!B:B,_xlpm.party,ledger!E:E,"<>*RD*")))+_xlfn.IFNA(C84,0)} -> 2459509 | S5: {=_xlfn.BYROW(B49, _xlfn.LAMBDA(_xlpm.party, SUMIFS(ledger!G:G, ledger!B:B, _xlpm.party, ledger!E:E, "<>*RD*") / 1.0936 ))+_xlfn.IFNA(D84,0)} -> 2249002.4 | T5: {=(_xlfn.BYROW(B49,_xlfn.LAMBDA(_xlpm.party,SUMIFS(ledger!G:G,ledger!B:B,_xlpm.party,ledger!E:E,"<>*RD*",ledger!D:D,"Chamki")+SUMIFS(ledger!G:G, ledger!B:B, _xlpm.party, ledger!E:E, "<>*RD*", ledger!D:D, "Crinkle")))/1.0936)+_xlfn.IFNA(E84,0)} -> 2027492.7 | U5: {=(_xlfn.BYROW(B49,_xlfn.LAMBDA(_xlpm.party,SUMIFS(ledger!G:G,ledger!B:B,_xlpm.party,ledger!E:E,"<>*RD*",ledger!D:D,"Silky")))/1.0936)+_xlfn.IFNA(F84,0)} -> 221509.69 | V5: {=(_xlfn.BYROW(B49,_xlfn.LAMBDA(_xlpm.party, (SUMIFS(ledger!J:J,ledger!B:B,_xlpm.party,ledger!E:E,"<>*RD*",ledger!D:D,"Chamki",ledger!C:C,"<>October Closing CF")+ SUMIFS(ledger!J:J,ledger!B:B,_xlpm.party,ledger!E:E,"<>*RD*",ledger!D:D,"Crinkle",ledger!C:C,"<>October Closing CF") )+_xlfn.IFNA(G84,0))))} -> 20274927 | W5: {=_xlfn.BYROW(B49, _xlfn.LAMBDA(_xlpm.party, SUMIFS(ledger!J:J, ledger!B:B, _xlpm.party, ledger!E:E, "<>*RD*", ledger!D:D, "Silky", ledger!C:C, "<>October Closing CF") )) + _xlfn.IFNA(H84, 0)} -> 2791270.1 | X5: {=_xlfn.BYROW(B49, _xlfn.LAMBDA(_xlpm.party, SUMIFS(ledger!J:J, ledger!B:B, _xlpm.party, ledger!E:E, "<>*RD*", ledger!D:D, "Slub", ledger!C:C, "<>October Closing CF") ))+ _xlfn.IFNA(I84, 0)} -> 0 | Y5: {=_xlfn.BYROW(B49, _xlfn.LAMBDA(_xlpm.party, SUMIFS(ledger!J:J, ledger!B:B, _xlpm.party, ledger!E:E, "<>*RD*", ledger!D:D, "Satin", ledger!C:C, "<>October Closing CF") ))+ _xlfn.IFNA(J84, 0)} -> 0 | Z5: {=_xlfn.BYROW(B49, _xlfn.LAMBDA(_xlpm.party, SUMIFS(ledger!J:J, ledger!B:B, _xlpm.party, ledger!E:E, "<>*RD*", ledger!D:D, "Black-Chamki", ledger!C:C, "<>October Closing CF") ))} -> 0 | AA5: {=_xlfn.BYROW(B49, _xlfn.LAMBDA(_xlpm.party, SUMIFS(ledger!J:J, ledger!B:B, _xlpm.party, ledger!E:E, "<>*RD*", ledger!D:D, "Kataan", ledger!C:C, "<>October Closing CF") ))} -> 0 | AB5: =V5+W5+X5+Y5+Z5+AA5 -> 23066197 | AC5: =(SUMIF(Table14[Party],Q5,Table14[Credit]))+_xlfn.IFNA(L84,0) -> 19750734 | AD5: =AB5-AC5 -> 3315463 | AE5: 10 | AF5: 13
B6: =B53 -> Sufi Nawaz Sahab | C6: =SUMIFS(ledger!G:G, ledger!B:B, B6, ledger!E:E, "<>*RD*") / 1.0936 -> 0 | D6: 10 | E6: =((SUMIFS(ledger!G:G, ledger!B:B, B6, ledger!E:E, "<>*RD*",ledger!D:D, "Silky") / 1.0936) *12) + ((SUMIFS(ledger!G:G, ledger!B:B, B6, ledger!E:E, "<>*RD*",ledger!D:D, "Chamki") / 1.0936)* 9) -> 0 | Q6: Ejaz Sahab | R6: {=_xlfn.BYROW(B50,_xlfn.LAMBDA(_xlpm.party,SUMIFS(ledger!G:G,ledger!B:B,_xlpm.party,ledger!E:E,"<>*RD*")))+_xlfn.IFNA(C85,0)} -> 393394 | S6: {=_xlfn.BYROW(B50, _xlfn.LAMBDA(_xlpm.party, SUMIFS(ledger!G:G, ledger!B:B, _xlpm.party, ledger!E:E, "<>*RD*") / 1.0936 ))+_xlfn.IFNA(D85,0)} -> 359723.85 | T6: {=(_xlfn.BYROW(B50,_xlfn.LAMBDA(_xlpm.party,SUMIFS(ledger!G:G,ledger!B:B,_xlpm.party,ledger!E:E,"<>*RD*",ledger!D:D,"Chamki")+SUMIFS(ledger!G:G, ledger!B:B, _xlpm.party, ledger!E:E, "<>*RD*", ledger!D:D, "Crinkle")))/1.0936)+_xlfn.IFNA(E85,0)} -> 148145.57 | U6: {=(_xlfn.BYROW(B50,_xlfn.LAMBDA(_xlpm.party,SUMIFS(ledger!G:G,ledger!B:B,_xlpm.party,ledger!E:E,"<>*RD*",ledger!D:D,"Silky")))/1.0936)+_xlfn.IFNA(F85,0)} -> 211578.27 | V6: {=(_xlfn.BYROW(B50,_xlfn.LAMBDA(_xlpm.party, (SUMIFS(ledger!J:J,ledger!B:B,_xlpm.party,ledger!E:E,"<>*RD*",ledger!D:D,"Chamki",ledger!C:C,"<>October Closing CF")+ SUMIFS(ledger!J:J,ledger!B:B,_xlpm.party,ledger!E:E,"<>*RD*",ledger!D:D,"Crinkle",ledger!C:C,"<>October Closing CF") )+_xlfn.IFNA(G85,0))))} -> 1481455.7 | W6: {=_xlfn.BYROW(B50, _xlfn.LAMBDA(_xlpm.party, SUMIFS(ledger!J:J, ledger!B:B, _xlpm.party, ledger!E:E, "<>*RD*", ledger!D:D, "Silky", ledger!C:C, "<>October Closing CF") )) + _xlfn.IFNA(H85, 0)} -> 2691373.4 | X6: {=_xlfn.BYROW(B50, _xlfn.LAMBDA(_xlpm.party, SUMIFS(ledger!J:J, ledger!B:B, _xlpm.party, ledger!E:E, "<>*RD*", ledger!D:D, "Slub", ledger!C:C, "<>October Closing CF") ))+ _xlfn.IFNA(I85, 0)} -> 0 | Y6: {=_xlfn.BYROW(B50, _xlfn.LAMBDA(_xlpm.party, SUMIFS(ledger!J:J, ledger!B:B, _xlpm.party, ledger!E:E, "<>*RD*", ledger!D:D, "Satin", ledger!C:C, "<>October Closing CF") ))+ _xlfn.IFNA(J85, 0)} -> 0 | Z6: {=_xlfn.BYROW(B50, _xlfn.LAMBDA(_xlpm.party, SUMIFS(ledger!J:J, ledger!B:B, _xlpm.party, ledger!E:E, "<>*RD*", ledger!D:D, "Black-Chamki", ledger!C:C, "<>October Closing CF") ))} -> 0 | AA6: {=_xlfn.BYROW(B50, _xlfn.LAMBDA(_xlpm.party, SUMIFS(ledger!J:J, ledger!B:B, _xlpm.party, ledger!E:E, "<>*RD*", ledger!D:D, "Kataan", ledger!C:C, "<>October Closing CF") ))} -> 0 | AB6: =V6+W6+X6+Y6+Z6+AA6 -> 4172829.2 | AC6: =(SUMIF(Table14[Party],Q6,Table14[Credit]))+_xlfn.IFNA(L85,0) -> 3663904 | AD6: =AB6-AC6 -> 508925.19 | AE6: 10 | AF6: 13
B7: =B54 -> Sajad Khan | C7: =SUMIFS(ledger!G:G, ledger!B:B, B7, ledger!E:E, "<>*RD*") / 1.0936 -> 172007.13 | D7: 10 | E7: {=(SUMIFS(ledger!G:G, ledger!B:B, B7, ledger!E:E, "<>*RD*",ledger!D:D, "Silky") / 1.0936)*12 + (SUMIFS(ledger!G:G, ledger!B:B, B7, ledger!E:E, "<>*RD*",ledger!D:D, "Chamki") / 1.0936)*10 +(SUMIFS(ledger!G:G, ledger!B:B, party, ledger!E:E, "<>*RD*", ledger!D:D, "Crinkle")/ 1.0936)*10} -> 1720071.3 | Q7: Arshad | R7: {=_xlfn.BYROW(B51,_xlfn.LAMBDA(_xlpm.party,SUMIFS(ledger!G:G,ledger!B:B,_xlpm.party,ledger!E:E,"<>*RD*")))+_xlfn.IFNA(C86,0)} -> 657148 | S7: {=_xlfn.BYROW(B51, _xlfn.LAMBDA(_xlpm.party, SUMIFS(ledger!G:G, ledger!B:B, _xlpm.party, ledger!E:E, "<>*RD*") / 1.0936 ))+_xlfn.IFNA(D86,0)} -> 600903.44 | T7: {=(_xlfn.BYROW(B51,_xlfn.LAMBDA(_xlpm.party,SUMIFS(ledger!G:G,ledger!B:B,_xlpm.party,ledger!E:E,"<>*RD*",ledger!D:D,"Chamki")+SUMIFS(ledger!G:G, ledger!B:B, _xlpm.party, ledger!E:E, "<>*RD*", ledger!D:D, "Crinkle")))/1.0936)+_xlfn.IFNA(E86,0)} -> 522790.78 | U7: {=(_xlfn.BYROW(B51,_xlfn.LAMBDA(_xlpm.party,SUMIFS(ledger!G:G,ledger!B:B,_xlpm.party,ledger!E:E,"<>*RD*",ledger!D:D,"Silky")))/1.0936)+_xlfn.IFNA(F86,0)} -> 78112.655 | V7: {=(_xlfn.BYROW(B51,_xlfn.LAMBDA(_xlpm.party, (SUMIFS(ledger!J:J,ledger!B:B,_xlpm.party,ledger!E:E,"<>*RD*",ledger!D:D,"Chamki",ledger!C:C,"<>October Closing CF")+ SUMIFS(ledger!J:J,ledger!B:B,_xlpm.party,ledger!E:E,"<>*RD*",ledger!D:D,"Crinkle",ledger!C:C,"<>October Closing CF") )+_xlfn.IFNA(G86,0))))} -> 5227907.8 | W7: {=_xlfn.BYROW(B51, _xlfn.LAMBDA(_xlpm.party, SUMIFS(ledger!J:J, ledger!B:B, _xlpm.party, ledger!E:E, "<>*RD*", ledger!D:D, "Silky", ledger!C:C, "<>October Closing CF") )) + _xlfn.IFNA(H86, 0)} -> 1000670.3 | X7: {=_xlfn.BYROW(B51, _xlfn.LAMBDA(_xlpm.party, SUMIFS(ledger!J:J, ledger!B:B, _xlpm.party, ledger!E:E, "<>*RD*", ledger!D:D, "Slub", ledger!C:C, "<>October Closing CF") ))+ _xlfn.IFNA(I86, 0)} -> 0 | Y7: {=_xlfn.BYROW(B51, _xlfn.LAMBDA(_xlpm.party, SUMIFS(ledger!J:J, ledger!B:B, _xlpm.party, ledger!E:E, "<>*RD*", ledger!D:D, "Satin", ledger!C:C, "<>October Closing CF") ))+ _xlfn.IFNA(J86, 0)} -> 0 | Z7: {=_xlfn.BYROW(B51, _xlfn.LAMBDA(_xlpm.party, SUMIFS(ledger!J:J, ledger!B:B, _xlpm.party, ledger!E:E, "<>*RD*", ledger!D:D, "Black-Chamki", ledger!C:C, "<>October Closing CF") ))} -> 0 | AA7: {=_xlfn.BYROW(B51, _xlfn.LAMBDA(_xlpm.party, SUMIFS(ledger!J:J, ledger!B:B, _xlpm.party, ledger!E:E, "<>*RD*", ledger!D:D, "Kataan", ledger!C:C, "<>October Closing CF") ))} -> 0 | AB7: =V7+W7+X7+Y7+Z7+AA7 -> 6228578.1 | AC7: =(SUMIF(Table14[Party],Q7,Table14[Credit]))+_xlfn.IFNA(L86,0) -> 5802935 | AD7: =AB7-AC7 -> 425643.09 | AE7: 10 | AF7: 13
B8: =B55 -> Raaz Fabrics | C8: =SUMIFS(ledger!G:G, ledger!B:B, B8, ledger!E:E, "<>*RD*") / 1.0936 -> 47108.632 | D8: 10 | E8: =(SUMIFS(ledger!G:G, ledger!B:B, B8, ledger!E:E, "<>*RD*",ledger!D:D, "Silky") / 1.0936)*12 + (SUMIFS(ledger!G:G, ledger!B:B, B8, ledger!E:E, "<>*RD*",ledger!D:D, "chamki") / 1.0936)*10 +(SUMIFS(ledger!G:G, ledger!B:B, B8, ledger!E:E, "<>*RD*",ledger!D:D, "Crinkle") / 1.0936)*10 -> 471086.32 | Q8: Shehzad Kamoki | R8: {=_xlfn.BYROW(B52,_xlfn.LAMBDA(_xlpm.party,SUMIFS(ledger!G:G,ledger!B:B,_xlpm.party,ledger!E:E,"<>*RD*")))+_xlfn.IFNA(C87,0)} -> 134607 | S8: {=_xlfn.BYROW(B52, _xlfn.LAMBDA(_xlpm.party, SUMIFS(ledger!G:G, ledger!B:B, _xlpm.party, ledger!E:E, "<>*RD*") / 1.0936 ))+_xlfn.IFNA(D87,0)} -> 123086.14 | T8: {=(_xlfn.BYROW(B52,_xlfn.LAMBDA(_xlpm.party,SUMIFS(ledger!G:G,ledger!B:B,_xlpm.party,ledger!E:E,"<>*RD*",ledger!D:D,"Chamki")+SUMIFS(ledger!G:G, ledger!B:B, _xlpm.party, ledger!E:E, "<>*RD*", ledger!D:D, "Crinkle")))/1.0936)+_xlfn.IFNA(E87,0)} -> 123086.14 | U8: {=(_xlfn.BYROW(B52,_xlfn.LAMBDA(_xlpm.party,SUMIFS(ledger!G:G,ledger!B:B,_xlpm.party,ledger!E:E,"<>*RD*",ledger!D:D,"Silky")))/1.0936)+_xlfn.IFNA(F87,0)} -> 0 | V8: {=(_xlfn.BYROW(B52,_xlfn.LAMBDA(_xlpm.party, (SUMIFS(ledger!J:J,ledger!B:B,_xlpm.party,ledger!E:E,"<>*RD*",ledger!D:D,"Chamki",ledger!C:C,"<>October Closing CF")+ SUMIFS(ledger!J:J,ledger!B:B,_xlpm.party,ledger!E:E,"<>*RD*",ledger!D:D,"Crinkle",ledger!C:C,"<>October Closing CF") )+_xlfn.IFNA(G87,0))))} -> 1269270.3 | W8: {=_xlfn.BYROW(B52, _xlfn.LAMBDA(_xlpm.party, SUMIFS(ledger!J:J, ledger!B:B, _xlpm.party, ledger!E:E, "<>*RD*", ledger!D:D, "Silky", ledger!C:C, "<>October Closing CF") )) + _xlfn.IFNA(H87, 0)} -> 0 | X8: {=_xlfn.BYROW(B52, _xlfn.LAMBDA(_xlpm.party, SUMIFS(ledger!J:J, ledger!B:B, _xlpm.party, ledger!E:E, "<>*RD*", ledger!D:D, "Slub", ledger!C:C, "<>October Closing CF") ))+ _xlfn.IFNA(I87, 0)} -> 0 | Y8: {=_xlfn.BYROW(B52, _xlfn.LAMBDA(_xlpm.party, SUMIFS(ledger!J:J, ledger!B:B, _xlpm.party, ledger!E:E, "<>*RD*", ledger!D:D, "Satin", ledger!C:C, "<>October Closing CF") ))+ _xlfn.IFNA(J87, 0)} -> 0 | Z8: {=_xlfn.BYROW(B52, _xlfn.LAMBDA(_xlpm.party, SUMIFS(ledger!J:J, ledger!B:B, _xlpm.party, ledger!E:E, "<>*RD*", ledger!D:D, "Black-Chamki", ledger!C:C, "<>October Closing CF") ))} -> 0 | AA8: {=_xlfn.BYROW(B52, _xlfn.LAMBDA(_xlpm.party, SUMIFS(ledger!J:J, ledger!B:B, _xlpm.party, ledger!E:E, "<>*RD*", ledger!D:D, "Kataan", ledger!C:C, "<>October Closing CF") ))} -> 0 | AB8: =V8+W8+X8+Y8+Z8+AA8 -> 1269270.3 | AC8: =(SUMIF(Table14[Party],Q8,Table14[Credit]))+_xlfn.IFNA(L87,0) -> 1268740 | AD8: =AB8-AC8 -> 530.34404 | AE8: 10.5 | AF8: 13
B9: =B56 -> Azam | C9: =SUMIFS(ledger!G:G, ledger!B:B, B9, ledger!E:E, "<>*RD*") / 1.0936 -> 139682.7 | D9: 10 | E9: =(SUMIFS(ledger!G:G, ledger!B:B, B9, ledger!E:E, "<>*RD*",ledger!D:D, "Silky") / 1.0936)*12 + (SUMIFS(ledger!G:G, ledger!B:B, B9, ledger!E:E, "<>*RD*",ledger!D:D, "Chamki") / 1.0936)*10 -> 1396827 | Q9: Sufi Nawaz Sahab | R9: {=_xlfn.BYROW(B53,_xlfn.LAMBDA(_xlpm.party,SUMIFS(ledger!G:G,ledger!B:B,_xlpm.party,ledger!E:E,"<>*RD*")))+_xlfn.IFNA(C88,0)} -> 1186725 | S9: {=_xlfn.BYROW(B53, _xlfn.LAMBDA(_xlpm.party, SUMIFS(ledger!G:G, ledger!B:B, _xlpm.party, ledger!E:E, "<>*RD*") / 1.0936 ))+_xlfn.IFNA(D88,0)} -> 1085154.5 | T9: {=(_xlfn.BYROW(B53,_xlfn.LAMBDA(_xlpm.party,SUMIFS(ledger!G:G,ledger!B:B,_xlpm.party,ledger!E:E,"<>*RD*",ledger!D:D,"Chamki")+SUMIFS(ledger!G:G, ledger!B:B, _xlpm.party, ledger!E:E, "<>*RD*", ledger!D:D, "Crinkle")))/1.0936)+_xlfn.IFNA(E88,0)} -> 599330.65 | U9: {=(_xlfn.BYROW(B53,_xlfn.LAMBDA(_xlpm.party,SUMIFS(ledger!G:G,ledger!B:B,_xlpm.party,ledger!E:E,"<>*RD*",ledger!D:D,"Silky")))/1.0936)+_xlfn.IFNA(F88,0)} -> 485823.88 | V9: {=(_xlfn.BYROW(B53,_xlfn.LAMBDA(_xlpm.party, (SUMIFS(ledger!J:J,ledger!B:B,_xlpm.party,ledger!E:E,"<>*RD*",ledger!D:D,"Chamki",ledger!C:C,"<>October Closing CF")+ SUMIFS(ledger!J:J,ledger!B:B,_xlpm.party,ledger!E:E,"<>*RD*",ledger!D:D,"Crinkle",ledger!C:C,"<>October Closing CF") )+_xlfn.IFNA(G88,0))))} -> 5408917.9 | W9: {=_xlfn.BYROW(B53, _xlfn.LAMBDA(_xlpm.party, SUMIFS(ledger!J:J, ledger!B:B, _xlpm.party, ledger!E:E, "<>*RD*", ledger!D:D, "Silky", ledger!C:C, "<>October Closing CF") )) + _xlfn.IFNA(H88, 0)} -> 5829886.6 | X9: {=_xlfn.BYROW(B53, _xlfn.LAMBDA(_xlpm.party, SUMIFS(ledger!J:J, ledger!B:B, _xlpm.party, ledger!E:E, "<>*RD*", ledger!D:D, "Slub", ledger!C:C, "<>October Closing CF") ))+ _xlfn.IFNA(I88, 0)} -> 0 | Y9: {=_xlfn.BYROW(B53, _xlfn.LAMBDA(_xlpm.party, SUMIFS(ledger!J:J, ledger!B:B, _xlpm.party, ledger!E:E, "<>*RD*", ledger!D:D, "Satin", ledger!C:C, "<>October Closing CF") ))+ _xlfn.IFNA(J88, 0)} -> 0 | Z9: {=_xlfn.BYROW(B53, _xlfn.LAMBDA(_xlpm.party, SUMIFS(ledger!J:J, ledger!B:B, _xlpm.party, ledger!E:E, "<>*RD*", ledger!D:D, "Black-Chamki", ledger!C:C, "<>October Closing CF") ))} -> 0 | AA9: {=_xlfn.BYROW(B53, _xlfn.LAMBDA(_xlpm.party, SUMIFS(ledger!J:J, ledger!B:B, _xlpm.party, ledger!E:E, "<>*RD*", ledger!D:D, "Kataan", ledger!C:C, "<>October Closing CF") ))} -> 0 | AB9: =V9+W9+X9+Y9+Z9+AA9 -> 11238804 | AC9: =(SUMIF(Table14[Party],Q9,Table14[Credit]))+_xlfn.IFNA(L88,0) -> 10629100 | AD9: =AB9-AC9 -> 609704.47 | AE9: 10 | AF9: 13
B10: =B57 -> Ubaidullah | C10: =SUMIFS(ledger!G:G, ledger!B:B, B10, ledger!E:E, "<>*RD*") / 1.0936 -> 0 | D10: 10 | E10: =(SUMIFS(ledger!G:G, ledger!B:B, B10, ledger!E:E, "<>*RD*",ledger!D:D, "Silky") / 1.0936)*12 + (SUMIFS(ledger!G:G, ledger!B:B, B10, ledger!E:E, "<>*RD*",ledger!D:D, "Chamki") / 1.0936)*10 -> 0 | Q10: Sajad Khan | R10: {=_xlfn.BYROW(B54,_xlfn.LAMBDA(_xlpm.party,SUMIFS(ledger!G:G,ledger!B:B,_xlpm.party,ledger!E:E,"<>*RD*")))+_xlfn.IFNA(C89,0)} -> 792787 | S10: {=_xlfn.BYROW(B54, _xlfn.LAMBDA(_xlpm.party, SUMIFS(ledger!G:G, ledger!B:B, _xlpm.party, ledger!E:E, "<>*RD*") / 1.0936 ))+_xlfn.IFNA(D89,0)} -> 724933.25 | T10: {=(_xlfn.BYROW(B54,_xlfn.LAMBDA(_xlpm.party,SUMIFS(ledger!G:G,ledger!B:B,_xlpm.party,ledger!E:E,"<>*RD*",ledger!D:D,"Chamki")+SUMIFS(ledger!G:G, ledger!B:B, _xlpm.party, ledger!E:E, "<>*RD*", ledger!D:D, "Crinkle")))/1.0936)+_xlfn.IFNA(E89,0)} -> 719444.04 | U10: {=(_xlfn.BYROW(B54,_xlfn.LAMBDA(_xlpm.party,SUMIFS(ledger!G:G,ledger!B:B,_xlpm.party,ledger!E:E,"<>*RD*",ledger!D:D,"Silky")))/1.0936)+_xlfn.IFNA(F89,0)} -> 0 | V10: {=(_xlfn.BYROW(B54,_xlfn.LAMBDA(_xlpm.party, (SUMIFS(ledger!J:J,ledger!B:B,_xlpm.party,ledger!E:E,"<>*RD*",ledger!D:D,"Chamki",ledger!C:C,"<>October Closing CF")+ SUMIFS(ledger!J:J,ledger!B:B,_xlpm.party,ledger!E:E,"<>*RD*",ledger!D:D,"Crinkle",ledger!C:C,"<>October Closing CF") )+_xlfn.IFNA(G89,0))))} -> 7194440.4 | W10: {=_xlfn.BYROW(B54, _xlfn.LAMBDA(_xlpm.party, SUMIFS(ledger!J:J, ledger!B:B, _xlpm.party, ledger!E:E, "<>*RD*", ledger!D:D, "Silky", ledger!C:C, "<>October Closing CF") )) + _xlfn.IFNA(H89, 0)} -> 0 | X10: {=_xlfn.BYROW(B54, _xlfn.LAMBDA(_xlpm.party, SUMIFS(ledger!J:J, ledger!B:B, _xlpm.party, ledger!E:E, "<>*RD*", ledger!D:D, "Slub", ledger!C:C, "<>October Closing CF") ))+ _xlfn.IFNA(I89, 0)} -> 71359.729 | Y10: {=_xlfn.BYROW(B54, _xlfn.LAMBDA(_xlpm.party, SUMIFS(ledger!J:J, ledger!B:B, _xlpm.party, ledger!E:E, "<>*RD*", ledger!D:D, "Satin", ledger!C:C, "<>October Closing CF") ))+ _xlfn.IFNA(J89, 0)} -> 0 | Z10: {=_xlfn.BYROW(B54, _xlfn.LAMBDA(_xlpm.party, SUMIFS(ledger!J:J, ledger!B:B, _xlpm.party, ledger!E:E, "<>*RD*", ledger!D:D, "Black-Chamki", ledger!C:C, "<>October Closing CF") ))} -> 0 | AA10: {=_xlfn.BYROW(B54, _xlfn.LAMBDA(_xlpm.party, SUMIFS(ledger!J:J, ledger!B:B, _xlpm.party, ledger!E:E, "<>*RD*", ledger!D:D, "Kataan", ledger!C:C, "<>October Closing CF") ))} -> 0 | AB10: =V10+W10+X10+Y10+Z10+AA10 -> 7265800.1 | AC10: =(SUMIF(Table14[Party],Q10,Table14[Credit]))+_xlfn.IFNA(L89,0) -> 6897871 | AD10: =AB10-AC10 -> 367929.11 | AE10: 10 | AF10: 13
B11: =B58 -> Ashraf Zia | C11: =SUMIFS(ledger!G:G, ledger!B:B, B11, ledger!E:E, "<>*RD*") / 1.0936 -> 0 | D11: 12 | E11: =(SUMIFS(ledger!G:G, ledger!B:B, B11, ledger!E:E, "<>*RD*",ledger!D:D, "Silky") / 1.0936)*12 + (SUMIFS(ledger!G:G, ledger!B:B, B11, ledger!E:E, "<>*RD*",ledger!D:D, "Chamki") / 1.0936)*10 -> 0 | Q11: Raaz Fabrics | R11: {=_xlfn.BYROW(B55,_xlfn.LAMBDA(_xlpm.party,SUMIFS(ledger!G:G,ledger!B:B,_xlpm.party,ledger!E:E,"<>*RD*")))+_xlfn.IFNA(C90,0)} -> 152434 | S11: {=_xlfn.BYROW(B55, _xlfn.LAMBDA(_xlpm.party, SUMIFS(ledger!G:G, ledger!B:B, _xlpm.party, ledger!E:E, "<>*RD*") / 1.0936 ))+_xlfn.IFNA(D90,0)} -> 139387.34 | T11: {=(_xlfn.BYROW(B55,_xlfn.LAMBDA(_xlpm.party,SUMIFS(ledger!G:G,ledger!B:B,_xlpm.party,ledger!E:E,"<>*RD*",ledger!D:D,"Chamki")+SUMIFS(ledger!G:G, ledger!B:B, _xlpm.party, ledger!E:E, "<>*RD*", ledger!D:D, "Crinkle")))/1.0936)+_xlfn.IFNA(E90,0)} -> 139387.34 | U11: {=(_xlfn.BYROW(B55,_xlfn.LAMBDA(_xlpm.party,SUMIFS(ledger!G:G,ledger!B:B,_xlpm.party,ledger!E:E,"<>*RD*",ledger!D:D,"Silky")))/1.0936)+_xlfn.IFNA(F90,0)} -> 0 | V11: {=(_xlfn.BYROW(B55,_xlfn.LAMBDA(_xlpm.party, (SUMIFS(ledger!J:J,ledger!B:B,_xlpm.party,ledger!E:E,"<>*RD*",ledger!D:D,"Chamki",ledger!C:C,"<>October Closing CF")+ SUMIFS(ledger!J:J,ledger!B:B,_xlpm.party,ledger!E:E,"<>*RD*",ledger!D:D,"Crinkle",ledger!C:C,"<>October Closing CF") )+_xlfn.IFNA(G90,0))))} -> 1393873.4 | W11: {=_xlfn.BYROW(B55, _xlfn.LAMBDA(_xlpm.party, SUMIFS(ledger!J:J, ledger!B:B, _xlpm.party, ledger!E:E, "<>*RD*", ledger!D:D, "Silky", ledger!C:C, "<>October Closing CF") )) + _xlfn.IFNA(H90, 0)} -> 0 | X11: {=_xlfn.BYROW(B55, _xlfn.LAMBDA(_xlpm.party, SUMIFS(ledger!J:J, ledger!B:B, _xlpm.party, ledger!E:E, "<>*RD*", ledger!D:D, "Slub", ledger!C:C, "<>October Closing CF") ))+ _xlfn.IFNA(I90, 0)} -> 0 | Y11: {=_xlfn.BYROW(B55, _xlfn.LAMBDA(_xlpm.party, SUMIFS(ledger!J:J, ledger!B:B, _xlpm.party, ledger!E:E, "<>*RD*", ledger!D:D, "Satin", ledger!C:C, "<>October Closing CF") ))+ _xlfn.IFNA(J90, 0)} -> 0 | Z11: {=_xlfn.BYROW(B55, _xlfn.LAMBDA(_xlpm.party, SUMIFS(ledger!J:J, ledger!B:B, _xlpm.party, ledger!E:E, "<>*RD*", ledger!D:D, "Black-Chamki", ledger!C:C, "<>October Closing CF") ))} -> 0 | AA11: {=_xlfn.BYROW(B55, _xlfn.LAMBDA(_xlpm.party, SUMIFS(ledger!J:J, ledger!B:B, _xlpm.party, ledger!E:E, "<>*RD*", ledger!D:D, "Kataan", ledger!C:C, "<>October Closing CF") ))} -> 0 | AB11: =V11+W11+X11+Y11+Z11+AA11 -> 1393873.4 | AC11: =(SUMIF(Table14[Party],Q11,Table14[Credit]))+_xlfn.IFNA(L90,0) -> 1000000 | AD11: =AB11-AC11 -> 393873.45 | AE11: 10 | AF11: 13
B12: =B59 -> Hafiz Qureshi | C12: =SUMIFS(ledger!G:G, ledger!B:B, B12, ledger!E:E, "<>*RD*") / 1.0936 -> 64305.048 | E12: =(SUMIFS(ledger!G:G, ledger!B:B, B12, ledger!E:E, "<>*RD*",ledger!D:D, "Silky") / 1.0936)*12 + (SUMIFS(ledger!G:G, ledger!B:B, B12, ledger!E:E, "<>*RD*",ledger!D:D, "Chamki") / 1.0936)*10 -> 643050.48 | Q12: Azam | R12: {=_xlfn.BYROW(B56,_xlfn.LAMBDA(_xlpm.party,SUMIFS(ledger!G:G,ledger!B:B,_xlpm.party,ledger!E:E,"<>*RD*")))+_xlfn.IFNA(C91,0)} -> 357257 | S12: {=_xlfn.BYROW(B56, _xlfn.LAMBDA(_xlpm.party, SUMIFS(ledger!G:G, ledger!B:B, _xlpm.party, ledger!E:E, "<>*RD*") / 1.0936 ))+_xlfn.IFNA(D91,0)} -> 326679.77 | T12: {=(_xlfn.BYROW(B56,_xlfn.LAMBDA(_xlpm.party,SUMIFS(ledger!G:G,ledger!B:B,_xlpm.party,ledger!E:E,"<>*RD*",ledger!D:D,"Chamki")+SUMIFS(ledger!G:G, ledger!B:B, _xlpm.party, ledger!E:E, "<>*RD*", ledger!D:D, "Crinkle")))/1.0936)+_xlfn.IFNA(E91,0)} -> 301491.4 | U12: {=(_xlfn.BYROW(B56,_xlfn.LAMBDA(_xlpm.party,SUMIFS(ledger!G:G,ledger!B:B,_xlpm.party,ledger!E:E,"<>*RD*",ledger!D:D,"Silky")))/1.0936)+_xlfn.IFNA(F91,0)} -> 25188.369 | V12: {=(_xlfn.BYROW(B56,_xlfn.LAMBDA(_xlpm.party, (SUMIFS(ledger!J:J,ledger!B:B,_xlpm.party,ledger!E:E,"<>*RD*",ledger!D:D,"Chamki",ledger!C:C,"<>October Closing CF")+ SUMIFS(ledger!J:J,ledger!B:B,_xlpm.party,ledger!E:E,"<>*RD*",ledger!D:D,"Crinkle",ledger!C:C,"<>October Closing CF") )+_xlfn.IFNA(G91,0))))} -> 3014914 | W12: {=_xlfn.BYROW(B56, _xlfn.LAMBDA(_xlpm.party, SUMIFS(ledger!J:J, ledger!B:B, _xlpm.party, ledger!E:E, "<>*RD*", ledger!D:D, "Silky", ledger!C:C, "<>October Closing CF") )) + _xlfn.IFNA(H91, 0)} -> 327448.79 | X12: {=_xlfn.BYROW(B56, _xlfn.LAMBDA(_xlpm.party, SUMIFS(ledger!J:J, ledger!B:B, _xlpm.party, ledger!E:E, "<>*RD*", ledger!D:D, "Slub", ledger!C:C, "<>October Closing CF") ))+ _xlfn.IFNA(I91, 0)} -> 0 | Y12: {=_xlfn.BYROW(B56, _xlfn.LAMBDA(_xlpm.party, SUMIFS(ledger!J:J, ledger!B:B, _xlpm.party, ledger!E:E, "<>*RD*", ledger!D:D, "Satin", ledger!C:C, "<>October Closing CF") ))+ _xlfn.IFNA(J91, 0)} -> 0 | Z12: {=_xlfn.BYROW(B56, _xlfn.LAMBDA(_xlpm.party, SUMIFS(ledger!J:J, ledger!B:B, _xlpm.party, ledger!E:E, "<>*RD*", ledger!D:D, "Black-Chamki", ledger!C:C, "<>October Closing CF") ))} -> 0 | AA12: {=_xlfn.BYROW(B56, _xlfn.LAMBDA(_xlpm.party, SUMIFS(ledger!J:J, ledger!B:B, _xlpm.party, ledger!E:E, "<>*RD*", ledger!D:D, "Kataan", ledger!C:C, "<>October Closing CF") ))} -> 0 | AB12: =V12+W12+X12+Y12+Z12+AA12 -> 3342362.8 | AC12: =(SUMIF(Table14[Party],Q12,Table14[Credit]))+_xlfn.IFNA(L91,0) -> 3322620 | AD12: =AB12-AC12 -> 19742.838 | AE12: 10 | AF12: 13
B13: =B60 -> Badshah Fabrics | C13: =SUMIFS(ledger!G:G, ledger!B:B, B13, ledger!E:E, "<>*RD*") / 1.0936 -> 68178.493 | E13: =(SUMIFS(ledger!G:G, ledger!B:B, B13, ledger!E:E, "<>*RD*",ledger!D:D, "Silky") / 1.0936)*12 + (SUMIFS(ledger!G:G, ledger!B:B, B13, ledger!E:E, "<>*RD*",ledger!D:D, "Chamki") / 1.0936)*10 -> 789903.07 | Q13: Ubaidullah | R13: {=_xlfn.BYROW(B57,_xlfn.LAMBDA(_xlpm.party,SUMIFS(ledger!G:G,ledger!B:B,_xlpm.party,ledger!E:E,"<>*RD*")))+_xlfn.IFNA(C92,0)} -> 66850 | S13: {=_xlfn.BYROW(B57, _xlfn.LAMBDA(_xlpm.party, SUMIFS(ledger!G:G, ledger!B:B, _xlpm.party, ledger!E:E, "<>*RD*") / 1.0936 ))+_xlfn.IFNA(D92,0)} -> 61128.383 | T13: {=(_xlfn.BYROW(B57,_xlfn.LAMBDA(_xlpm.party,SUMIFS(ledger!G:G,ledger!B:B,_xlpm.party,ledger!E:E,"<>*RD*",ledger!D:D,"Chamki")+SUMIFS(ledger!G:G, ledger!B:B, _xlpm.party, ledger!E:E, "<>*RD*", ledger!D:D, "Crinkle")))/1.0936)+_xlfn.IFNA(E92,0)} -> 46132.955 | U13: {=(_xlfn.BYROW(B57,_xlfn.LAMBDA(_xlpm.party,SUMIFS(ledger!G:G,ledger!B:B,_xlpm.party,ledger!E:E,"<>*RD*",ledger!D:D,"Silky")))/1.0936)+_xlfn.IFNA(F92,0)} -> 14995.428 | V13: {=(_xlfn.BYROW(B57,_xlfn.LAMBDA(_xlpm.party, (SUMIFS(ledger!J:J,ledger!B:B,_xlpm.party,ledger!E:E,"<>*RD*",ledger!D:D,"Chamki",ledger!C:C,"<>October Closing CF")+ SUMIFS(ledger!J:J,ledger!B:B,_xlpm.party,ledger!E:E,"<>*RD*",ledger!D:D,"Crinkle",ledger!C:C,"<>October Closing CF") )+_xlfn.IFNA(G92,0))))} -> 461329.55 | W13: {=_xlfn.BYROW(B57, _xlfn.LAMBDA(_xlpm.party, SUMIFS(ledger!J:J, ledger!B:B, _xlpm.party, ledger!E:E, "<>*RD*", ledger!D:D, "Silky", ledger!C:C, "<>October Closing CF") )) + _xlfn.IFNA(H92, 0)} -> 179945.14 | X13: {=_xlfn.BYROW(B57, _xlfn.LAMBDA(_xlpm.party, SUMIFS(ledger!J:J, ledger!B:B, _xlpm.party, ledger!E:E, "<>*RD*", ledger!D:D, "Slub", ledger!C:C, "<>October Closing CF") ))+ _xlfn.IFNA(I92, 0)} -> 0 | Y13: {=_xlfn.BYROW(B57, _xlfn.LAMBDA(_xlpm.party, SUMIFS(ledger!J:J, ledger!B:B, _xlpm.party, ledger!E:E, "<>*RD*", ledger!D:D, "Satin", ledger!C:C, "<>October Closing CF") ))+ _xlfn.IFNA(J92, 0)} -> 0 | Z13: {=_xlfn.BYROW(B57, _xlfn.LAMBDA(_xlpm.party, SUMIFS(ledger!J:J, ledger!B:B, _xlpm.party, ledger!E:E, "<>*RD*", ledger!D:D, "Black-Chamki", ledger!C:C, "<>October Closing CF") ))} -> 0 | AA13: {=_xlfn.BYROW(B57, _xlfn.LAMBDA(_xlpm.party, SUMIFS(ledger!J:J, ledger!B:B, _xlpm.party, ledger!E:E, "<>*RD*", ledger!D:D, "Kataan", ledger!C:C, "<>October Closing CF") ))} -> 0 | AB13: =V13+W13+X13+Y13+Z13+AA13 -> 641274.69 | AC13: =(SUMIF(Table14[Party],Q13,Table14[Credit]))+_xlfn.IFNA(L92,0) -> 640190 | AD13: =AB13-AC13 -> 1084.6891 | AE13: 10 | AF13: 13
B14: =B61 -> Reject | C14: =SUMIFS(ledger!G:G, ledger!B:B, B14, ledger!E:E, "<>*RD*") / 1.0936 -> 0 | E14: =(SUMIFS(ledger!G:G, ledger!B:B, B14, ledger!E:E, "<>*RD*",ledger!D:D, "Silky") / 1.0936)*12 + (SUMIFS(ledger!G:G, ledger!B:B, B14, ledger!E:E, "<>*RD*",ledger!D:D, "Chamki") / 1.0936)*10 -> 0 | Q14: Ashraf Zia | R14: {=_xlfn.BYROW(B58,_xlfn.LAMBDA(_xlpm.party,SUMIFS(ledger!G:G,ledger!B:B,_xlpm.party,ledger!E:E,"<>*RD*")))+_xlfn.IFNA(C93,0)} -> 23305 | S14: {=_xlfn.BYROW(B58, _xlfn.LAMBDA(_xlpm.party, SUMIFS(ledger!G:G, ledger!B:B, _xlpm.party, ledger!E:E, "<>*RD*") / 1.0936 ))+_xlfn.IFNA(D93,0)} -> 21310.351 | T14: {=(_xlfn.BYROW(B58,_xlfn.LAMBDA(_xlpm.party,SUMIFS(ledger!G:G,ledger!B:B,_xlpm.party,ledger!E:E,"<>*RD*",ledger!D:D,"Chamki")+SUMIFS(ledger!G:G, ledger!B:B, _xlpm.party, ledger!E:E, "<>*RD*", ledger!D:D, "Crinkle")))/1.0936)+_xlfn.IFNA(E93,0)} -> 21310.351 | U14: {=(_xlfn.BYROW(B58,_xlfn.LAMBDA(_xlpm.party,SUMIFS(ledger!G:G,ledger!B:B,_xlpm.party,ledger!E:E,"<>*RD*",ledger!D:D,"Silky")))/1.0936)+_xlfn.IFNA(F93,0)} -> 0 | V14: {=(_xlfn.BYROW(B58,_xlfn.LAMBDA(_xlpm.party, (SUMIFS(ledger!J:J,ledger!B:B,_xlpm.party,ledger!E:E,"<>*RD*",ledger!D:D,"Chamki",ledger!C:C,"<>October Closing CF")+ SUMIFS(ledger!J:J,ledger!B:B,_xlpm.party,ledger!E:E,"<>*RD*",ledger!D:D,"Crinkle",ledger!C:C,"<>October Closing CF") )+_xlfn.IFNA(G93,0))))} -> 255724.21 | W14: {=_xlfn.BYROW(B58, _xlfn.LAMBDA(_xlpm.party, SUMIFS(ledger!J:J, ledger!B:B, _xlpm.party, ledger!E:E, "<>*RD*", ledger!D:D, "Silky", ledger!C:C, "<>October Closing CF") )) + _xlfn.IFNA(H93, 0)} -> 0 | X14: {=_xlfn.BYROW(B58, _xlfn.LAMBDA(_xlpm.party, SUMIFS(ledger!J:J, ledger!B:B, _xlpm.party, ledger!E:E, "<>*RD*", ledger!D:D, "Slub", ledger!C:C, "<>October Closing CF") ))+ _xlfn.IFNA(I93, 0)} -> 0 | Y14: {=_xlfn.BYROW(B58, _xlfn.LAMBDA(_xlpm.party, SUMIFS(ledger!J:J, ledger!B:B, _xlpm.party, ledger!E:E, "<>*RD*", ledger!D:D, "Satin", ledger!C:C, "<>October Closing CF") ))+ _xlfn.IFNA(J93, 0)} -> 0 | Z14: {=_xlfn.BYROW(B58, _xlfn.LAMBDA(_xlpm.party, SUMIFS(ledger!J:J, ledger!B:B, _xlpm.party, ledger!E:E, "<>*RD*", ledger!D:D, "Black-Chamki", ledger!C:C, "<>October Closing CF") ))} -> 0 | AA14: {=_xlfn.BYROW(B58, _xlfn.LAMBDA(_xlpm.party, SUMIFS(ledger!J:J, ledger!B:B, _xlpm.party, ledger!E:E, "<>*RD*", ledger!D:D, "Kataan", ledger!C:C, "<>October Closing CF") ))} -> 0 | AB14: =V14+W14+X14+Y14+Z14+AA14 -> 255724.21 | AC14: =(SUMIF(Table14[Party],Q14,Table14[Credit]))+_xlfn.IFNA(L93,0) -> 130000 | AD14: =AB14-AC14 -> 125724.21 | AE14: 12 | AF14: 13
B15: =B62 -> Amjad 7up | C15: =SUMIFS(ledger!G:G, ledger!B:B, B15, ledger!E:E, "<>*RD*") / 1.0936 -> 0 | E15: =(SUMIFS(ledger!G:G, ledger!B:B, B15, ledger!E:E, "<>*RD*",ledger!D:D, "Silky") / 1.0936)*12 + (SUMIFS(ledger!G:G, ledger!B:B, B15, ledger!E:E, "<>*RD*",ledger!D:D, "Chamki") / 1.0936)*10 -> 0 | Q15: Hafiz Qureshi | R15: {=_xlfn.BYROW(B59,_xlfn.LAMBDA(_xlpm.party,SUMIFS(ledger!G:G,ledger!B:B,_xlpm.party,ledger!E:E,"<>*RD*")))+_xlfn.IFNA(C94,0)} -> 202815 | S15: {=_xlfn.BYROW(B59, _xlfn.LAMBDA(_xlpm.party, SUMIFS(ledger!G:G, ledger!B:B, _xlpm.party, ledger!E:E, "<>*RD*") / 1.0936 ))+_xlfn.IFNA(D94,0)} -> 185456.29 | T15: {=(_xlfn.BYROW(B59,_xlfn.LAMBDA(_xlpm.party,SUMIFS(ledger!G:G,ledger!B:B,_xlpm.party,ledger!E:E,"<>*RD*",ledger!D:D,"Chamki")+SUMIFS(ledger!G:G, ledger!B:B, _xlpm.party, ledger!E:E, "<>*RD*", ledger!D:D, "Crinkle")))/1.0936)+_xlfn.IFNA(E94,0)} -> 185456.29 | U15: {=(_xlfn.BYROW(B59,_xlfn.LAMBDA(_xlpm.party,SUMIFS(ledger!G:G,ledger!B:B,_xlpm.party,ledger!E:E,"<>*RD*",ledger!D:D,"Silky")))/1.0936)+_xlfn.IFNA(F94,0)} -> 0 | V15: {=(_xlfn.BYROW(B59,_xlfn.LAMBDA(_xlpm.party, (SUMIFS(ledger!J:J,ledger!B:B,_xlpm.party,ledger!E:E,"<>*RD*",ledger!D:D,"Chamki",ledger!C:C,"<>October Closing CF")+ SUMIFS(ledger!J:J,ledger!B:B,_xlpm.party,ledger!E:E,"<>*RD*",ledger!D:D,"Crinkle",ledger!C:C,"<>October Closing CF") )+_xlfn.IFNA(G94,0))))} -> 1854562.9 | W15: {=_xlfn.BYROW(B59, _xlfn.LAMBDA(_xlpm.party, SUMIFS(ledger!J:J, ledger!B:B, _xlpm.party, ledger!E:E, "<>*RD*", ledger!D:D, "Silky", ledger!C:C, "<>October Closing CF") )) + _xlfn.IFNA(H94, 0)} -> 0 | X15: {=_xlfn.BYROW(B59, _xlfn.LAMBDA(_xlpm.party, SUMIFS(ledger!J:J, ledger!B:B, _xlpm.party, ledger!E:E, "<>*RD*", ledger!D:D, "Slub", ledger!C:C, "<>October Closing CF") ))+ _xlfn.IFNA(I94, 0)} -> 0 | Y15: {=_xlfn.BYROW(B59, _xlfn.LAMBDA(_xlpm.party, SUMIFS(ledger!J:J, ledger!B:B, _xlpm.party, ledger!E:E, "<>*RD*", ledger!D:D, "Satin", ledger!C:C, "<>October Closing CF") ))+ _xlfn.IFNA(J94, 0)} -> 0 | Z15: {=_xlfn.BYROW(B59, _xlfn.LAMBDA(_xlpm.party, SUMIFS(ledger!J:J, ledger!B:B, _xlpm.party, ledger!E:E, "<>*RD*", ledger!D:D, "Black-Chamki", ledger!C:C, "<>October Closing CF") ))} -> 0 | AA15: {=_xlfn.BYROW(B59, _xlfn.LAMBDA(_xlpm.party, SUMIFS(ledger!J:J, ledger!B:B, _xlpm.party, ledger!E:E, "<>*RD*", ledger!D:D, "Kataan", ledger!C:C, "<>October Closing CF") ))} -> 0 | AB15: =V15+W15+X15+Y15+Z15+AA15 -> 1854562.9 | AC15: =(SUMIF(Table14[Party],Q15,Table14[Credit]))+_xlfn.IFNA(L94,0) -> 1805980 | AD15: =AB15-AC15 -> 48582.911 | AE15: 10 | AF15: 13
B16: =B63 -> Hazrat Khan | C16: =SUMIFS(ledger!G:G, ledger!B:B, B16, ledger!E:E, "<>*RD*") / 1.0936 -> 0 | E16: =(SUMIFS(ledger!G:G, ledger!B:B, B16, ledger!E:E, "<>*RD*",ledger!D:D, "Silky") / 1.0936)*12 + (SUMIFS(ledger!G:G, ledger!B:B, B16, ledger!E:E, "<>*RD*",ledger!D:D, "Chamki") / 1.0936)*10 -> 0 | Q16: Badshah Fabrics | R16: {=_xlfn.BYROW(B60,_xlfn.LAMBDA(_xlpm.party,SUMIFS(ledger!G:G,ledger!B:B,_xlpm.party,ledger!E:E,"<>*RD*")))+_xlfn.IFNA(C95,0)} -> 517408 | S16: {=_xlfn.BYROW(B60, _xlfn.LAMBDA(_xlpm.party, SUMIFS(ledger!G:G, ledger!B:B, _xlpm.party, ledger!E:E, "<>*RD*") / 1.0936 ))+_xlfn.IFNA(D95,0)} -> 473123.63 | T16: {=(_xlfn.BYROW(B60,_xlfn.LAMBDA(_xlpm.party,SUMIFS(ledger!G:G,ledger!B:B,_xlpm.party,ledger!E:E,"<>*RD*",ledger!D:D,"Chamki")+SUMIFS(ledger!G:G, ledger!B:B, _xlpm.party, ledger!E:E, "<>*RD*", ledger!D:D, "Crinkle")))/1.0936)+_xlfn.IFNA(E95,0)} -> 355909.84 | U16: {=(_xlfn.BYROW(B60,_xlfn.LAMBDA(_xlpm.party,SUMIFS(ledger!G:G,ledger!B:B,_xlpm.party,ledger!E:E,"<>*RD*",ledger!D:D,"Silky")))/1.0936)+_xlfn.IFNA(F95,0)} -> 117213.79 | V16: {=(_xlfn.BYROW(B60,_xlfn.LAMBDA(_xlpm.party, (SUMIFS(ledger!J:J,ledger!B:B,_xlpm.party,ledger!E:E,"<>*RD*",ledger!D:D,"Chamki",ledger!C:C,"<>October Closing CF")+ SUMIFS(ledger!J:J,ledger!B:B,_xlpm.party,ledger!E:E,"<>*RD*",ledger!D:D,"Crinkle",ledger!C:C,"<>October Closing CF") )+_xlfn.IFNA(G95,0))))} -> 3559098.4 | W16: {=_xlfn.BYROW(B60, _xlfn.LAMBDA(_xlpm.party, SUMIFS(ledger!J:J, ledger!B:B, _xlpm.party, ledger!E:E, "<>*RD*", ledger!D:D, "Silky", ledger!C:C, "<>October Closing CF") )) + _xlfn.IFNA(H95, 0)} -> 1460624.5 | X16: {=_xlfn.BYROW(B60, _xlfn.LAMBDA(_xlpm.party, SUMIFS(ledger!J:J, ledger!B:B, _xlpm.party, ledger!E:E, "<>*RD*", ledger!D:D, "Slub", ledger!C:C, "<>October Closing CF") ))+ _xlfn.IFNA(I95, 0)} -> 0 | Y16: {=_xlfn.BYROW(B60, _xlfn.LAMBDA(_xlpm.party, SUMIFS(ledger!J:J, ledger!B:B, _xlpm.party, ledger!E:E, "<>*RD*", ledger!D:D, "Satin", ledger!C:C, "<>October Closing CF") ))+ _xlfn.IFNA(J95, 0)} -> 0 | Z16: {=_xlfn.BYROW(B60, _xlfn.LAMBDA(_xlpm.party, SUMIFS(ledger!J:J, ledger!B:B, _xlpm.party, ledger!E:E, "<>*RD*", ledger!D:D, "Black-Chamki", ledger!C:C, "<>October Closing CF") ))} -> 0 | AA16: {=_xlfn.BYROW(B60, _xlfn.LAMBDA(_xlpm.party, SUMIFS(ledger!J:J, ledger!B:B, _xlpm.party, ledger!E:E, "<>*RD*", ledger!D:D, "Kataan", ledger!C:C, "<>October Closing CF") ))} -> 0 | AB16: =V16+W16+X16+Y16+Z16+AA16 -> 5019722.9 | AC16: =(SUMIF(Table14[Party],Q16,Table14[Credit]))+_xlfn.IFNA(L95,0) -> 4925761 | AD16: =AB16-AC16 -> 93961.933 | AE16: 10 | AF16: 13
B17: =B64 -> Haseeb Shamsi | C17: =SUMIFS(ledger!G:G, ledger!B:B, B17, ledger!E:E, "<>*RD*") / 1.0936 -> 0 | E17: =(SUMIFS(ledger!G:G, ledger!B:B, B17, ledger!E:E, "<>*RD*",ledger!D:D, "Silky") / 1.0936)*12 + (SUMIFS(ledger!G:G, ledger!B:B, B17, ledger!E:E, "<>*RD*",ledger!D:D, "Chamki") / 1.0936)*10 -> 0 | Q17: Reject | R17: {=_xlfn.BYROW(B61,_xlfn.LAMBDA(_xlpm.party,SUMIFS(ledger!G:G,ledger!B:B,_xlpm.party,ledger!E:E,"<>*RD*")))+_xlfn.IFNA(C96,0)} -> 0 | S17: {=_xlfn.BYROW(B61, _xlfn.LAMBDA(_xlpm.party, SUMIFS(ledger!G:G, ledger!B:B, _xlpm.party, ledger!E:E, "<>*RD*") / 1.0936 ))+_xlfn.IFNA(D96,0)} -> 0 | T17: {=(_xlfn.BYROW(B61,_xlfn.LAMBDA(_xlpm.party,SUMIFS(ledger!G:G,ledger!B:B,_xlpm.party,ledger!E:E,"<>*RD*",ledger!D:D,"Chamki")+SUMIFS(ledger!G:G, ledger!B:B, _xlpm.party, ledger!E:E, "<>*RD*", ledger!D:D, "Crinkle")))/1.0936)+_xlfn.IFNA(E96,0)} -> 0 | U17: {=(_xlfn.BYROW(B61,_xlfn.LAMBDA(_xlpm.party,SUMIFS(ledger!G:G,ledger!B:B,_xlpm.party,ledger!E:E,"<>*RD*",ledger!D:D,"Silky")))/1.0936)+_xlfn.IFNA(F96,0)} -> 0 | V17: {=(_xlfn.BYROW(B61,_xlfn.LAMBDA(_xlpm.party, (SUMIFS(ledger!J:J,ledger!B:B,_xlpm.party,ledger!E:E,"<>*RD*",ledger!D:D,"Chamki",ledger!C:C,"<>October Closing CF")+ SUMIFS(ledger!J:J,ledger!B:B,_xlpm.party,ledger!E:E,"<>*RD*",ledger!D:D,"Crinkle",ledger!C:C,"<>October Closing CF") )+_xlfn.IFNA(G96,0))))} -> 0 | W17: {=_xlfn.BYROW(B61, _xlfn.LAMBDA(_xlpm.party, SUMIFS(ledger!J:J, ledger!B:B, _xlpm.party, ledger!E:E, "<>*RD*", ledger!D:D, "Silky", ledger!C:C, "<>October Closing CF") )) + _xlfn.IFNA(H96, 0)} -> 0 | X17: {=_xlfn.BYROW(B61, _xlfn.LAMBDA(_xlpm.party, SUMIFS(ledger!J:J, ledger!B:B, _xlpm.party, ledger!E:E, "<>*RD*", ledger!D:D, "Slub", ledger!C:C, "<>October Closing CF") ))+ _xlfn.IFNA(I96, 0)} -> 0 | Y17: {=_xlfn.BYROW(B61, _xlfn.LAMBDA(_xlpm.party, SUMIFS(ledger!J:J, ledger!B:B, _xlpm.party, ledger!E:E, "<>*RD*", ledger!D:D, "Satin", ledger!C:C, "<>October Closing CF") ))+ _xlfn.IFNA(J96, 0)} -> 0 | Z17: {=_xlfn.BYROW(B61, _xlfn.LAMBDA(_xlpm.party, SUMIFS(ledger!J:J, ledger!B:B, _xlpm.party, ledger!E:E, "<>*RD*", ledger!D:D, "Black-Chamki", ledger!C:C, "<>October Closing CF") ))} -> 0 | AA17: {=_xlfn.BYROW(B61, _xlfn.LAMBDA(_xlpm.party, SUMIFS(ledger!J:J, ledger!B:B, _xlpm.party, ledger!E:E, "<>*RD*", ledger!D:D, "Kataan", ledger!C:C, "<>October Closing CF") ))} -> 0 | AB17: =V17+W17+X17+Y17+Z17+AA17 -> 0 | AC17: =(SUMIF(Table14[Party],Q17,Table14[Credit]))+_xlfn.IFNA(L96,0) -> 0 | AD17: =AB17-AC17 -> 0 | AE17: 10 | AF17: 13
B18: =B65 -> Faizan | C18: =SUMIFS(ledger!G:G, ledger!B:B, B18, ledger!E:E, "<>*RD*") / 1.0936 -> 198235.19 | E18: =(SUMIFS(ledger!G:G, ledger!B:B, B18, ledger!E:E, "<>*RD*",ledger!D:D, "Silky") / 1.0936)*12 + (SUMIFS(ledger!G:G, ledger!B:B, B18, ledger!E:E, "<>*RD*",ledger!D:D, "Chamki") / 1.0936)*10 -> 2378822.2 | Q18: Amjad 7up | R18: {=_xlfn.BYROW(B62,_xlfn.LAMBDA(_xlpm.party,SUMIFS(ledger!G:G,ledger!B:B,_xlpm.party,ledger!E:E,"<>*RD*")))+_xlfn.IFNA(C97,0)} -> 52914 | S18: {=_xlfn.BYROW(B62, _xlfn.LAMBDA(_xlpm.party, SUMIFS(ledger!G:G, ledger!B:B, _xlpm.party, ledger!E:E, "<>*RD*") / 1.0936 ))+_xlfn.IFNA(D97,0)} -> 48385.15 | T18: {=(_xlfn.BYROW(B62,_xlfn.LAMBDA(_xlpm.party,SUMIFS(ledger!G:G,ledger!B:B,_xlpm.party,ledger!E:E,"<>*RD*",ledger!D:D,"Chamki")+SUMIFS(ledger!G:G, ledger!B:B, _xlpm.party, ledger!E:E, "<>*RD*", ledger!D:D, "Crinkle")))/1.0936)+_xlfn.IFNA(E97,0)} -> 48385.15 | U18: {=(_xlfn.BYROW(B62,_xlfn.LAMBDA(_xlpm.party,SUMIFS(ledger!G:G,ledger!B:B,_xlpm.party,ledger!E:E,"<>*RD*",ledger!D:D,"Silky")))/1.0936)+_xlfn.IFNA(F97,0)} -> 0 | V18: {=(_xlfn.BYROW(B62,_xlfn.LAMBDA(_xlpm.party, (SUMIFS(ledger!J:J,ledger!B:B,_xlpm.party,ledger!E:E,"<>*RD*",ledger!D:D,"Chamki",ledger!C:C,"<>October Closing CF")+ SUMIFS(ledger!J:J,ledger!B:B,_xlpm.party,ledger!E:E,"<>*RD*",ledger!D:D,"Crinkle",ledger!C:C,"<>October Closing CF") )+_xlfn.IFNA(G97,0))))} -> 483851.5 | W18: {=_xlfn.BYROW(B62, _xlfn.LAMBDA(_xlpm.party, SUMIFS(ledger!J:J, ledger!B:B, _xlpm.party, ledger!E:E, "<>*RD*", ledger!D:D, "Silky", ledger!C:C, "<>October Closing CF") )) + _xlfn.IFNA(H97, 0)} -> 0 | X18: {=_xlfn.BYROW(B62, _xlfn.LAMBDA(_xlpm.party, SUMIFS(ledger!J:J, ledger!B:B, _xlpm.party, ledger!E:E, "<>*RD*", ledger!D:D, "Slub", ledger!C:C, "<>October Closing CF") ))+ _xlfn.IFNA(I97, 0)} -> 0 | Y18: {=_xlfn.BYROW(B62, _xlfn.LAMBDA(_xlpm.party, SUMIFS(ledger!J:J, ledger!B:B, _xlpm.party, ledger!E:E, "<>*RD*", ledger!D:D, "Satin", ledger!C:C, "<>October Closing CF") ))+ _xlfn.IFNA(J97, 0)} -> 0 | Z18: {=_xlfn.BYROW(B62, _xlfn.LAMBDA(_xlpm.party, SUMIFS(ledger!J:J, ledger!B:B, _xlpm.party, ledger!E:E, "<>*RD*", ledger!D:D, "Black-Chamki", ledger!C:C, "<>October Closing CF") ))} -> 0 | AA18: {=_xlfn.BYROW(B62, _xlfn.LAMBDA(_xlpm.party, SUMIFS(ledger!J:J, ledger!B:B, _xlpm.party, ledger!E:E, "<>*RD*", ledger!D:D, "Kataan", ledger!C:C, "<>October Closing CF") ))} -> 0 | AB18: =V18+W18+X18+Y18+Z18+AA18 -> 483851.5 | AC18: =(SUMIF(Table14[Party],Q18,Table14[Credit]))+_xlfn.IFNA(L97,0) -> 480000 | AD18: =AB18-AC18 -> 3851.4996 | AE18: 10 | AF18: 13
Q19: Hazrat Khan | R19: {=_xlfn.BYROW(B63,_xlfn.LAMBDA(_xlpm.party,SUMIFS(ledger!G:G,ledger!B:B,_xlpm.party,ledger!E:E,"<>*RD*")))+_xlfn.IFNA(C98,0)} -> 9750 | S19: {=_xlfn.BYROW(B63, _xlfn.LAMBDA(_xlpm.party, SUMIFS(ledger!G:G, ledger!B:B, _xlpm.party, ledger!E:E, "<>*RD*") / 1.0936 ))+_xlfn.IFNA(D98,0)} -> 8915.5084 | T19: {=(_xlfn.BYROW(B63,_xlfn.LAMBDA(_xlpm.party,SUMIFS(ledger!G:G,ledger!B:B,_xlpm.party,ledger!E:E,"<>*RD*",ledger!D:D,"Chamki")+SUMIFS(ledger!G:G, ledger!B:B, _xlpm.party, ledger!E:E, "<>*RD*", ledger!D:D, "Crinkle")))/1.0936)+_xlfn.IFNA(E98,0)} -> 8915.5084 | U19: {=(_xlfn.BYROW(B63,_xlfn.LAMBDA(_xlpm.party,SUMIFS(ledger!G:G,ledger!B:B,_xlpm.party,ledger!E:E,"<>*RD*",ledger!D:D,"Silky")))/1.0936)+_xlfn.IFNA(F98,0)} -> 0 | V19: {=(_xlfn.BYROW(B63,_xlfn.LAMBDA(_xlpm.party, (SUMIFS(ledger!J:J,ledger!B:B,_xlpm.party,ledger!E:E,"<>*RD*",ledger!D:D,"Chamki",ledger!C:C,"<>October Closing CF")+ SUMIFS(ledger!J:J,ledger!B:B,_xlpm.party,ledger!E:E,"<>*RD*",ledger!D:D,"Crinkle",ledger!C:C,"<>October Closing CF") )+_xlfn.IFNA(G98,0))))} -> 89155.084 | W19: {=_xlfn.BYROW(B63, _xlfn.LAMBDA(_xlpm.party, SUMIFS(ledger!J:J, ledger!B:B, _xlpm.party, ledger!E:E, "<>*RD*", ledger!D:D, "Silky", ledger!C:C, "<>October Closing CF") )) + _xlfn.IFNA(H98, 0)} -> 0 | X19: {=_xlfn.BYROW(B63, _xlfn.LAMBDA(_xlpm.party, SUMIFS(ledger!J:J, ledger!B:B, _xlpm.party, ledger!E:E, "<>*RD*", ledger!D:D, "Slub", ledger!C:C, "<>October Closing CF") ))+ _xlfn.IFNA(I98, 0)} -> 0 | Y19: {=_xlfn.BYROW(B63, _xlfn.LAMBDA(_xlpm.party, SUMIFS(ledger!J:J, ledger!B:B, _xlpm.party, ledger!E:E, "<>*RD*", ledger!D:D, "Satin", ledger!C:C, "<>October Closing CF") ))+ _xlfn.IFNA(J98, 0)} -> 0 | Z19: {=_xlfn.BYROW(B63, _xlfn.LAMBDA(_xlpm.party, SUMIFS(ledger!J:J, ledger!B:B, _xlpm.party, ledger!E:E, "<>*RD*", ledger!D:D, "Black-Chamki", ledger!C:C, "<>October Closing CF") ))} -> 0 | AA19: {=_xlfn.BYROW(B63, _xlfn.LAMBDA(_xlpm.party, SUMIFS(ledger!J:J, ledger!B:B, _xlpm.party, ledger!E:E, "<>*RD*", ledger!D:D, "Kataan", ledger!C:C, "<>October Closing CF") ))} -> 0 | AB19: =V19+W19+X19+Y19+Z19+AA19 -> 89155.084 | AC19: =(SUMIF(Table14[Party],Q19,Table14[Credit]))+_xlfn.IFNA(L98,0) -> 95000 | AD19: =AB19-AC19 -> -5844.9159 | AE19: 10 | AF19: 13
Q20: Haseeb Shamsi | R20: {=_xlfn.BYROW(B64,_xlfn.LAMBDA(_xlpm.party,SUMIFS(ledger!G:G,ledger!B:B,_xlpm.party,ledger!E:E,"<>*RD*")))+_xlfn.IFNA(C99,0)} -> 61975 | S20: {=_xlfn.BYROW(B64, _xlfn.LAMBDA(_xlpm.party, SUMIFS(ledger!G:G, ledger!B:B, _xlpm.party, ledger!E:E, "<>*RD*") / 1.0936 ))+_xlfn.IFNA(D99,0)} -> 56670.629 | T20: {=(_xlfn.BYROW(B64,_xlfn.LAMBDA(_xlpm.party,SUMIFS(ledger!G:G,ledger!B:B,_xlpm.party,ledger!E:E,"<>*RD*",ledger!D:D,"Chamki")+SUMIFS(ledger!G:G, ledger!B:B, _xlpm.party, ledger!E:E, "<>*RD*", ledger!D:D, "Crinkle")))/1.0936)+_xlfn.IFNA(E99,0)} -> 47437.82 | U20: {=(_xlfn.BYROW(B64,_xlfn.LAMBDA(_xlpm.party,SUMIFS(ledger!G:G,ledger!B:B,_xlpm.party,ledger!E:E,"<>*RD*",ledger!D:D,"Silky")))/1.0936)+_xlfn.IFNA(F99,0)} -> 9232.8091 | V20: {=(_xlfn.BYROW(B64,_xlfn.LAMBDA(_xlpm.party, (SUMIFS(ledger!J:J,ledger!B:B,_xlpm.party,ledger!E:E,"<>*RD*",ledger!D:D,"Chamki",ledger!C:C,"<>October Closing CF")+ SUMIFS(ledger!J:J,ledger!B:B,_xlpm.party,ledger!E:E,"<>*RD*",ledger!D:D,"Crinkle",ledger!C:C,"<>October Closing CF") )+_xlfn.IFNA(G99,0))))} -> 474378.2 | W20: {=_xlfn.BYROW(B64, _xlfn.LAMBDA(_xlpm.party, SUMIFS(ledger!J:J, ledger!B:B, _xlpm.party, ledger!E:E, "<>*RD*", ledger!D:D, "Silky", ledger!C:C, "<>October Closing CF") )) + _xlfn.IFNA(H99, 0)} -> 120026.52 | X20: {=_xlfn.BYROW(B64, _xlfn.LAMBDA(_xlpm.party, SUMIFS(ledger!J:J, ledger!B:B, _xlpm.party, ledger!E:E, "<>*RD*", ledger!D:D, "Slub", ledger!C:C, "<>October Closing CF") ))+ _xlfn.IFNA(I99, 0)} -> 0 | Y20: {=_xlfn.BYROW(B64, _xlfn.LAMBDA(_xlpm.party, SUMIFS(ledger!J:J, ledger!B:B, _xlpm.party, ledger!E:E, "<>*RD*", ledger!D:D, "Satin", ledger!C:C, "<>October Closing CF") ))+ _xlfn.IFNA(J99, 0)} -> 0 | Z20: {=_xlfn.BYROW(B64, _xlfn.LAMBDA(_xlpm.party, SUMIFS(ledger!J:J, ledger!B:B, _xlpm.party, ledger!E:E, "<>*RD*", ledger!D:D, "Black-Chamki", ledger!C:C, "<>October Closing CF") ))} -> 0 | AA20: {=_xlfn.BYROW(B64, _xlfn.LAMBDA(_xlpm.party, SUMIFS(ledger!J:J, ledger!B:B, _xlpm.party, ledger!E:E, "<>*RD*", ledger!D:D, "Kataan", ledger!C:C, "<>October Closing CF") ))} -> 0 | AB20: =V20+W20+X20+Y20+Z20+AA20 -> 594404.72 | AC20: =(SUMIF(Table14[Party],Q20,Table14[Credit]))+_xlfn.IFNA(L99,0) -> 594405 | AD20: =AB20-AC20 -> -0.28163862 | AE20: 10 | AF20: 13
B21: Total: | C21: =SUM(K49:K78) -> 18025314 | D21: (Real Figure) | Q21: Faizan | R21: {=_xlfn.BYROW(B65,_xlfn.LAMBDA(_xlpm.party,SUMIFS(ledger!G:G,ledger!B:B,_xlpm.party,ledger!E:E,"<>*RD*")))+_xlfn.IFNA(C100,0)} -> 438975 | S21: {=_xlfn.BYROW(B65, _xlfn.LAMBDA(_xlpm.party, SUMIFS(ledger!G:G, ledger!B:B, _xlpm.party, ledger!E:E, "<>*RD*") / 1.0936 ))+_xlfn.IFNA(D100,0)} -> 401403.62 | T21: {=(_xlfn.BYROW(B65,_xlfn.LAMBDA(_xlpm.party,SUMIFS(ledger!G:G,ledger!B:B,_xlpm.party,ledger!E:E,"<>*RD*",ledger!D:D,"Chamki")+SUMIFS(ledger!G:G, ledger!B:B, _xlpm.party, ledger!E:E, "<>*RD*", ledger!D:D, "Crinkle")))/1.0936)+_xlfn.IFNA(E100,0)} -> 0 | U21: {=(_xlfn.BYROW(B65,_xlfn.LAMBDA(_xlpm.party,SUMIFS(ledger!G:G,ledger!B:B,_xlpm.party,ledger!E:E,"<>*RD*",ledger!D:D,"Silky")))/1.0936)+_xlfn.IFNA(F100,0)} -> 398433.61 | V21: {=(_xlfn.BYROW(B65,_xlfn.LAMBDA(_xlpm.party, (SUMIFS(ledger!J:J,ledger!B:B,_xlpm.party,ledger!E:E,"<>*RD*",ledger!D:D,"Chamki",ledger!C:C,"<>October Closing CF")+ SUMIFS(ledger!J:J,ledger!B:B,_xlpm.party,ledger!E:E,"<>*RD*",ledger!D:D,"Crinkle",ledger!C:C,"<>October Closing CF") )+_xlfn.IFNA(G100,0))))} -> 0 | W21: {=_xlfn.BYROW(B65, _xlfn.LAMBDA(_xlpm.party, SUMIFS(ledger!J:J, ledger!B:B, _xlpm.party, ledger!E:E, "<>*RD*", ledger!D:D, "Silky", ledger!C:C, "<>October Closing CF") )) + _xlfn.IFNA(H100, 0)} -> 5179637 | X21: {=_xlfn.BYROW(B65, _xlfn.LAMBDA(_xlpm.party, SUMIFS(ledger!J:J, ledger!B:B, _xlpm.party, ledger!E:E, "<>*RD*", ledger!D:D, "Slub", ledger!C:C, "<>October Closing CF") ))+ _xlfn.IFNA(I100, 0)} -> 44550.11 | Y21: {=_xlfn.BYROW(B65, _xlfn.LAMBDA(_xlpm.party, SUMIFS(ledger!J:J, ledger!B:B, _xlpm.party, ledger!E:E, "<>*RD*", ledger!D:D, "Satin", ledger!C:C, "<>October Closing CF") ))+ _xlfn.IFNA(J100, 0)} -> 0 | Z21: {=_xlfn.BYROW(B65, _xlfn.LAMBDA(_xlpm.party, SUMIFS(ledger!J:J, ledger!B:B, _xlpm.party, ledger!E:E, "<>*RD*", ledger!D:D, "Black-Chamki", ledger!C:C, "<>October Closing CF") ))} -> 0 | AA21: {=_xlfn.BYROW(B65, _xlfn.LAMBDA(_xlpm.party, SUMIFS(ledger!J:J, ledger!B:B, _xlpm.party, ledger!E:E, "<>*RD*", ledger!D:D, "Kataan", ledger!C:C, "<>October Closing CF") ))} -> 0 | AB21: =V21+W21+X21+Y21+Z21+AA21 -> 5224187.1 | AC21: =(SUMIF(Table14[Party],Q21,Table14[Credit]))+_xlfn.IFNA(L100,0) -> 4915571 | AD21: =AB21-AC21 -> 308616.09 | AE21: 10 | AF21: 13
Q22: Shafique Ansari | R22: {=_xlfn.BYROW(B66,_xlfn.LAMBDA(_xlpm.party,SUMIFS(ledger!G:G,ledger!B:B,_xlpm.party,ledger!E:E,"<>*RD*")))+_xlfn.IFNA(C101,0)} -> 82290 | S22: {=_xlfn.BYROW(B66, _xlfn.LAMBDA(_xlpm.party, SUMIFS(ledger!G:G, ledger!B:B, _xlpm.party, ledger!E:E, "<>*RD*") / 1.0936 ))+_xlfn.IFNA(D101,0)} -> 75246.891 | T22: {=(_xlfn.BYROW(B66,_xlfn.LAMBDA(_xlpm.party,SUMIFS(ledger!G:G,ledger!B:B,_xlpm.party,ledger!E:E,"<>*RD*",ledger!D:D,"Chamki")+SUMIFS(ledger!G:G, ledger!B:B, _xlpm.party, ledger!E:E, "<>*RD*", ledger!D:D, "Crinkle")))/1.0936)+_xlfn.IFNA(E101,0)} -> 64300.475 | U22: {=(_xlfn.BYROW(B66,_xlfn.LAMBDA(_xlpm.party,SUMIFS(ledger!G:G,ledger!B:B,_xlpm.party,ledger!E:E,"<>*RD*",ledger!D:D,"Silky")))/1.0936)+_xlfn.IFNA(F101,0)} -> 7565.8376 | V22: {=(_xlfn.BYROW(B66,_xlfn.LAMBDA(_xlpm.party, (SUMIFS(ledger!J:J,ledger!B:B,_xlpm.party,ledger!E:E,"<>*RD*",ledger!D:D,"Chamki",ledger!C:C,"<>October Closing CF")+ SUMIFS(ledger!J:J,ledger!B:B,_xlpm.party,ledger!E:E,"<>*RD*",ledger!D:D,"Crinkle",ledger!C:C,"<>October Closing CF") )+_xlfn.IFNA(G101,0))))} -> 643004.75 | W22: {=_xlfn.BYROW(B66, _xlfn.LAMBDA(_xlpm.party, SUMIFS(ledger!J:J, ledger!B:B, _xlpm.party, ledger!E:E, "<>*RD*", ledger!D:D, "Silky", ledger!C:C, "<>October Closing CF") )) + _xlfn.IFNA(H101, 0)} -> 98355.889 | X22: {=_xlfn.BYROW(B66, _xlfn.LAMBDA(_xlpm.party, SUMIFS(ledger!J:J, ledger!B:B, _xlpm.party, ledger!E:E, "<>*RD*", ledger!D:D, "Slub", ledger!C:C, "<>October Closing CF") ))+ _xlfn.IFNA(I101, 0)} -> 0 | Y22: {=_xlfn.BYROW(B66, _xlfn.LAMBDA(_xlpm.party, SUMIFS(ledger!J:J, ledger!B:B, _xlpm.party, ledger!E:E, "<>*RD*", ledger!D:D, "Satin", ledger!C:C, "<>October Closing CF") ))+ _xlfn.IFNA(J101, 0)} -> 94656.181 | Z22: {=_xlfn.BYROW(B66, _xlfn.LAMBDA(_xlpm.party, SUMIFS(ledger!J:J, ledger!B:B, _xlpm.party, ledger!E:E, "<>*RD*", ledger!D:D, "Black-Chamki", ledger!C:C, "<>October Closing CF") ))} -> 0 | AA22: {=_xlfn.BYROW(B66, _xlfn.LAMBDA(_xlpm.party, SUMIFS(ledger!J:J, ledger!B:B, _xlpm.party, ledger!E:E, "<>*RD*", ledger!D:D, "Kataan", ledger!C:C, "<>October Closing CF") ))} -> 0 | AB22: =V22+W22+X22+Y22+Z22+AA22 -> 836016.83 | AC22: =(SUMIF(Table14[Party],Q22,Table14[Credit]))+_xlfn.IFNA(L101,0) -> 835660 | AD22: =AB22-AC22 -> 356.82516 | AE22: 10 | AF22: 13
B23: Total influx | C23: =SUM(K49:K71) -> 17900753 | D23: (considering 10.5) | Q23: Amjad sohail | R23: {=_xlfn.BYROW(B67,_xlfn.LAMBDA(_xlpm.party,SUMIFS(ledger!G:G,ledger!B:B,_xlpm.party,ledger!E:E,"<>*RD*")))+_xlfn.IFNA(C102,0)} -> 281909 | S23: {=_xlfn.BYROW(B67, _xlfn.LAMBDA(_xlpm.party, SUMIFS(ledger!G:G, ledger!B:B, _xlpm.party, ledger!E:E, "<>*RD*") / 1.0936 ))+_xlfn.IFNA(D102,0)} -> 257780.72 | T23: {=(_xlfn.BYROW(B67,_xlfn.LAMBDA(_xlpm.party,SUMIFS(ledger!G:G,ledger!B:B,_xlpm.party,ledger!E:E,"<>*RD*",ledger!D:D,"Chamki")+SUMIFS(ledger!G:G, ledger!B:B, _xlpm.party, ledger!E:E, "<>*RD*", ledger!D:D, "Crinkle")))/1.0936)+_xlfn.IFNA(E102,0)} -> 213946.6 | U23: {=(_xlfn.BYROW(B67,_xlfn.LAMBDA(_xlpm.party,SUMIFS(ledger!G:G,ledger!B:B,_xlpm.party,ledger!E:E,"<>*RD*",ledger!D:D,"Silky")))/1.0936)+_xlfn.IFNA(F102,0)} -> 43834.126 | V23: {=(_xlfn.BYROW(B67,_xlfn.LAMBDA(_xlpm.party, (SUMIFS(ledger!J:J,ledger!B:B,_xlpm.party,ledger!E:E,"<>*RD*",ledger!D:D,"Chamki",ledger!C:C,"<>October Closing CF")+ SUMIFS(ledger!J:J,ledger!B:B,_xlpm.party,ledger!E:E,"<>*RD*",ledger!D:D,"Crinkle",ledger!C:C,"<>October Closing CF") )+_xlfn.IFNA(G102,0))))} -> 2139466 | W23: {=_xlfn.BYROW(B67, _xlfn.LAMBDA(_xlpm.party, SUMIFS(ledger!J:J, ledger!B:B, _xlpm.party, ledger!E:E, "<>*RD*", ledger!D:D, "Silky", ledger!C:C, "<>October Closing CF") )) + _xlfn.IFNA(H102, 0)} -> 569843.64 | X23: {=_xlfn.BYROW(B67, _xlfn.LAMBDA(_xlpm.party, SUMIFS(ledger!J:J, ledger!B:B, _xlpm.party, ledger!E:E, "<>*RD*", ledger!D:D, "Slub", ledger!C:C, "<>October Closing CF") ))+ _xlfn.IFNA(I102, 0)} -> 0 | Y23: {=_xlfn.BYROW(B67, _xlfn.LAMBDA(_xlpm.party, SUMIFS(ledger!J:J, ledger!B:B, _xlpm.party, ledger!E:E, "<>*RD*", ledger!D:D, "Satin", ledger!C:C, "<>October Closing CF") ))+ _xlfn.IFNA(J102, 0)} -> 0 | Z23: {=_xlfn.BYROW(B67, _xlfn.LAMBDA(_xlpm.party, SUMIFS(ledger!J:J, ledger!B:B, _xlpm.party, ledger!E:E, "<>*RD*", ledger!D:D, "Black-Chamki", ledger!C:C, "<>October Closing CF") ))} -> 0 | AA23: {=_xlfn.BYROW(B67, _xlfn.LAMBDA(_xlpm.party, SUMIFS(ledger!J:J, ledger!B:B, _xlpm.party, ledger!E:E, "<>*RD*", ledger!D:D, "Kataan", ledger!C:C, "<>October Closing CF") ))} -> 0 | AB23: =V23+W23+X23+Y23+Z23+AA23 -> 2709309.6 | AC23: =(SUMIF(Table14[Party],Q23,Table14[Credit]))+_xlfn.IFNA(L102,0) -> 2300000 | AD23: =AB23-AC23 -> 409309.62 | AE23: 10 | AF23: 13
Q24: Salman Zaffar | R24: {=_xlfn.BYROW(B68,_xlfn.LAMBDA(_xlpm.party,SUMIFS(ledger!G:G,ledger!B:B,_xlpm.party,ledger!E:E,"<>*RD*")))+_xlfn.IFNA(C103,0)} -> 55541 | S24: {=_xlfn.BYROW(B68, _xlfn.LAMBDA(_xlpm.party, SUMIFS(ledger!G:G, ledger!B:B, _xlpm.party, ledger!E:E, "<>*RD*") / 1.0936 ))+_xlfn.IFNA(D103,0)} -> 50787.308 | T24: {=(_xlfn.BYROW(B68,_xlfn.LAMBDA(_xlpm.party,SUMIFS(ledger!G:G,ledger!B:B,_xlpm.party,ledger!E:E,"<>*RD*",ledger!D:D,"Chamki")+SUMIFS(ledger!G:G, ledger!B:B, _xlpm.party, ledger!E:E, "<>*RD*", ledger!D:D, "Crinkle")))/1.0936)+_xlfn.IFNA(E103,0)} -> 14355.34 | U24: {=(_xlfn.BYROW(B68,_xlfn.LAMBDA(_xlpm.party,SUMIFS(ledger!G:G,ledger!B:B,_xlpm.party,ledger!E:E,"<>*RD*",ledger!D:D,"Silky")))/1.0936)+_xlfn.IFNA(F103,0)} -> 31409.108 | V24: {=(_xlfn.BYROW(B68,_xlfn.LAMBDA(_xlpm.party, (SUMIFS(ledger!J:J,ledger!B:B,_xlpm.party,ledger!E:E,"<>*RD*",ledger!D:D,"Chamki",ledger!C:C,"<>October Closing CF")+ SUMIFS(ledger!J:J,ledger!B:B,_xlpm.party,ledger!E:E,"<>*RD*",ledger!D:D,"Crinkle",ledger!C:C,"<>October Closing CF") )+_xlfn.IFNA(G103,0))))} -> 143553.4 | W24: {=_xlfn.BYROW(B68, _xlfn.LAMBDA(_xlpm.party, SUMIFS(ledger!J:J, ledger!B:B, _xlpm.party, ledger!E:E, "<>*RD*", ledger!D:D, "Silky", ledger!C:C, "<>October Closing CF") )) + _xlfn.IFNA(H103, 0)} -> 408318.4 | X24: {=_xlfn.BYROW(B68, _xlfn.LAMBDA(_xlpm.party, SUMIFS(ledger!J:J, ledger!B:B, _xlpm.party, ledger!E:E, "<>*RD*", ledger!D:D, "Slub", ledger!C:C, "<>October Closing CF") ))+ _xlfn.IFNA(I103, 0)} -> 0 | Y24: {=_xlfn.BYROW(B68, _xlfn.LAMBDA(_xlpm.party, SUMIFS(ledger!J:J, ledger!B:B, _xlpm.party, ledger!E:E, "<>*RD*", ledger!D:D, "Satin", ledger!C:C, "<>October Closing CF") ))+ _xlfn.IFNA(J103, 0)} -> 0 | Z24: {=_xlfn.BYROW(B68, _xlfn.LAMBDA(_xlpm.party, SUMIFS(ledger!J:J, ledger!B:B, _xlpm.party, ledger!E:E, "<>*RD*", ledger!D:D, "Black-Chamki", ledger!C:C, "<>October Closing CF") ))} -> 60274.323 | AA24: {=_xlfn.BYROW(B68, _xlfn.LAMBDA(_xlpm.party, SUMIFS(ledger!J:J, ledger!B:B, _xlpm.party, ledger!E:E, "<>*RD*", ledger!D:D, "Kataan", ledger!C:C, "<>October Closing CF") ))} -> 0 | AB24: =V24+W24+X24+Y24+Z24+AA24 -> 612146.12 | AC24: =(SUMIF(Table14[Party],Q24,Table14[Credit]))+_xlfn.IFNA(L103,0) -> 0 | AD24: =AB24-AC24 -> 612146.12 | AE24: 10 | AF24: 13
Q25: Shahid Qasayi | R25: {=_xlfn.BYROW(B69,_xlfn.LAMBDA(_xlpm.party,SUMIFS(ledger!G:G,ledger!B:B,_xlpm.party,ledger!E:E,"<>*RD*")))+_xlfn.IFNA(C104,0)} -> 165343 | S25: {=_xlfn.BYROW(B69, _xlfn.LAMBDA(_xlpm.party, SUMIFS(ledger!G:G, ledger!B:B, _xlpm.party, ledger!E:E, "<>*RD*") / 1.0936 ))+_xlfn.IFNA(D104,0)} -> 151191.48 | T25: {=(_xlfn.BYROW(B69,_xlfn.LAMBDA(_xlpm.party,SUMIFS(ledger!G:G,ledger!B:B,_xlpm.party,ledger!E:E,"<>*RD*",ledger!D:D,"Chamki")+SUMIFS(ledger!G:G, ledger!B:B, _xlpm.party, ledger!E:E, "<>*RD*", ledger!D:D, "Crinkle")))/1.0936)+_xlfn.IFNA(E104,0)} -> 113495.79 | U25: {=(_xlfn.BYROW(B69,_xlfn.LAMBDA(_xlpm.party,SUMIFS(ledger!G:G,ledger!B:B,_xlpm.party,ledger!E:E,"<>*RD*",ledger!D:D,"Silky")))/1.0936)+_xlfn.IFNA(F104,0)} -> 0 | V25: {=(_xlfn.BYROW(B69,_xlfn.LAMBDA(_xlpm.party, (SUMIFS(ledger!J:J,ledger!B:B,_xlpm.party,ledger!E:E,"<>*RD*",ledger!D:D,"Chamki",ledger!C:C,"<>October Closing CF")+ SUMIFS(ledger!J:J,ledger!B:B,_xlpm.party,ledger!E:E,"<>*RD*",ledger!D:D,"Crinkle",ledger!C:C,"<>October Closing CF") )+_xlfn.IFNA(G104,0))))} -> 1134957.9 | W25: {=_xlfn.BYROW(B69, _xlfn.LAMBDA(_xlpm.party, SUMIFS(ledger!J:J, ledger!B:B, _xlpm.party, ledger!E:E, "<>*RD*", ledger!D:D, "Silky", ledger!C:C, "<>October Closing CF") )) + _xlfn.IFNA(H104, 0)} -> 0 | X25: {=_xlfn.BYROW(B69, _xlfn.LAMBDA(_xlpm.party, SUMIFS(ledger!J:J, ledger!B:B, _xlpm.party, ledger!E:E, "<>*RD*", ledger!D:D, "Slub", ledger!C:C, "<>October Closing CF") ))+ _xlfn.IFNA(I104, 0)} -> 0 | Y25: {=_xlfn.BYROW(B69, _xlfn.LAMBDA(_xlpm.party, SUMIFS(ledger!J:J, ledger!B:B, _xlpm.party, ledger!E:E, "<>*RD*", ledger!D:D, "Satin", ledger!C:C, "<>October Closing CF") ))+ _xlfn.IFNA(J104, 0)} -> 0 | Z25: {=_xlfn.BYROW(B69, _xlfn.LAMBDA(_xlpm.party, SUMIFS(ledger!J:J, ledger!B:B, _xlpm.party, ledger!E:E, "<>*RD*", ledger!D:D, "Black-Chamki", ledger!C:C, "<>October Closing CF") ))} -> 0 | AA25: {=_xlfn.BYROW(B69, _xlfn.LAMBDA(_xlpm.party, SUMIFS(ledger!J:J, ledger!B:B, _xlpm.party, ledger!E:E, "<>*RD*", ledger!D:D, "Kataan", ledger!C:C, "<>October Closing CF") ))} -> 414652.52 | AB25: =V25+W25+X25+Y25+Z25+AA25 -> 1549610.5 | AC25: =(SUMIF(Table14[Party],Q25,Table14[Credit]))+_xlfn.IFNA(L104,0) -> 1103325 | AD25: =AB25-AC25 -> 446285.46 | AE25: 10 | AF25: 13
Q26: Hameed corporation | R26: {=_xlfn.BYROW(B70,_xlfn.LAMBDA(_xlpm.party,SUMIFS(ledger!G:G,ledger!B:B,_xlpm.party,ledger!E:E,"<>*RD*")))+_xlfn.IFNA(C105,0)} -> 46404 | S26: {=_xlfn.BYROW(B70, _xlfn.LAMBDA(_xlpm.party, SUMIFS(ledger!G:G, ledger!B:B, _xlpm.party, ledger!E:E, "<>*RD*") / 1.0936 ))+_xlfn.IFNA(D105,0)} -> 42432.334 | T26: {=(_xlfn.BYROW(B70,_xlfn.LAMBDA(_xlpm.party,SUMIFS(ledger!G:G,ledger!B:B,_xlpm.party,ledger!E:E,"<>*RD*",ledger!D:D,"Chamki")+SUMIFS(ledger!G:G, ledger!B:B, _xlpm.party, ledger!E:E, "<>*RD*", ledger!D:D, "Crinkle")))/1.0936)+_xlfn.IFNA(E105,0)} -> 42432.334 | U26: {=(_xlfn.BYROW(B70,_xlfn.LAMBDA(_xlpm.party,SUMIFS(ledger!G:G,ledger!B:B,_xlpm.party,ledger!E:E,"<>*RD*",ledger!D:D,"Silky")))/1.0936)+_xlfn.IFNA(F105,0)} -> 0 | V26: {=(_xlfn.BYROW(B70,_xlfn.LAMBDA(_xlpm.party, (SUMIFS(ledger!J:J,ledger!B:B,_xlpm.party,ledger!E:E,"<>*RD*",ledger!D:D,"Chamki",ledger!C:C,"<>October Closing CF")+ SUMIFS(ledger!J:J,ledger!B:B,_xlpm.party,ledger!E:E,"<>*RD*",ledger!D:D,"Crinkle",ledger!C:C,"<>October Closing CF") )+_xlfn.IFNA(G105,0))))} -> 424323.34 | W26: {=_xlfn.BYROW(B70, _xlfn.LAMBDA(_xlpm.party, SUMIFS(ledger!J:J, ledger!B:B, _xlpm.party, ledger!E:E, "<>*RD*", ledger!D:D, "Silky", ledger!C:C, "<>October Closing CF") )) + _xlfn.IFNA(H105, 0)} -> 0 | X26: {=_xlfn.BYROW(B70, _xlfn.LAMBDA(_xlpm.party, SUMIFS(ledger!J:J, ledger!B:B, _xlpm.party, ledger!E:E, "<>*RD*", ledger!D:D, "Slub", ledger!C:C, "<>October Closing CF") ))+ _xlfn.IFNA(I105, 0)} -> 0 | Y26: {=_xlfn.BYROW(B70, _xlfn.LAMBDA(_xlpm.party, SUMIFS(ledger!J:J, ledger!B:B, _xlpm.party, ledger!E:E, "<>*RD*", ledger!D:D, "Satin", ledger!C:C, "<>October Closing CF") ))+ _xlfn.IFNA(J105, 0)} -> 0 | Z26: {=_xlfn.BYROW(B70, _xlfn.LAMBDA(_xlpm.party, SUMIFS(ledger!J:J, ledger!B:B, _xlpm.party, ledger!E:E, "<>*RD*", ledger!D:D, "Black-Chamki", ledger!C:C, "<>October Closing CF") ))} -> 0 | AA26: {=_xlfn.BYROW(B70, _xlfn.LAMBDA(_xlpm.party, SUMIFS(ledger!J:J, ledger!B:B, _xlpm.party, ledger!E:E, "<>*RD*", ledger!D:D, "Kataan", ledger!C:C, "<>October Closing CF") ))} -> 0 | AB26: =V26+W26+X26+Y26+Z26+AA26 -> 424323.34 | AC26: =(SUMIF(Table14[Party],Q26,Table14[Credit]))+_xlfn.IFNA(L105,0) -> 424323 | AD26: =AB26-AC26 -> 0.33577176 | AE26: 10 | AF26: 13
Q27: ibraheem behraam | R27: {=_xlfn.BYROW(B71,_xlfn.LAMBDA(_xlpm.party,SUMIFS(ledger!G:G,ledger!B:B,_xlpm.party,ledger!E:E,"<>*RD*")))+_xlfn.IFNA(C106,0)} -> 35948 | S27: {=_xlfn.BYROW(B71, _xlfn.LAMBDA(_xlpm.party, SUMIFS(ledger!G:G, ledger!B:B, _xlpm.party, ledger!E:E, "<>*RD*") / 1.0936 ))+_xlfn.IFNA(D106,0)} -> 32871.251 | T27: {=(_xlfn.BYROW(B71,_xlfn.LAMBDA(_xlpm.party,SUMIFS(ledger!G:G,ledger!B:B,_xlpm.party,ledger!E:E,"<>*RD*",ledger!D:D,"Chamki")+SUMIFS(ledger!G:G, ledger!B:B, _xlpm.party, ledger!E:E, "<>*RD*", ledger!D:D, "Crinkle")))/1.0936)+_xlfn.IFNA(E106,0)} -> 0 | U27: {=(_xlfn.BYROW(B71,_xlfn.LAMBDA(_xlpm.party,SUMIFS(ledger!G:G,ledger!B:B,_xlpm.party,ledger!E:E,"<>*RD*",ledger!D:D,"Silky")))/1.0936)+_xlfn.IFNA(F106,0)} -> 32871.251 | V27: {=(_xlfn.BYROW(B71,_xlfn.LAMBDA(_xlpm.party, (SUMIFS(ledger!J:J,ledger!B:B,_xlpm.party,ledger!E:E,"<>*RD*",ledger!D:D,"Chamki",ledger!C:C,"<>October Closing CF")+ SUMIFS(ledger!J:J,ledger!B:B,_xlpm.party,ledger!E:E,"<>*RD*",ledger!D:D,"Crinkle",ledger!C:C,"<>October Closing CF") )+_xlfn.IFNA(G106,0))))} -> 0 | W27: {=_xlfn.BYROW(B71, _xlfn.LAMBDA(_xlpm.party, SUMIFS(ledger!J:J, ledger!B:B, _xlpm.party, ledger!E:E, "<>*RD*", ledger!D:D, "Silky", ledger!C:C, "<>October Closing CF") )) + _xlfn.IFNA(H106, 0)} -> 427326.26 | X27: {=_xlfn.BYROW(B71, _xlfn.LAMBDA(_xlpm.party, SUMIFS(ledger!J:J, ledger!B:B, _xlpm.party, ledger!E:E, "<>*RD*", ledger!D:D, "Slub", ledger!C:C, "<>October Closing CF") ))+ _xlfn.IFNA(I106, 0)} -> 0 | Y27: {=_xlfn.BYROW(B71, _xlfn.LAMBDA(_xlpm.party, SUMIFS(ledger!J:J, ledger!B:B, _xlpm.party, ledger!E:E, "<>*RD*", ledger!D:D, "Satin", ledger!C:C, "<>October Closing CF") ))+ _xlfn.IFNA(J106, 0)} -> 0 | Z27: {=_xlfn.BYROW(B71, _xlfn.LAMBDA(_xlpm.party, SUMIFS(ledger!J:J, ledger!B:B, _xlpm.party, ledger!E:E, "<>*RD*", ledger!D:D, "Black-Chamki", ledger!C:C, "<>October Closing CF") ))} -> 0 | AA27: {=_xlfn.BYROW(B71, _xlfn.LAMBDA(_xlpm.party, SUMIFS(ledger!J:J, ledger!B:B, _xlpm.party, ledger!E:E, "<>*RD*", ledger!D:D, "Kataan", ledger!C:C, "<>October Closing CF") ))} -> 0 | AB27: =V27+W27+X27+Y27+Z27+AA27 -> 427326.26 | AC27: =(SUMIF(Table14[Party],Q27,Table14[Credit]))+_xlfn.IFNA(L106,0) -> 437000 | AD27: =AB27-AC27 -> -9673.7381 | AE27: 10 | AF27: 13
Q28: Zia-ullah karachi | R28: {=_xlfn.BYROW(B72,_xlfn.LAMBDA(_xlpm.party,SUMIFS(ledger!G:G,ledger!B:B,_xlpm.party,ledger!E:E,"<>*RD*")))+_xlfn.IFNA(C107,0)} -> 13622 | S28: {=_xlfn.BYROW(B72, _xlfn.LAMBDA(_xlpm.party, SUMIFS(ledger!G:G, ledger!B:B, _xlpm.party, ledger!E:E, "<>*RD*") / 1.0936 ))+_xlfn.IFNA(D107,0)} -> 12456.108 | T28: {=(_xlfn.BYROW(B72,_xlfn.LAMBDA(_xlpm.party,SUMIFS(ledger!G:G,ledger!B:B,_xlpm.party,ledger!E:E,"<>*RD*",ledger!D:D,"Chamki")+SUMIFS(ledger!G:G, ledger!B:B, _xlpm.party, ledger!E:E, "<>*RD*", ledger!D:D, "Crinkle")))/1.0936)+_xlfn.IFNA(E107,0)} -> 12456.108 | U28: {=(_xlfn.BYROW(B72,_xlfn.LAMBDA(_xlpm.party,SUMIFS(ledger!G:G,ledger!B:B,_xlpm.party,ledger!E:E,"<>*RD*",ledger!D:D,"Silky")))/1.0936)+_xlfn.IFNA(F107,0)} -> 0 | V28: {=(_xlfn.BYROW(B72,_xlfn.LAMBDA(_xlpm.party, (SUMIFS(ledger!J:J,ledger!B:B,_xlpm.party,ledger!E:E,"<>*RD*",ledger!D:D,"Chamki",ledger!C:C,"<>October Closing CF")+ SUMIFS(ledger!J:J,ledger!B:B,_xlpm.party,ledger!E:E,"<>*RD*",ledger!D:D,"Crinkle",ledger!C:C,"<>October Closing CF") )+_xlfn.IFNA(G107,0))))} -> 124561.08 | W28: {=_xlfn.BYROW(B72, _xlfn.LAMBDA(_xlpm.party, SUMIFS(ledger!J:J, ledger!B:B, _xlpm.party, ledger!E:E, "<>*RD*", ledger!D:D, "Silky", ledger!C:C, "<>October Closing CF") )) + _xlfn.IFNA(H107, 0)} -> 0 | X28: {=_xlfn.BYROW(B72, _xlfn.LAMBDA(_xlpm.party, SUMIFS(ledger!J:J, ledger!B:B, _xlpm.party, ledger!E:E, "<>*RD*", ledger!D:D, "Slub", ledger!C:C, "<>October Closing CF") ))+ _xlfn.IFNA(I107, 0)} -> 0 | Y28: {=_xlfn.BYROW(B72, _xlfn.LAMBDA(_xlpm.party, SUMIFS(ledger!J:J, ledger!B:B, _xlpm.party, ledger!E:E, "<>*RD*", ledger!D:D, "Satin", ledger!C:C, "<>October Closing CF") ))+ _xlfn.IFNA(J107, 0)} -> 0 | Z28: {=_xlfn.BYROW(B72, _xlfn.LAMBDA(_xlpm.party, SUMIFS(ledger!J:J, ledger!B:B, _xlpm.party, ledger!E:E, "<>*RD*", ledger!D:D, "Black-Chamki", ledger!C:C, "<>October Closing CF") ))} -> 0 | AA28: {=_xlfn.BYROW(B72, _xlfn.LAMBDA(_xlpm.party, SUMIFS(ledger!J:J, ledger!B:B, _xlpm.party, ledger!E:E, "<>*RD*", ledger!D:D, "Kataan", ledger!C:C, "<>October Closing CF") ))} -> 0 | AB28: =V28+W28+X28+Y28+Z28+AA28 -> 124561.08 | AC28: =(SUMIF(Table14[Party],Q28,Table14[Credit]))+_xlfn.IFNA(L107,0) -> 137260 | AD28: =AB28-AC28 -> -12698.917 | AE28: 10 | AF28: 13
R29: {=_xlfn.BYROW(B73,_xlfn.LAMBDA(_xlpm.party,SUMIFS(ledger!G:G,ledger!B:B,_xlpm.party,ledger!E:E,"<>*RD*")))+_xlfn.IFNA(C108,0)} -> 0 | S29: {=_xlfn.BYROW(B73, _xlfn.LAMBDA(_xlpm.party, SUMIFS(ledger!G:G, ledger!B:B, _xlpm.party, ledger!E:E, "<>*RD*") / 1.0936 ))+_xlfn.IFNA(D108,0)} -> 0 | T29: {=(_xlfn.BYROW(B73,_xlfn.LAMBDA(_xlpm.party,SUMIFS(ledger!G:G,ledger!B:B,_xlpm.party,ledger!E:E,"<>*RD*",ledger!D:D,"Chamki")+SUMIFS(ledger!G:G, ledger!B:B, _xlpm.party, ledger!E:E, "<>*RD*", ledger!D:D, "Crinkle")))/1.0936)+_xlfn.IFNA(E108,0)} -> 0 | U29: {=(_xlfn.BYROW(B73,_xlfn.LAMBDA(_xlpm.party,SUMIFS(ledger!G:G,ledger!B:B,_xlpm.party,ledger!E:E,"<>*RD*",ledger!D:D,"Silky")))/1.0936)+_xlfn.IFNA(F108,0)} -> 0 | V29: {=(_xlfn.BYROW(B73,_xlfn.LAMBDA(_xlpm.party, (SUMIFS(ledger!J:J,ledger!B:B,_xlpm.party,ledger!E:E,"<>*RD*",ledger!D:D,"Chamki",ledger!C:C,"<>October Closing CF")+ SUMIFS(ledger!J:J,ledger!B:B,_xlpm.party,ledger!E:E,"<>*RD*",ledger!D:D,"Crinkle",ledger!C:C,"<>October Closing CF") )+_xlfn.IFNA(G108,0))))} -> 0 | W29: {=_xlfn.BYROW(B73, _xlfn.LAMBDA(_xlpm.party, SUMIFS(ledger!J:J, ledger!B:B, _xlpm.party, ledger!E:E, "<>*RD*", ledger!D:D, "Silky", ledger!C:C, "<>October Closing CF") )) + _xlfn.IFNA(H108, 0)} -> 0 | X29: {=_xlfn.BYROW(B73, _xlfn.LAMBDA(_xlpm.party, SUMIFS(ledger!J:J, ledger!B:B, _xlpm.party, ledger!E:E, "<>*RD*", ledger!D:D, "Slub", ledger!C:C, "<>October Closing CF") ))+ _xlfn.IFNA(I108, 0)} -> 0 | Y29: {=_xlfn.BYROW(B73, _xlfn.LAMBDA(_xlpm.party, SUMIFS(ledger!J:J, ledger!B:B, _xlpm.party, ledger!E:E, "<>*RD*", ledger!D:D, "Satin", ledger!C:C, "<>October Closing CF") ))+ _xlfn.IFNA(J108, 0)} -> 0 | Z29: {=_xlfn.BYROW(B73, _xlfn.LAMBDA(_xlpm.party, SUMIFS(ledger!J:J, ledger!B:B, _xlpm.party, ledger!E:E, "<>*RD*", ledger!D:D, "Black-Chamki", ledger!C:C, "<>October Closing CF") ))} -> 0 | AA29: {=_xlfn.BYROW(B73, _xlfn.LAMBDA(_xlpm.party, SUMIFS(ledger!J:J, ledger!B:B, _xlpm.party, ledger!E:E, "<>*RD*", ledger!D:D, "Kataan", ledger!C:C, "<>October Closing CF") ))} -> 0 | AB29: =V29+W29+X29+Y29+Z29+AA29 -> 0 | AC29: =(SUMIF(Table14[Party],Q29,Table14[Credit]))+_xlfn.IFNA(L108,0) -> 0 | AD29: =AB29-AC29 -> 0 | AE29: 10 | AF29: 13
R30: {=_xlfn.BYROW(B74,_xlfn.LAMBDA(_xlpm.party,SUMIFS(ledger!G:G,ledger!B:B,_xlpm.party,ledger!E:E,"<>*RD*")))+_xlfn.IFNA(C109,0)} -> 0 | S30: {=_xlfn.BYROW(B74, _xlfn.LAMBDA(_xlpm.party, SUMIFS(ledger!G:G, ledger!B:B, _xlpm.party, ledger!E:E, "<>*RD*") / 1.0936 ))+_xlfn.IFNA(D109,0)} -> 0 | T30: {=(_xlfn.BYROW(B74,_xlfn.LAMBDA(_xlpm.party,SUMIFS(ledger!G:G,ledger!B:B,_xlpm.party,ledger!E:E,"<>*RD*",ledger!D:D,"Chamki")+SUMIFS(ledger!G:G, ledger!B:B, _xlpm.party, ledger!E:E, "<>*RD*", ledger!D:D, "Crinkle")))/1.0936)+_xlfn.IFNA(E109,0)} -> 0 | U30: {=(_xlfn.BYROW(B74,_xlfn.LAMBDA(_xlpm.party,SUMIFS(ledger!G:G,ledger!B:B,_xlpm.party,ledger!E:E,"<>*RD*",ledger!D:D,"Silky")))/1.0936)+_xlfn.IFNA(F109,0)} -> 0 | V30: {=(_xlfn.BYROW(B74,_xlfn.LAMBDA(_xlpm.party, (SUMIFS(ledger!J:J,ledger!B:B,_xlpm.party,ledger!E:E,"<>*RD*",ledger!D:D,"Chamki",ledger!C:C,"<>October Closing CF")+ SUMIFS(ledger!J:J,ledger!B:B,_xlpm.party,ledger!E:E,"<>*RD*",ledger!D:D,"Crinkle",ledger!C:C,"<>October Closing CF") )+_xlfn.IFNA(G109,0))))} -> 0 | W30: {=_xlfn.BYROW(B74, _xlfn.LAMBDA(_xlpm.party, SUMIFS(ledger!J:J, ledger!B:B, _xlpm.party, ledger!E:E, "<>*RD*", ledger!D:D, "Silky", ledger!C:C, "<>October Closing CF") )) + _xlfn.IFNA(H109, 0)} -> 0 | X30: {=_xlfn.BYROW(B74, _xlfn.LAMBDA(_xlpm.party, SUMIFS(ledger!J:J, ledger!B:B, _xlpm.party, ledger!E:E, "<>*RD*", ledger!D:D, "Slub", ledger!C:C, "<>October Closing CF") ))} -> 0 | Y30: {=_xlfn.BYROW(B74, _xlfn.LAMBDA(_xlpm.party, SUMIFS(ledger!J:J, ledger!B:B, _xlpm.party, ledger!E:E, "<>*RD*", ledger!D:D, "Satin", ledger!C:C, "<>October Closing CF") ))} -> 0 | Z30: {=_xlfn.BYROW(B74, _xlfn.LAMBDA(_xlpm.party, SUMIFS(ledger!J:J, ledger!B:B, _xlpm.party, ledger!E:E, "<>*RD*", ledger!D:D, "Black-Chamki", ledger!C:C, "<>October Closing CF") ))} -> 0 | AA30: {=_xlfn.BYROW(B74, _xlfn.LAMBDA(_xlpm.party, SUMIFS(ledger!J:J, ledger!B:B, _xlpm.party, ledger!E:E, "<>*RD*", ledger!D:D, "Kataan", ledger!C:C, "<>October Closing CF") ))} -> 0 | AB30: =V30+W30+X30+Y30+Z30+AA30 -> 0 | AC30: =(SUMIF(Table14[Party],Q30,Table14[Credit]))+_xlfn.IFNA(L109,0) -> 0 | AD30: =AB30-AC30 -> 0 | AE30: 10 | AF30: 13
R31: {=_xlfn.BYROW(B75,_xlfn.LAMBDA(_xlpm.party,SUMIFS(ledger!G:G,ledger!B:B,_xlpm.party,ledger!E:E,"<>*RD*")))+_xlfn.IFNA(C110,0)} -> 0 | S31: {=_xlfn.BYROW(B75, _xlfn.LAMBDA(_xlpm.party, SUMIFS(ledger!G:G, ledger!B:B, _xlpm.party, ledger!E:E, "<>*RD*") / 1.0936 ))+_xlfn.IFNA(D110,0)} -> 0 | T31: {=(_xlfn.BYROW(B75,_xlfn.LAMBDA(_xlpm.party,SUMIFS(ledger!G:G,ledger!B:B,_xlpm.party,ledger!E:E,"<>*RD*",ledger!D:D,"Chamki")+SUMIFS(ledger!G:G, ledger!B:B, _xlpm.party, ledger!E:E, "<>*RD*", ledger!D:D, "Crinkle")))/1.0936)+_xlfn.IFNA(E110,0)} -> 0 | U31: {=(_xlfn.BYROW(B75,_xlfn.LAMBDA(_xlpm.party,SUMIFS(ledger!G:G,ledger!B:B,_xlpm.party,ledger!E:E,"<>*RD*",ledger!D:D,"Silky")))/1.0936)+_xlfn.IFNA(F110,0)} -> 0 | V31: {=(_xlfn.BYROW(B75,_xlfn.LAMBDA(_xlpm.party, (SUMIFS(ledger!J:J,ledger!B:B,_xlpm.party,ledger!E:E,"<>*RD*",ledger!D:D,"Chamki",ledger!C:C,"<>October Closing CF")+ SUMIFS(ledger!J:J,ledger!B:B,_xlpm.party,ledger!E:E,"<>*RD*",ledger!D:D,"Crinkle",ledger!C:C,"<>October Closing CF") )+_xlfn.IFNA(G110,0))))} -> 0 | W31: {=_xlfn.BYROW(B75, _xlfn.LAMBDA(_xlpm.party, SUMIFS(ledger!J:J, ledger!B:B, _xlpm.party, ledger!E:E, "<>*RD*", ledger!D:D, "Silky", ledger!C:C, "<>October Closing CF") )) + _xlfn.IFNA(H110, 0)} -> 0 | X31: {=_xlfn.BYROW(B75, _xlfn.LAMBDA(_xlpm.party, SUMIFS(ledger!J:J, ledger!B:B, _xlpm.party, ledger!E:E, "<>*RD*", ledger!D:D, "Slub", ledger!C:C, "<>October Closing CF") ))} -> 0 | Y31: {=_xlfn.BYROW(B75, _xlfn.LAMBDA(_xlpm.party, SUMIFS(ledger!J:J, ledger!B:B, _xlpm.party, ledger!E:E, "<>*RD*", ledger!D:D, "Satin", ledger!C:C, "<>October Closing CF") ))} -> 0 | Z31: {=_xlfn.BYROW(B75, _xlfn.LAMBDA(_xlpm.party, SUMIFS(ledger!J:J, ledger!B:B, _xlpm.party, ledger!E:E, "<>*RD*", ledger!D:D, "Black-Chamki", ledger!C:C, "<>October Closing CF") ))} -> 0 | AA31: {=_xlfn.BYROW(B75, _xlfn.LAMBDA(_xlpm.party, SUMIFS(ledger!J:J, ledger!B:B, _xlpm.party, ledger!E:E, "<>*RD*", ledger!D:D, "Kataan", ledger!C:C, "<>October Closing CF") ))} -> 0 | AB31: =V31+W31+X31+Y31+Z31+AA31 -> 0 | AC31: =(SUMIF(Table14[Party],Q31,Table14[Credit]))+_xlfn.IFNA(L110,0) -> 0 | AD31: =AB31-AC31 -> 0 | AE31: 10 | AF31: 13
R32: {=_xlfn.BYROW(B76,_xlfn.LAMBDA(_xlpm.party,SUMIFS(ledger!G:G,ledger!B:B,_xlpm.party,ledger!E:E,"<>*RD*")))+_xlfn.IFNA(C111,0)} -> 0 | S32: {=_xlfn.BYROW(B76, _xlfn.LAMBDA(_xlpm.party, SUMIFS(ledger!G:G, ledger!B:B, _xlpm.party, ledger!E:E, "<>*RD*") / 1.0936 ))+_xlfn.IFNA(D111,0)} -> 0 | T32: {=(_xlfn.BYROW(B76,_xlfn.LAMBDA(_xlpm.party,SUMIFS(ledger!G:G,ledger!B:B,_xlpm.party,ledger!E:E,"<>*RD*",ledger!D:D,"Chamki")+SUMIFS(ledger!G:G, ledger!B:B, _xlpm.party, ledger!E:E, "<>*RD*", ledger!D:D, "Crinkle")))/1.0936)+_xlfn.IFNA(E111,0)} -> 0 | U32: {=(_xlfn.BYROW(B76,_xlfn.LAMBDA(_xlpm.party,SUMIFS(ledger!G:G,ledger!B:B,_xlpm.party,ledger!E:E,"<>*RD*",ledger!D:D,"Silky")))/1.0936)+_xlfn.IFNA(F111,0)} -> 0 | V32: {=(_xlfn.BYROW(B76,_xlfn.LAMBDA(_xlpm.party, (SUMIFS(ledger!J:J,ledger!B:B,_xlpm.party,ledger!E:E,"<>*RD*",ledger!D:D,"Chamki",ledger!C:C,"<>October Closing CF")+ SUMIFS(ledger!J:J,ledger!B:B,_xlpm.party,ledger!E:E,"<>*RD*",ledger!D:D,"Crinkle",ledger!C:C,"<>October Closing CF") )+_xlfn.IFNA(G111,0))))} -> 0 | W32: {=_xlfn.BYROW(B76, _xlfn.LAMBDA(_xlpm.party, SUMIFS(ledger!J:J, ledger!B:B, _xlpm.party, ledger!E:E, "<>*RD*", ledger!D:D, "Silky", ledger!C:C, "<>October Closing CF") )) + _xlfn.IFNA(H111, 0)} -> 0 | X32: {=_xlfn.BYROW(B76, _xlfn.LAMBDA(_xlpm.party, SUMIFS(ledger!J:J, ledger!B:B, _xlpm.party, ledger!E:E, "<>*RD*", ledger!D:D, "Slub", ledger!C:C, "<>October Closing CF") ))} -> 0 | Y32: {=_xlfn.BYROW(B76, _xlfn.LAMBDA(_xlpm.party, SUMIFS(ledger!J:J, ledger!B:B, _xlpm.party, ledger!E:E, "<>*RD*", ledger!D:D, "Satin", ledger!C:C, "<>October Closing CF") ))} -> 0 | Z32: {=_xlfn.BYROW(B76, _xlfn.LAMBDA(_xlpm.party, SUMIFS(ledger!J:J, ledger!B:B, _xlpm.party, ledger!E:E, "<>*RD*", ledger!D:D, "Black-Chamki", ledger!C:C, "<>October Closing CF") ))} -> 0 | AA32: {=_xlfn.BYROW(B76, _xlfn.LAMBDA(_xlpm.party, SUMIFS(ledger!J:J, ledger!B:B, _xlpm.party, ledger!E:E, "<>*RD*", ledger!D:D, "Kataan", ledger!C:C, "<>October Closing CF") ))} -> 0 | AB32: =V32+W32+X32+Y32+Z32+AA32 -> 0 | AC32: =(SUMIF(Table14[Party],Q32,Table14[Credit]))+_xlfn.IFNA(L111,0) -> 0 | AD32: =AB32-AC32 -> 0 | AE32: 10 | AF32: 13
R33: {=_xlfn.BYROW(B77,_xlfn.LAMBDA(_xlpm.party,SUMIFS(ledger!G:G,ledger!B:B,_xlpm.party,ledger!E:E,"<>*RD*")))+_xlfn.IFNA(C112,0)} -> 0 | S33: {=_xlfn.BYROW(B77, _xlfn.LAMBDA(_xlpm.party, SUMIFS(ledger!G:G, ledger!B:B, _xlpm.party, ledger!E:E, "<>*RD*") / 1.0936 ))+_xlfn.IFNA(D112,0)} -> 0 | T33: {=(_xlfn.BYROW(B77,_xlfn.LAMBDA(_xlpm.party,SUMIFS(ledger!G:G,ledger!B:B,_xlpm.party,ledger!E:E,"<>*RD*",ledger!D:D,"Chamki")+SUMIFS(ledger!G:G, ledger!B:B, _xlpm.party, ledger!E:E, "<>*RD*", ledger!D:D, "Crinkle")))/1.0936)+_xlfn.IFNA(E112,0)} -> 0 | U33: {=(_xlfn.BYROW(B77,_xlfn.LAMBDA(_xlpm.party,SUMIFS(ledger!G:G,ledger!B:B,_xlpm.party,ledger!E:E,"<>*RD*",ledger!D:D,"Silky")))/1.0936)+_xlfn.IFNA(F112,0)} -> 0 | V33: {=(_xlfn.BYROW(B77,_xlfn.LAMBDA(_xlpm.party, (SUMIFS(ledger!J:J,ledger!B:B,_xlpm.party,ledger!E:E,"<>*RD*",ledger!D:D,"Chamki",ledger!C:C,"<>October Closing CF")+ SUMIFS(ledger!J:J,ledger!B:B,_xlpm.party,ledger!E:E,"<>*RD*",ledger!D:D,"Crinkle",ledger!C:C,"<>October Closing CF") )+_xlfn.IFNA(G112,0))))} -> 0 | W33: {=_xlfn.BYROW(B77, _xlfn.LAMBDA(_xlpm.party, SUMIFS(ledger!J:J, ledger!B:B, _xlpm.party, ledger!E:E, "<>*RD*", ledger!D:D, "Silky", ledger!C:C, "<>October Closing CF") )) + _xlfn.IFNA(H112, 0)} -> 0 | X33: {=_xlfn.BYROW(B77, _xlfn.LAMBDA(_xlpm.party, SUMIFS(ledger!J:J, ledger!B:B, _xlpm.party, ledger!E:E, "<>*RD*", ledger!D:D, "Slub", ledger!C:C, "<>October Closing CF") ))} -> 0 | Y33: {=_xlfn.BYROW(B77, _xlfn.LAMBDA(_xlpm.party, SUMIFS(ledger!J:J, ledger!B:B, _xlpm.party, ledger!E:E, "<>*RD*", ledger!D:D, "Satin", ledger!C:C, "<>October Closing CF") ))} -> 0 | Z33: {=_xlfn.BYROW(B77, _xlfn.LAMBDA(_xlpm.party, SUMIFS(ledger!J:J, ledger!B:B, _xlpm.party, ledger!E:E, "<>*RD*", ledger!D:D, "Black-Chamki", ledger!C:C, "<>October Closing CF") ))} -> 0 | AA33: {=_xlfn.BYROW(B77, _xlfn.LAMBDA(_xlpm.party, SUMIFS(ledger!J:J, ledger!B:B, _xlpm.party, ledger!E:E, "<>*RD*", ledger!D:D, "Kataan", ledger!C:C, "<>October Closing CF") ))} -> 0 | AB33: =V33+W33+X33+Y33+Z33+AA33 -> 0 | AC33: =(SUMIF(Table14[Party],Q33,Table14[Credit]))+_xlfn.IFNA(L112,0) -> 0 | AD33: =AB33-AC33 -> 0 | AE33: 10 | AF33: 13
R34: {=_xlfn.BYROW(B78,_xlfn.LAMBDA(_xlpm.party,SUMIFS(ledger!G:G,ledger!B:B,_xlpm.party,ledger!E:E,"<>*RD*")))+_xlfn.IFNA(C113,0)} -> 0 | S34: {=_xlfn.BYROW(B78, _xlfn.LAMBDA(_xlpm.party, SUMIFS(ledger!G:G, ledger!B:B, _xlpm.party, ledger!E:E, "<>*RD*") / 1.0936 ))+_xlfn.IFNA(D113,0)} -> 0 | T34: {=(_xlfn.BYROW(B78,_xlfn.LAMBDA(_xlpm.party,SUMIFS(ledger!G:G,ledger!B:B,_xlpm.party,ledger!E:E,"<>*RD*",ledger!D:D,"Chamki")+SUMIFS(ledger!G:G, ledger!B:B, _xlpm.party, ledger!E:E, "<>*RD*", ledger!D:D, "Crinkle")))/1.0936)+_xlfn.IFNA(E113,0)} -> 0 | U34: {=(_xlfn.BYROW(B78,_xlfn.LAMBDA(_xlpm.party,SUMIFS(ledger!G:G,ledger!B:B,_xlpm.party,ledger!E:E,"<>*RD*",ledger!D:D,"Silky")))/1.0936)+_xlfn.IFNA(F113,0)} -> 0 | V34: {=(_xlfn.BYROW(B78,_xlfn.LAMBDA(_xlpm.party, (SUMIFS(ledger!J:J,ledger!B:B,_xlpm.party,ledger!E:E,"<>*RD*",ledger!D:D,"Chamki",ledger!C:C,"<>October Closing CF")+ SUMIFS(ledger!J:J,ledger!B:B,_xlpm.party,ledger!E:E,"<>*RD*",ledger!D:D,"Crinkle",ledger!C:C,"<>October Closing CF") )+_xlfn.IFNA(G113,0))))} -> 0 | W34: {=_xlfn.BYROW(B78, _xlfn.LAMBDA(_xlpm.party, SUMIFS(ledger!J:J, ledger!B:B, _xlpm.party, ledger!E:E, "<>*RD*", ledger!D:D, "Silky", ledger!C:C, "<>October Closing CF") )) + _xlfn.IFNA(H113, 0)} -> 0 | X34: {=_xlfn.BYROW(B78, _xlfn.LAMBDA(_xlpm.party, SUMIFS(ledger!J:J, ledger!B:B, _xlpm.party, ledger!E:E, "<>*RD*", ledger!D:D, "Slub", ledger!C:C, "<>October Closing CF") ))} -> 0 | Y34: {=_xlfn.BYROW(B78, _xlfn.LAMBDA(_xlpm.party, SUMIFS(ledger!J:J, ledger!B:B, _xlpm.party, ledger!E:E, "<>*RD*", ledger!D:D, "Satin", ledger!C:C, "<>October Closing CF") ))} -> 0 | Z34: {=_xlfn.BYROW(B78, _xlfn.LAMBDA(_xlpm.party, SUMIFS(ledger!J:J, ledger!B:B, _xlpm.party, ledger!E:E, "<>*RD*", ledger!D:D, "Black-Chamki", ledger!C:C, "<>October Closing CF") ))} -> 0 | AA34: {=_xlfn.BYROW(B78, _xlfn.LAMBDA(_xlpm.party, SUMIFS(ledger!J:J, ledger!B:B, _xlpm.party, ledger!E:E, "<>*RD*", ledger!D:D, "Kataan", ledger!C:C, "<>October Closing CF") ))} -> 0 | AB34: =V34+W34+X34+Y34+Z34+AA34 -> 0 | AC34: =(SUMIF(Table14[Party],Q34,Table14[Credit]))+_xlfn.IFNA(L113,0) -> 0 | AD34: =AB34-AC34 -> 0 | AE34: 10 | AF34: 13
R35: {=_xlfn.BYROW(B79,_xlfn.LAMBDA(_xlpm.party,SUMIFS(ledger!G:G,ledger!B:B,_xlpm.party,ledger!E:E,"<>*RD*")))+_xlfn.IFNA(C114,0)} -> 0 | S35: {=_xlfn.BYROW(B79, _xlfn.LAMBDA(_xlpm.party, SUMIFS(ledger!G:G, ledger!B:B, _xlpm.party, ledger!E:E, "<>*RD*") / 1.0936 ))+_xlfn.IFNA(D114,0)} -> 0 | T35: {=(_xlfn.BYROW(B79,_xlfn.LAMBDA(_xlpm.party,SUMIFS(ledger!G:G,ledger!B:B,_xlpm.party,ledger!E:E,"<>*RD*",ledger!D:D,"Chamki")+SUMIFS(ledger!G:G, ledger!B:B, _xlpm.party, ledger!E:E, "<>*RD*", ledger!D:D, "Crinkle")))/1.0936)+_xlfn.IFNA(E114,0)} -> 0 | U35: {=(_xlfn.BYROW(B79,_xlfn.LAMBDA(_xlpm.party,SUMIFS(ledger!G:G,ledger!B:B,_xlpm.party,ledger!E:E,"<>*RD*",ledger!D:D,"Silky")))/1.0936)+_xlfn.IFNA(F114,0)} -> 0 | V35: {=(_xlfn.BYROW(B79,_xlfn.LAMBDA(_xlpm.party, (SUMIFS(ledger!J:J,ledger!B:B,_xlpm.party,ledger!E:E,"<>*RD*",ledger!D:D,"Chamki",ledger!C:C,"<>October Closing CF")+ SUMIFS(ledger!J:J,ledger!B:B,_xlpm.party,ledger!E:E,"<>*RD*",ledger!D:D,"Crinkle",ledger!C:C,"<>October Closing CF") )+_xlfn.IFNA(G114,0))))} -> 0 | W35: {=_xlfn.BYROW(B79, _xlfn.LAMBDA(_xlpm.party, SUMIFS(ledger!J:J, ledger!B:B, _xlpm.party, ledger!E:E, "<>*RD*", ledger!D:D, "Silky", ledger!C:C, "<>October Closing CF") )) + _xlfn.IFNA(H114, 0)} -> 0 | X35: {=_xlfn.BYROW(B79, _xlfn.LAMBDA(_xlpm.party, SUMIFS(ledger!J:J, ledger!B:B, _xlpm.party, ledger!E:E, "<>*RD*", ledger!D:D, "Slub", ledger!C:C, "<>October Closing CF") ))} -> 0 | Y35: {=_xlfn.BYROW(B79, _xlfn.LAMBDA(_xlpm.party, SUMIFS(ledger!J:J, ledger!B:B, _xlpm.party, ledger!E:E, "<>*RD*", ledger!D:D, "Satin", ledger!C:C, "<>October Closing CF") ))} -> 0 | AA35: {=_xlfn.BYROW(B79, _xlfn.LAMBDA(_xlpm.party, SUMIFS(ledger!J:J, ledger!B:B, _xlpm.party, ledger!E:E, "<>*RD*", ledger!D:D, "Kataan", ledger!C:C, "<>October Closing CF") ))} -> 0 | AB35: =V35+W35+X35+Y35+Z35+AA35 -> 0 | AC35: =(SUMIF(Table14[Party],Q35,Table14[Credit]))+_xlfn.IFNA(L114,0) -> 0 | AD35: =AB35-AC35 -> 0 | AE35: 10 | AF35: 13
B47: Billing September
C48: Gaz | D48: Total Metres | E48: Total Chamki | F48: Total Super Silky | G48: Billing (Chamki/Crinkle) | H48: Billing (Super Chamki) | I48: Billing (Slub) | J48: Billing (Satin) | K48: Adjusted Bill | L48: Amount Paid | M48: Balance | N48: Rate (Chamki) | O48: Rate (Super Silky)
A49: Parties: | B49: {=_xlfn.UNIQUE(Table1[Party Name])} -> BSC | C49: {=_xlfn.BYROW(_xlfn.ANCHORARRAY(B49),_xlfn.LAMBDA(_xlpm.party,SUMIFS(ledger!G:G,ledger!B:B,_xlpm.party,ledger!E:E,"<>*RD*")))} -> 254101 | D49: {=_xlfn.BYROW(_xlfn.ANCHORARRAY(B49), _xlfn.LAMBDA(_xlpm.party, SUMIFS(ledger!G:G, ledger!B:B, _xlpm.party, ledger!E:E, "<>*RD*") / 1.0936 ))} -> 232352.78 | E49: {=(_xlfn.BYROW(_xlfn.ANCHORARRAY(B49),_xlfn.LAMBDA(_xlpm.party,SUMIFS(ledger!G:G,ledger!B:B,_xlpm.party,ledger!E:E,"<>*RD*",ledger!D:D,"Chamki")+SUMIFS(ledger!G:G, ledger!B:B, _xlpm.party, ledger!E:E, "<>*RD*", ledger!D:D, "Crinkle")))/1.0936)} -> 132090.34 | F49: {=(_xlfn.BYROW(_xlfn.ANCHORARRAY(B49),_xlfn.LAMBDA(_xlpm.party,SUMIFS(ledger!G:G,ledger!B:B,_xlpm.party,ledger!E:E,"<>*RD*",ledger!D:D,"Silky")))/1.0936)} -> 100262.44 | G49: {=(_xlfn.BYROW(B49,_xlfn.LAMBDA(_xlpm.party, (SUMIFS(ledger!J:J,ledger!B:B,_xlpm.party,ledger!E:E,"<>*RD*",ledger!D:D,"Chamki",ledger!C:C,"<>October Closing CF")+ SUMIFS(ledger!J:J,ledger!B:B,_xlpm.party,ledger!E:E,"<>*RD*",ledger!D:D,"Crinkle",ledger!C:C,"<>October Closing CF") ))))} -> 1320903.4 | H49: {=_xlfn.BYROW(B49, _xlfn.LAMBDA(_xlpm.party, SUMIFS(ledger!J:J, ledger!B:B, _xlpm.party, ledger!E:E, "<>*RD*", ledger!D:D, "Silky", ledger!C:C, "<>October Closing CF") ))} -> 1303411.7 | I49: {=_xlfn.BYROW(B49, _xlfn.LAMBDA(_xlpm.party, SUMIFS(ledger!J:J, ledger!B:B, _xlpm.party, ledger!E:E, "<>*RD*", ledger!D:D, "Slub", ledger!C:C, "<>October Closing CF") ))} -> 0 | J49: {=_xlfn.BYROW(B49, _xlfn.LAMBDA(_xlpm.party, SUMIFS(ledger!J:J, ledger!B:B, _xlpm.party, ledger!E:E, "<>*RD*", ledger!D:D, "Satin", ledger!C:C, "<>October Closing CF") ))} -> 0 | K49: =G49+H49+I49+J49 -> 2624315.1 | L49: =(SUMIF(Table14[Party],B49,Table14[Credit])) -> 1339058 | M49: =K49-L49 -> 1285257.1 | N49: 10 | O49: 12
B50: Ejaz Sahab | C50: 115553 | D50: 105662.95 | E50: 0 | F50: 105662.95 | G50: {=(_xlfn.BYROW(B50,_xlfn.LAMBDA(_xlpm.party, (SUMIFS(ledger!J:J,ledger!B:B,_xlpm.party,ledger!E:E,"<>*RD*",ledger!D:D,"Chamki",ledger!C:C,"<>October Closing CF")+ SUMIFS(ledger!J:J,ledger!B:B,_xlpm.party,ledger!E:E,"<>*RD*",ledger!D:D,"Crinkle",ledger!C:C,"<>October Closing CF") ))))} -> 0 | H50: {=_xlfn.BYROW(B50, _xlfn.LAMBDA(_xlpm.party, SUMIFS(ledger!J:J, ledger!B:B, _xlpm.party, ledger!E:E, "<>*RD*", ledger!D:D, "Silky", ledger!C:C, "<>October Closing CF") ))} -> 1373618.3 | I50: {=_xlfn.BYROW(B50, _xlfn.LAMBDA(_xlpm.party, SUMIFS(ledger!J:J, ledger!B:B, _xlpm.party, ledger!E:E, "<>*RD*", ledger!D:D, "Slub", ledger!C:C, "<>October Closing CF") ))} -> 0 | J50: {=_xlfn.BYROW(B50, _xlfn.LAMBDA(_xlpm.party, SUMIFS(ledger!J:J, ledger!B:B, _xlpm.party, ledger!E:E, "<>*RD*", ledger!D:D, "Satin", ledger!C:C, "<>October Closing CF") ))} -> 0 | K50: =G50+H50+I50+J50 -> 1373618.3 | L50: =(SUMIF(Table14[Party],B50,Table14[Credit])) -> 500000 | M50: =K50-L50 -> 873618.32 | N50: 10 | O50: 12
B51: Arshad | C51: 211642 | D51: 193527.8 | E51: 130209.4 | F51: 63318.398 | G51: {=(_xlfn.BYROW(B51,_xlfn.LAMBDA(_xlpm.party, (SUMIFS(ledger!J:J,ledger!B:B,_xlpm.party,ledger!E:E,"<>*RD*",ledger!D:D,"Chamki",ledger!C:C,"<>October Closing CF")+ SUMIFS(ledger!J:J,ledger!B:B,_xlpm.party,ledger!E:E,"<>*RD*",ledger!D:D,"Crinkle",ledger!C:C,"<>October Closing CF") ))))} -> 1302094 | H51: {=_xlfn.BYROW(B51, _xlfn.LAMBDA(_xlpm.party, SUMIFS(ledger!J:J, ledger!B:B, _xlpm.party, ledger!E:E, "<>*RD*", ledger!D:D, "Silky", ledger!C:C, "<>October Closing CF") ))} -> 823139.17 | I51: {=_xlfn.BYROW(B51, _xlfn.LAMBDA(_xlpm.party, SUMIFS(ledger!J:J, ledger!B:B, _xlpm.party, ledger!E:E, "<>*RD*", ledger!D:D, "Slub", ledger!C:C, "<>October Closing CF") ))} -> 0 | J51: {=_xlfn.BYROW(B51, _xlfn.LAMBDA(_xlpm.party, SUMIFS(ledger!J:J, ledger!B:B, _xlpm.party, ledger!E:E, "<>*RD*", ledger!D:D, "Satin", ledger!C:C, "<>October Closing CF") ))} -> 0 | K51: =G51+H51+I51+J51 -> 2125233.2 | L51: =(SUMIF(Table14[Party],B51,Table14[Credit])) -> 1700000 | M51: =K51-L51 -> 425233.17 | N51: 10 | O51: 12
B52: Shehzad Kamoki | C52: 0 | D52: 0 | E52: 0 | F52: 0 | G52: {=(_xlfn.BYROW(B52,_xlfn.LAMBDA(_xlpm.party, (SUMIFS(ledger!J:J,ledger!B:B,_xlpm.party,ledger!E:E,"<>*RD*",ledger!D:D,"Chamki",ledger!C:C,"<>October Closing CF")+ SUMIFS(ledger!J:J,ledger!B:B,_xlpm.party,ledger!E:E,"<>*RD*",ledger!D:D,"Crinkle",ledger!C:C,"<>October Closing CF") ))))} -> 0 | H52: {=_xlfn.BYROW(B52, _xlfn.LAMBDA(_xlpm.party, SUMIFS(ledger!J:J, ledger!B:B, _xlpm.party, ledger!E:E, "<>*RD*", ledger!D:D, "Silky", ledger!C:C, "<>October Closing CF") ))} -> 0 | I52: {=_xlfn.BYROW(B52, _xlfn.LAMBDA(_xlpm.party, SUMIFS(ledger!J:J, ledger!B:B, _xlpm.party, ledger!E:E, "<>*RD*", ledger!D:D, "Slub", ledger!C:C, "<>October Closing CF") ))} -> 0 | J52: {=_xlfn.BYROW(B52, _xlfn.LAMBDA(_xlpm.party, SUMIFS(ledger!J:J, ledger!B:B, _xlpm.party, ledger!E:E, "<>*RD*", ledger!D:D, "Satin", ledger!C:C, "<>October Closing CF") ))} -> 0 | K52: =G52+H52+I52+J52 -> 0 | L52: =(SUMIF(Table14[Party],B52,Table14[Credit])) -> 0 | M52: =K52-L52 -> 0 | N52: 10.5 | O52: 13
B53: Sufi Nawaz Sahab | C53: 0 | D53: 0 | E53: 0 | F53: 0 | G53: {=(_xlfn.BYROW(B53,_xlfn.LAMBDA(_xlpm.party, (SUMIFS(ledger!J:J,ledger!B:B,_xlpm.party,ledger!E:E,"<>*RD*",ledger!D:D,"Chamki",ledger!C:C,"<>October Closing CF")+ SUMIFS(ledger!J:J,ledger!B:B,_xlpm.party,ledger!E:E,"<>*RD*",ledger!D:D,"Crinkle",ledger!C:C,"<>October Closing CF") ))))} -> 0 | H53: {=_xlfn.BYROW(B53, _xlfn.LAMBDA(_xlpm.party, SUMIFS(ledger!J:J, ledger!B:B, _xlpm.party, ledger!E:E, "<>*RD*", ledger!D:D, "Silky", ledger!C:C, "<>October Closing CF") ))} -> 0 | I53: {=_xlfn.BYROW(B53, _xlfn.LAMBDA(_xlpm.party, SUMIFS(ledger!J:J, ledger!B:B, _xlpm.party, ledger!E:E, "<>*RD*", ledger!D:D, "Slub", ledger!C:C, "<>October Closing CF") ))} -> 0 | J53: {=_xlfn.BYROW(B53, _xlfn.LAMBDA(_xlpm.party, SUMIFS(ledger!J:J, ledger!B:B, _xlpm.party, ledger!E:E, "<>*RD*", ledger!D:D, "Satin", ledger!C:C, "<>October Closing CF") ))} -> 0 | K53: =G53+H53+I53+J53 -> 0 | L53: =(SUMIF(Table14[Party],B53,Table14[Credit])) -> 0 | M53: =K53-L53 -> 0 | N53: 10 | O53: 12
B54: Sajad Khan | C54: 188107 | D54: 172007.13 | E54: 172007.13 | F54: 0 | G54: {=(_xlfn.BYROW(B54,_xlfn.LAMBDA(_xlpm.party, (SUMIFS(ledger!J:J,ledger!B:B,_xlpm.party,ledger!E:E,"<>*RD*",ledger!D:D,"Chamki",ledger!C:C,"<>October Closing CF")+ SUMIFS(ledger!J:J,ledger!B:B,_xlpm.party,ledger!E:E,"<>*RD*",ledger!D:D,"Crinkle",ledger!C:C,"<>October Closing CF") ))))} -> 1720071.3 | H54: {=_xlfn.BYROW(B54, _xlfn.LAMBDA(_xlpm.party, SUMIFS(ledger!J:J, ledger!B:B, _xlpm.party, ledger!E:E, "<>*RD*", ledger!D:D, "Silky", ledger!C:C, "<>October Closing CF") ))} -> 0 | I54: {=_xlfn.BYROW(B54, _xlfn.LAMBDA(_xlpm.party, SUMIFS(ledger!J:J, ledger!B:B, _xlpm.party, ledger!E:E, "<>*RD*", ledger!D:D, "Slub", ledger!C:C, "<>October Closing CF") ))} -> 0 | J54: {=_xlfn.BYROW(B54, _xlfn.LAMBDA(_xlpm.party, SUMIFS(ledger!J:J, ledger!B:B, _xlpm.party, ledger!E:E, "<>*RD*", ledger!D:D, "Satin", ledger!C:C, "<>October Closing CF") ))} -> 0 | K54: =G54+H54+I54+J54 -> 1720071.3 | L54: =(SUMIF(Table14[Party],B54,Table14[Credit])) -> 1353061 | M54: =K54-L54 -> 367010.32 | N54: 10 | O54: 12
B55: Raaz Fabrics | C55: 51518 | D55: 47108.632 | E55: 47108.632 | F55: 0 | G55: {=(_xlfn.BYROW(B55,_xlfn.LAMBDA(_xlpm.party, (SUMIFS(ledger!J:J,ledger!B:B,_xlpm.party,ledger!E:E,"<>*RD*",ledger!D:D,"Chamki",ledger!C:C,"<>October Closing CF")+ SUMIFS(ledger!J:J,ledger!B:B,_xlpm.party,ledger!E:E,"<>*RD*",ledger!D:D,"Crinkle",ledger!C:C,"<>October Closing CF") ))))} -> 471086.32 | H55: {=_xlfn.BYROW(B55, _xlfn.LAMBDA(_xlpm.party, SUMIFS(ledger!J:J, ledger!B:B, _xlpm.party, ledger!E:E, "<>*RD*", ledger!D:D, "Silky", ledger!C:C, "<>October Closing CF") ))} -> 0 | I55: {=_xlfn.BYROW(B55, _xlfn.LAMBDA(_xlpm.party, SUMIFS(ledger!J:J, ledger!B:B, _xlpm.party, ledger!E:E, "<>*RD*", ledger!D:D, "Slub", ledger!C:C, "<>October Closing CF") ))} -> 0 | J55: {=_xlfn.BYROW(B55, _xlfn.LAMBDA(_xlpm.party, SUMIFS(ledger!J:J, ledger!B:B, _xlpm.party, ledger!E:E, "<>*RD*", ledger!D:D, "Satin", ledger!C:C, "<>October Closing CF") ))} -> 0 | K55: =G55+H55+I55+J55 -> 471086.32 | L55: =(SUMIF(Table14[Party],B55,Table14[Credit])) -> 100000 | M55: =K55-L55 -> 371086.32 | N55: 10 | O55: 12
B56: Azam | C56: 152757 | D56: 139682.7 | E56: 139682.7 | F56: 0 | G56: {=(_xlfn.BYROW(B56,_xlfn.LAMBDA(_xlpm.party, (SUMIFS(ledger!J:J,ledger!B:B,_xlpm.party,ledger!E:E,"<>*RD*",ledger!D:D,"Chamki",ledger!C:C,"<>October Closing CF")+ SUMIFS(ledger!J:J,ledger!B:B,_xlpm.party,ledger!E:E,"<>*RD*",ledger!D:D,"Crinkle",ledger!C:C,"<>October Closing CF") ))))} -> 1396827 | H56: {=_xlfn.BYROW(B56, _xlfn.LAMBDA(_xlpm.party, SUMIFS(ledger!J:J, ledger!B:B, _xlpm.party, ledger!E:E, "<>*RD*", ledger!D:D, "Silky", ledger!C:C, "<>October Closing CF") ))} -> 0 | I56: {=_xlfn.BYROW(B56, _xlfn.LAMBDA(_xlpm.party, SUMIFS(ledger!J:J, ledger!B:B, _xlpm.party, ledger!E:E, "<>*RD*", ledger!D:D, "Slub", ledger!C:C, "<>October Closing CF") ))} -> 0 | J56: {=_xlfn.BYROW(B56, _xlfn.LAMBDA(_xlpm.party, SUMIFS(ledger!J:J, ledger!B:B, _xlpm.party, ledger!E:E, "<>*RD*", ledger!D:D, "Satin", ledger!C:C, "<>October Closing CF") ))} -> 0 | K56: =G56+H56+I56+J56 -> 1396827 | L56: =(SUMIF(Table14[Party],B56,Table14[Credit])) -> 1705000 | M56: =K56-L56 -> -308173.01 | N56: 10 | O56: 12
B57: Ubaidullah | C57: 0 | D57: 0 | E57: 0 | F57: 0 | G57: {=(_xlfn.BYROW(B57,_xlfn.LAMBDA(_xlpm.party, (SUMIFS(ledger!J:J,ledger!B:B,_xlpm.party,ledger!E:E,"<>*RD*",ledger!D:D,"Chamki",ledger!C:C,"<>October Closing CF")+ SUMIFS(ledger!J:J,ledger!B:B,_xlpm.party,ledger!E:E,"<>*RD*",ledger!D:D,"Crinkle",ledger!C:C,"<>October Closing CF") ))))} -> 0 | H57: {=_xlfn.BYROW(B57, _xlfn.LAMBDA(_xlpm.party, SUMIFS(ledger!J:J, ledger!B:B, _xlpm.party, ledger!E:E, "<>*RD*", ledger!D:D, "Silky", ledger!C:C, "<>October Closing CF") ))} -> 0 | I57: {=_xlfn.BYROW(B57, _xlfn.LAMBDA(_xlpm.party, SUMIFS(ledger!J:J, ledger!B:B, _xlpm.party, ledger!E:E, "<>*RD*", ledger!D:D, "Slub", ledger!C:C, "<>October Closing CF") ))} -> 0 | J57: {=_xlfn.BYROW(B57, _xlfn.LAMBDA(_xlpm.party, SUMIFS(ledger!J:J, ledger!B:B, _xlpm.party, ledger!E:E, "<>*RD*", ledger!D:D, "Satin", ledger!C:C, "<>October Closing CF") ))} -> 0 | K57: =G57+H57+I57+J57 -> 0 | L57: =SUMIF(Table14[Party], B57, Table14[Credit]) -> 10040 | M57: =K57-L57 -> -10040 | N57: 10 | O57: 12 | U57: Row Labels | V57: Sum of Tiyaar | W57: Sum of Total
B58: Ashraf Zia | C58: 0 | D58: 0 | E58: 0 | F58: 0 | G58: {=(_xlfn.BYROW(B58,_xlfn.LAMBDA(_xlpm.party, (SUMIFS(ledger!J:J,ledger!B:B,_xlpm.party,ledger!E:E,"<>*RD*",ledger!D:D,"Chamki",ledger!C:C,"<>October Closing CF")+ SUMIFS(ledger!J:J,ledger!B:B,_xlpm.party,ledger!E:E,"<>*RD*",ledger!D:D,"Crinkle",ledger!C:C,"<>October Closing CF") ))))} -> 0 | H58: {=_xlfn.BYROW(B58, _xlfn.LAMBDA(_xlpm.party, SUMIFS(ledger!J:J, ledger!B:B, _xlpm.party, ledger!E:E, "<>*RD*", ledger!D:D, "Silky", ledger!C:C, "<>October Closing CF") ))} -> 0 | I58: {=_xlfn.BYROW(B58, _xlfn.LAMBDA(_xlpm.party, SUMIFS(ledger!J:J, ledger!B:B, _xlpm.party, ledger!E:E, "<>*RD*", ledger!D:D, "Slub", ledger!C:C, "<>October Closing CF") ))} -> 0 | J58: {=_xlfn.BYROW(B58, _xlfn.LAMBDA(_xlpm.party, SUMIFS(ledger!J:J, ledger!B:B, _xlpm.party, ledger!E:E, "<>*RD*", ledger!D:D, "Satin", ledger!C:C, "<>October Closing CF") ))} -> 0 | K58: =G58+H58+I58+J58 -> 0 | L58: =SUMIF(Table14[Party], B58, Table14[Credit]) -> 130000 | M58: =K58-L58 -> -130000 | N58: 12 | O58: 12 | U58: BSC | V58: 232352.78 | W58: 2524052.7
B59: Hafiz Qureshi | C59: 70324 | D59: 64305.048 | E59: 64305.048 | F59: 0 | G59: {=(_xlfn.BYROW(B59,_xlfn.LAMBDA(_xlpm.party, (SUMIFS(ledger!J:J,ledger!B:B,_xlpm.party,ledger!E:E,"<>*RD*",ledger!D:D,"Chamki",ledger!C:C,"<>October Closing CF")+ SUMIFS(ledger!J:J,ledger!B:B,_xlpm.party,ledger!E:E,"<>*RD*",ledger!D:D,"Crinkle",ledger!C:C,"<>October Closing CF") ))))} -> 643050.48 | H59: {=_xlfn.BYROW(B59, _xlfn.LAMBDA(_xlpm.party, SUMIFS(ledger!J:J, ledger!B:B, _xlpm.party, ledger!E:E, "<>*RD*", ledger!D:D, "Silky", ledger!C:C, "<>October Closing CF") ))} -> 0 | I59: {=_xlfn.BYROW(B59, _xlfn.LAMBDA(_xlpm.party, SUMIFS(ledger!J:J, ledger!B:B, _xlpm.party, ledger!E:E, "<>*RD*", ledger!D:D, "Slub", ledger!C:C, "<>October Closing CF") ))} -> 0 | J59: {=_xlfn.BYROW(B59, _xlfn.LAMBDA(_xlpm.party, SUMIFS(ledger!J:J, ledger!B:B, _xlpm.party, ledger!E:E, "<>*RD*", ledger!D:D, "Satin", ledger!C:C, "<>October Closing CF") ))} -> 0 | K59: =G59+H59+I59+J59 -> 643050.48 | L59: =SUMIF(Table14[Party], B59, Table14[Credit]) -> 605980 | M59: =K59-L59 -> 37070.475 | N59: 10 | O59: 12 | U59: Ejaz Sahab | V59: 105662.95 | W59: 1267955.4
B60: Badshah Fabrics | C60: 74560 | D60: 68178.493 | E60: 14119.422 | F60: 54059.071 | G60: {=(_xlfn.BYROW(B60,_xlfn.LAMBDA(_xlpm.party, (SUMIFS(ledger!J:J,ledger!B:B,_xlpm.party,ledger!E:E,"<>*RD*",ledger!D:D,"Chamki",ledger!C:C,"<>October Closing CF")+ SUMIFS(ledger!J:J,ledger!B:B,_xlpm.party,ledger!E:E,"<>*RD*",ledger!D:D,"Crinkle",ledger!C:C,"<>October Closing CF") ))))} -> 141194.22 | H60: {=_xlfn.BYROW(B60, _xlfn.LAMBDA(_xlpm.party, SUMIFS(ledger!J:J, ledger!B:B, _xlpm.party, ledger!E:E, "<>*RD*", ledger!D:D, "Silky", ledger!C:C, "<>October Closing CF") ))} -> 702767.92 | I60: {=_xlfn.BYROW(B60, _xlfn.LAMBDA(_xlpm.party, SUMIFS(ledger!J:J, ledger!B:B, _xlpm.party, ledger!E:E, "<>*RD*", ledger!D:D, "Slub", ledger!C:C, "<>October Closing CF") ))} -> 0 | J60: {=_xlfn.BYROW(B60, _xlfn.LAMBDA(_xlpm.party, SUMIFS(ledger!J:J, ledger!B:B, _xlpm.party, ledger!E:E, "<>*RD*", ledger!D:D, "Satin", ledger!C:C, "<>October Closing CF") ))} -> 0 | K60: =G60+H60+I60+J60 -> 843962.14 | L60: =SUMIF(Table14[Party], B60, Table14[Credit]) -> 925217 | M60: =K60-L60 -> -81254.857 | N60: 10 | O60: 12 | U60: Arshad | V60: 193527.8 | W60: 2061914.8
B61: Reject | C61: 0 | D61: 0 | E61: 0 | F61: 0 | G61: {=(_xlfn.BYROW(B61,_xlfn.LAMBDA(_xlpm.party, (SUMIFS(ledger!J:J,ledger!B:B,_xlpm.party,ledger!E:E,"<>*RD*",ledger!D:D,"Chamki",ledger!C:C,"<>October Closing CF")+ SUMIFS(ledger!J:J,ledger!B:B,_xlpm.party,ledger!E:E,"<>*RD*",ledger!D:D,"Crinkle",ledger!C:C,"<>October Closing CF") ))))} -> 0 | H61: {=_xlfn.BYROW(B61, _xlfn.LAMBDA(_xlpm.party, SUMIFS(ledger!J:J, ledger!B:B, _xlpm.party, ledger!E:E, "<>*RD*", ledger!D:D, "Silky", ledger!C:C, "<>October Closing CF") ))} -> 0 | I61: {=_xlfn.BYROW(B61, _xlfn.LAMBDA(_xlpm.party, SUMIFS(ledger!J:J, ledger!B:B, _xlpm.party, ledger!E:E, "<>*RD*", ledger!D:D, "Slub", ledger!C:C, "<>October Closing CF") ))} -> 0 | J61: {=_xlfn.BYROW(B61, _xlfn.LAMBDA(_xlpm.party, SUMIFS(ledger!J:J, ledger!B:B, _xlpm.party, ledger!E:E, "<>*RD*", ledger!D:D, "Satin", ledger!C:C, "<>October Closing CF") ))} -> 0 | K61: =G61+H61+I61+J61 -> 0 | L61: =SUMIF(Table14[Party], B61, Table14[Credit]) -> 0 | M61: =K61-L61 -> 0 | N61: 10 | O61: 12 | U61: Shehzad Kamoki | V61: 0 | W61: 0
B62: Amjad 7up | C62: 0 | D62: 0 | E62: 0 | F62: 0 | G62: {=(_xlfn.BYROW(B62,_xlfn.LAMBDA(_xlpm.party, (SUMIFS(ledger!J:J,ledger!B:B,_xlpm.party,ledger!E:E,"<>*RD*",ledger!D:D,"Chamki",ledger!C:C,"<>October Closing CF")+ SUMIFS(ledger!J:J,ledger!B:B,_xlpm.party,ledger!E:E,"<>*RD*",ledger!D:D,"Crinkle",ledger!C:C,"<>October Closing CF") ))))} -> 0 | H62: {=_xlfn.BYROW(B62, _xlfn.LAMBDA(_xlpm.party, SUMIFS(ledger!J:J, ledger!B:B, _xlpm.party, ledger!E:E, "<>*RD*", ledger!D:D, "Silky", ledger!C:C, "<>October Closing CF") ))} -> 0 | I62: {=_xlfn.BYROW(B62, _xlfn.LAMBDA(_xlpm.party, SUMIFS(ledger!J:J, ledger!B:B, _xlpm.party, ledger!E:E, "<>*RD*", ledger!D:D, "Slub", ledger!C:C, "<>October Closing CF") ))} -> 0 | J62: {=_xlfn.BYROW(B62, _xlfn.LAMBDA(_xlpm.party, SUMIFS(ledger!J:J, ledger!B:B, _xlpm.party, ledger!E:E, "<>*RD*", ledger!D:D, "Satin", ledger!C:C, "<>October Closing CF") ))} -> 0 | K62: =G62+H62+I62+J62 -> 0 | L62: =SUMIF(Table14[Party], B62, Table14[Credit]) -> 0 | M62: =K62-L62 -> 0 | N62: 10 | O62: 12 | U62: Sufi Nawaz Sahab | V62: 0 | W62: 0
B63: Hazrat Khan | C63: 0 | D63: 0 | E63: 0 | F63: 0 | G63: {=(_xlfn.BYROW(B63,_xlfn.LAMBDA(_xlpm.party, (SUMIFS(ledger!J:J,ledger!B:B,_xlpm.party,ledger!E:E,"<>*RD*",ledger!D:D,"Chamki",ledger!C:C,"<>October Closing CF")+ SUMIFS(ledger!J:J,ledger!B:B,_xlpm.party,ledger!E:E,"<>*RD*",ledger!D:D,"Crinkle",ledger!C:C,"<>October Closing CF") ))))} -> 0 | H63: {=_xlfn.BYROW(B63, _xlfn.LAMBDA(_xlpm.party, SUMIFS(ledger!J:J, ledger!B:B, _xlpm.party, ledger!E:E, "<>*RD*", ledger!D:D, "Silky", ledger!C:C, "<>October Closing CF") ))} -> 0 | I63: {=_xlfn.BYROW(B63, _xlfn.LAMBDA(_xlpm.party, SUMIFS(ledger!J:J, ledger!B:B, _xlpm.party, ledger!E:E, "<>*RD*", ledger!D:D, "Slub", ledger!C:C, "<>October Closing CF") ))} -> 0 | J63: {=_xlfn.BYROW(B63, _xlfn.LAMBDA(_xlpm.party, SUMIFS(ledger!J:J, ledger!B:B, _xlpm.party, ledger!E:E, "<>*RD*", ledger!D:D, "Satin", ledger!C:C, "<>October Closing CF") ))} -> 0 | K63: =G63+H63+I63+J63 -> 0 | L63: =SUMIF(Table14[Party], B63, Table14[Credit]) -> 0 | M63: =K63-L63 -> 0 | N63: 10 | O63: 12 | U63: Sajad Khan | V63: 172007.13 | W63: 1720071.3
B64: Haseeb Shamsi | C64: 0 | D64: 0 | E64: 0 | F64: 0 | G64: {=(_xlfn.BYROW(B64,_xlfn.LAMBDA(_xlpm.party, (SUMIFS(ledger!J:J,ledger!B:B,_xlpm.party,ledger!E:E,"<>*RD*",ledger!D:D,"Chamki",ledger!C:C,"<>October Closing CF")+ SUMIFS(ledger!J:J,ledger!B:B,_xlpm.party,ledger!E:E,"<>*RD*",ledger!D:D,"Crinkle",ledger!C:C,"<>October Closing CF") ))))} -> 0 | H64: {=_xlfn.BYROW(B64, _xlfn.LAMBDA(_xlpm.party, SUMIFS(ledger!J:J, ledger!B:B, _xlpm.party, ledger!E:E, "<>*RD*", ledger!D:D, "Silky", ledger!C:C, "<>October Closing CF") ))} -> 0 | I64: {=_xlfn.BYROW(B64, _xlfn.LAMBDA(_xlpm.party, SUMIFS(ledger!J:J, ledger!B:B, _xlpm.party, ledger!E:E, "<>*RD*", ledger!D:D, "Slub", ledger!C:C, "<>October Closing CF") ))} -> 0 | J64: {=_xlfn.BYROW(B64, _xlfn.LAMBDA(_xlpm.party, SUMIFS(ledger!J:J, ledger!B:B, _xlpm.party, ledger!E:E, "<>*RD*", ledger!D:D, "Satin", ledger!C:C, "<>October Closing CF") ))} -> 0 | K64: =G64+H64+I64+J64 -> 0 | L64: =SUMIF(Table14[Party], B81, Table14[Credit]) -> 0 | M64: =K64-L64 -> 0 | N64: 10 | O64: 12 | U64: Raaz Fabrics | V64: 47108.632 | W64: 471086.32
B65: Faizan | C65: 216790 | D65: 198235.19 | E65: 0 | F65: 198235.19 | G65: {=(_xlfn.BYROW(B65,_xlfn.LAMBDA(_xlpm.party, (SUMIFS(ledger!J:J,ledger!B:B,_xlpm.party,ledger!E:E,"<>*RD*",ledger!D:D,"Chamki",ledger!C:C,"<>October Closing CF")+ SUMIFS(ledger!J:J,ledger!B:B,_xlpm.party,ledger!E:E,"<>*RD*",ledger!D:D,"Crinkle",ledger!C:C,"<>October Closing CF") ))))} -> 0 | H65: {=_xlfn.BYROW(B65, _xlfn.LAMBDA(_xlpm.party, SUMIFS(ledger!J:J, ledger!B:B, _xlpm.party, ledger!E:E, "<>*RD*", ledger!D:D, "Silky", ledger!C:C, "<>October Closing CF") ))} -> 2577057.4 | I65: {=_xlfn.BYROW(B65, _xlfn.LAMBDA(_xlpm.party, SUMIFS(ledger!J:J, ledger!B:B, _xlpm.party, ledger!E:E, "<>*RD*", ledger!D:D, "Slub", ledger!C:C, "<>October Closing CF") ))} -> 0 | J65: {=_xlfn.BYROW(B65, _xlfn.LAMBDA(_xlpm.party, SUMIFS(ledger!J:J, ledger!B:B, _xlpm.party, ledger!E:E, "<>*RD*", ledger!D:D, "Satin", ledger!C:C, "<>October Closing CF") ))} -> 0 | K65: =G65+H65+I65+J65 -> 2577057.4 | L65: =SUMIF(Table14[Party], B65, Table14[Credit]) -> 2000000 | M65: =K65-L65 -> 577057.43 | N65: 10 | O65: 13 | U65: Azam | V65: 139682.7 | W65: 1396827
B66: Shafique Ansari | C66: 0 | D66: 0 | E66: 0 | F66: 0 | G66: {=(_xlfn.BYROW(B66,_xlfn.LAMBDA(_xlpm.party, (SUMIFS(ledger!J:J,ledger!B:B,_xlpm.party,ledger!E:E,"<>*RD*",ledger!D:D,"Chamki",ledger!C:C,"<>October Closing CF")+ SUMIFS(ledger!J:J,ledger!B:B,_xlpm.party,ledger!E:E,"<>*RD*",ledger!D:D,"Crinkle",ledger!C:C,"<>October Closing CF") ))))} -> 0 | H66: {=_xlfn.BYROW(B66, _xlfn.LAMBDA(_xlpm.party, SUMIFS(ledger!J:J, ledger!B:B, _xlpm.party, ledger!E:E, "<>*RD*", ledger!D:D, "Silky", ledger!C:C, "<>October Closing CF") ))} -> 0 | I66: {=_xlfn.BYROW(B66, _xlfn.LAMBDA(_xlpm.party, SUMIFS(ledger!J:J, ledger!B:B, _xlpm.party, ledger!E:E, "<>*RD*", ledger!D:D, "Slub", ledger!C:C, "<>October Closing CF") ))} -> 0 | J66: {=_xlfn.BYROW(B66, _xlfn.LAMBDA(_xlpm.party, SUMIFS(ledger!J:J, ledger!B:B, _xlpm.party, ledger!E:E, "<>*RD*", ledger!D:D, "Satin", ledger!C:C, "<>October Closing CF") ))} -> 0 | K66: =G66+H66+I66+J66 -> 0 | L66: =SUMIF(Table14[Party], B66, Table14[Credit]) -> 0 | M66: =K66-L66 -> 0 | N66: 10 | O66: 12 | U66: Ubaidullah | V66: 0 | W66: 0
B67: Amjad sohail | C67: 173560 | D67: 158705.19 | E67: 158705.19 | F67: 0 | G67: {=(_xlfn.BYROW(B67,_xlfn.LAMBDA(_xlpm.party, (SUMIFS(ledger!J:J,ledger!B:B,_xlpm.party,ledger!E:E,"<>*RD*",ledger!D:D,"Chamki",ledger!C:C,"<>October Closing CF")+ SUMIFS(ledger!J:J,ledger!B:B,_xlpm.party,ledger!E:E,"<>*RD*",ledger!D:D,"Crinkle",ledger!C:C,"<>October Closing CF") ))))} -> 1587051.9 | H67: {=_xlfn.BYROW(B67, _xlfn.LAMBDA(_xlpm.party, SUMIFS(ledger!J:J, ledger!B:B, _xlpm.party, ledger!E:E, "<>*RD*", ledger!D:D, "Silky", ledger!C:C, "<>October Closing CF") ))} -> 0 | I67: {=_xlfn.BYROW(B67, _xlfn.LAMBDA(_xlpm.party, SUMIFS(ledger!J:J, ledger!B:B, _xlpm.party, ledger!E:E, "<>*RD*", ledger!D:D, "Slub", ledger!C:C, "<>October Closing CF") ))} -> 0 | J67: {=_xlfn.BYROW(B67, _xlfn.LAMBDA(_xlpm.party, SUMIFS(ledger!J:J, ledger!B:B, _xlpm.party, ledger!E:E, "<>*RD*", ledger!D:D, "Satin", ledger!C:C, "<>October Closing CF") ))} -> 0 | K67: =G67+H67+I67+J67 -> 1587051.9 | L67: =SUMIF(Table14[Party], B67, Table14[Credit]) -> 1500000 | M67: =K67-L67 -> 87051.939 | N67: 10 | O67: 12 | U67: Ashraf Zia | V67: 0 | W67: 0
B68: Salman Zaffar | C68: 55541 | D68: 50787.308 | E68: 14355.34 | F68: 31409.108 | G68: {=(_xlfn.BYROW(B68,_xlfn.LAMBDA(_xlpm.party, (SUMIFS(ledger!J:J,ledger!B:B,_xlpm.party,ledger!E:E,"<>*RD*",ledger!D:D,"Chamki",ledger!C:C,"<>October Closing CF")+ SUMIFS(ledger!J:J,ledger!B:B,_xlpm.party,ledger!E:E,"<>*RD*",ledger!D:D,"Crinkle",ledger!C:C,"<>October Closing CF") ))))} -> 143553.4 | H68: {=_xlfn.BYROW(B68, _xlfn.LAMBDA(_xlpm.party, SUMIFS(ledger!J:J, ledger!B:B, _xlpm.party, ledger!E:E, "<>*RD*", ledger!D:D, "Silky", ledger!C:C, "<>October Closing CF") ))} -> 408318.4 | I68: {=_xlfn.BYROW(B68, _xlfn.LAMBDA(_xlpm.party, SUMIFS(ledger!J:J, ledger!B:B, _xlpm.party, ledger!E:E, "<>*RD*", ledger!D:D, "Slub", ledger!C:C, "<>October Closing CF") ))} -> 0 | J68: {=_xlfn.BYROW(B68, _xlfn.LAMBDA(_xlpm.party, SUMIFS(ledger!J:J, ledger!B:B, _xlpm.party, ledger!E:E, "<>*RD*", ledger!D:D, "Satin", ledger!C:C, "<>October Closing CF") ))} -> 0 | K68: =G68+H68+I68+J68 -> 551871.8 | L68: =SUMIF(Table14[Party], B68, Table14[Credit]) -> 0 | M68: =K68-L68 -> 551871.8 | N68: 10 | O68: 12 | U68: Hafiz Qureshi | V68: 64305.048 | W68: 643050.48
B69: Shahid Qasayi | C69: 165343 | D69: 151191.48 | E69: 113495.79 | F69: 0 | G69: {=(_xlfn.BYROW(B69,_xlfn.LAMBDA(_xlpm.party, (SUMIFS(ledger!J:J,ledger!B:B,_xlpm.party,ledger!E:E,"<>*RD*",ledger!D:D,"Chamki",ledger!C:C,"<>October Closing CF")+ SUMIFS(ledger!J:J,ledger!B:B,_xlpm.party,ledger!E:E,"<>*RD*",ledger!D:D,"Crinkle",ledger!C:C,"<>October Closing CF") ))))} -> 1134957.9 | H69: {=_xlfn.BYROW(B69, _xlfn.LAMBDA(_xlpm.party, SUMIFS(ledger!J:J, ledger!B:B, _xlpm.party, ledger!E:E, "<>*RD*", ledger!D:D, "Silky", ledger!C:C, "<>October Closing CF") ))} -> 0 | I69: {=_xlfn.BYROW(B69, _xlfn.LAMBDA(_xlpm.party, SUMIFS(ledger!J:J, ledger!B:B, _xlpm.party, ledger!E:E, "<>*RD*", ledger!D:D, "Slub", ledger!C:C, "<>October Closing CF") ))} -> 0 | J69: {=_xlfn.BYROW(B69, _xlfn.LAMBDA(_xlpm.party, SUMIFS(ledger!J:J, ledger!B:B, _xlpm.party, ledger!E:E, "<>*RD*", ledger!D:D, "Satin", ledger!C:C, "<>October Closing CF") ))} -> 0 | K69: =G69+H69+I69+J69 -> 1134957.9 | L69: =SUMIF(Table14[Party], B69, Table14[Credit]) -> 1103325 | M69: =K69-L69 -> 31632.937 | N69: 10 | O69: 12 | U69: Badshah Fabrics | V69: 68178.493 | W69: 789903.07
B70: Hameed corporation | C70: 46404 | D70: 42432.334 | E70: 42432.334 | F70: 0 | G70: {=(_xlfn.BYROW(B70,_xlfn.LAMBDA(_xlpm.party, (SUMIFS(ledger!J:J,ledger!B:B,_xlpm.party,ledger!E:E,"<>*RD*",ledger!D:D,"Chamki",ledger!C:C,"<>October Closing CF")+ SUMIFS(ledger!J:J,ledger!B:B,_xlpm.party,ledger!E:E,"<>*RD*",ledger!D:D,"Crinkle",ledger!C:C,"<>October Closing CF") ))))} -> 424323.34 | H70: {=_xlfn.BYROW(B70, _xlfn.LAMBDA(_xlpm.party, SUMIFS(ledger!J:J, ledger!B:B, _xlpm.party, ledger!E:E, "<>*RD*", ledger!D:D, "Silky", ledger!C:C, "<>October Closing CF") ))} -> 0 | I70: {=_xlfn.BYROW(B70, _xlfn.LAMBDA(_xlpm.party, SUMIFS(ledger!J:J, ledger!B:B, _xlpm.party, ledger!E:E, "<>*RD*", ledger!D:D, "Slub", ledger!C:C, "<>October Closing CF") ))} -> 0 | J70: {=_xlfn.BYROW(B70, _xlfn.LAMBDA(_xlpm.party, SUMIFS(ledger!J:J, ledger!B:B, _xlpm.party, ledger!E:E, "<>*RD*", ledger!D:D, "Satin", ledger!C:C, "<>October Closing CF") ))} -> 0 | K70: =G70+H70+I70+J70 -> 424323.34 | L70: =SUMIF(Table14[Party], B70, Table14[Credit]) -> 424323 | M70: =K70-L70 -> 0.33577176 | U70: Reject | V70: 0 | W70: 0
B71: ibraheem behraam | C71: 35948 | D71: 32871.251 | E71: 0 | F71: 32871.251 | G71: {=(_xlfn.BYROW(B71,_xlfn.LAMBDA(_xlpm.party, (SUMIFS(ledger!J:J,ledger!B:B,_xlpm.party,ledger!E:E,"<>*RD*",ledger!D:D,"Chamki",ledger!C:C,"<>October Closing CF")+ SUMIFS(ledger!J:J,ledger!B:B,_xlpm.party,ledger!E:E,"<>*RD*",ledger!D:D,"Crinkle",ledger!C:C,"<>October Closing CF") ))))} -> 0 | H71: {=_xlfn.BYROW(B71, _xlfn.LAMBDA(_xlpm.party, SUMIFS(ledger!J:J, ledger!B:B, _xlpm.party, ledger!E:E, "<>*RD*", ledger!D:D, "Silky", ledger!C:C, "<>October Closing CF") ))} -> 427326.26 | I71: {=_xlfn.BYROW(B71, _xlfn.LAMBDA(_xlpm.party, SUMIFS(ledger!J:J, ledger!B:B, _xlpm.party, ledger!E:E, "<>*RD*", ledger!D:D, "Slub", ledger!C:C, "<>October Closing CF") ))} -> 0 | J71: {=_xlfn.BYROW(B71, _xlfn.LAMBDA(_xlpm.party, SUMIFS(ledger!J:J, ledger!B:B, _xlpm.party, ledger!E:E, "<>*RD*", ledger!D:D, "Satin", ledger!C:C, "<>October Closing CF") ))} -> 0 | K71: =G71+H71+I71+J71 -> 427326.26 | L71: =SUMIF(Table14[Party], B71, Table14[Credit]) -> 437000 | M71: =K71-L71 -> -9673.7381 | U71: Amjad 7up | V71: 0 | W71: 0
B72: Zia-ullah karachi | C72: 13622 | D72: 12456.108 | E72: 12456.108 | F72: 0 | G72: {=(_xlfn.BYROW(B72,_xlfn.LAMBDA(_xlpm.party, (SUMIFS(ledger!J:J,ledger!B:B,_xlpm.party,ledger!E:E,"<>*RD*",ledger!D:D,"Chamki",ledger!C:C,"<>October Closing CF")+ SUMIFS(ledger!J:J,ledger!B:B,_xlpm.party,ledger!E:E,"<>*RD*",ledger!D:D,"Crinkle",ledger!C:C,"<>October Closing CF") ))))} -> 124561.08 | H72: {=_xlfn.BYROW(B72, _xlfn.LAMBDA(_xlpm.party, SUMIFS(ledger!J:J, ledger!B:B, _xlpm.party, ledger!E:E, "<>*RD*", ledger!D:D, "Silky", ledger!C:C, "<>October Closing CF") ))} -> 0 | I72: {=_xlfn.BYROW(B72, _xlfn.LAMBDA(_xlpm.party, SUMIFS(ledger!J:J, ledger!B:B, _xlpm.party, ledger!E:E, "<>*RD*", ledger!D:D, "Slub", ledger!C:C, "<>October Closing CF") ))} -> 0 | J72: {=_xlfn.BYROW(B72, _xlfn.LAMBDA(_xlpm.party, SUMIFS(ledger!J:J, ledger!B:B, _xlpm.party, ledger!E:E, "<>*RD*", ledger!D:D, "Satin", ledger!C:C, "<>October Closing CF") ))} -> 0 | K72: =G72+H72+I72+J72 -> 124561.08 | L72: =SUMIF(Table14[Party], B72, Table14[Credit]) -> 137260 | M72: =K72-L72 -> -12698.917 | U72: Hazrat Khan | V72: 0 | W72: 0
G73: {=(_xlfn.BYROW(B73,_xlfn.LAMBDA(_xlpm.party, (SUMIFS(ledger!J:J,ledger!B:B,_xlpm.party,ledger!E:E,"<>*RD*",ledger!D:D,"Chamki",ledger!C:C,"<>October Closing CF")+ SUMIFS(ledger!J:J,ledger!B:B,_xlpm.party,ledger!E:E,"<>*RD*",ledger!D:D,"Crinkle",ledger!C:C,"<>October Closing CF") ))))} -> 0 | H73: {=_xlfn.BYROW(B73, _xlfn.LAMBDA(_xlpm.party, SUMIFS(ledger!J:J, ledger!B:B, _xlpm.party, ledger!E:E, "<>*RD*", ledger!D:D, "Silky", ledger!C:C, "<>October Closing CF") ))} -> 0 | I73: {=_xlfn.BYROW(B73, _xlfn.LAMBDA(_xlpm.party, SUMIFS(ledger!J:J, ledger!B:B, _xlpm.party, ledger!E:E, "<>*RD*", ledger!D:D, "Slub", ledger!C:C, "<>October Closing CF") ))} -> 0 | J73: {=_xlfn.BYROW(B73, _xlfn.LAMBDA(_xlpm.party, SUMIFS(ledger!J:J, ledger!B:B, _xlpm.party, ledger!E:E, "<>*RD*", ledger!D:D, "Satin", ledger!C:C, "<>October Closing CF") ))} -> 0 | K73: =G73+H73+I73+J73 -> 0 | L73: =SUMIF(Table14[Party], B73, Table14[Credit]) -> 0 | M73: =K73-L73 -> 0 | U73: Haseeb Shamsi | V73: 0 | W73: 0
G74: {=(_xlfn.BYROW(B74,_xlfn.LAMBDA(_xlpm.party, (SUMIFS(ledger!J:J,ledger!B:B,_xlpm.party,ledger!E:E,"<>*RD*",ledger!D:D,"Chamki",ledger!C:C,"<>October Closing CF")+ SUMIFS(ledger!J:J,ledger!B:B,_xlpm.party,ledger!E:E,"<>*RD*",ledger!D:D,"Crinkle",ledger!C:C,"<>October Closing CF") ))))} -> 0 | H74: {=_xlfn.BYROW(B74, _xlfn.LAMBDA(_xlpm.party, SUMIFS(ledger!J:J, ledger!B:B, _xlpm.party, ledger!E:E, "<>*RD*", ledger!D:D, "Silky", ledger!C:C, "<>October Closing CF") ))} -> 0 | I74: {=_xlfn.BYROW(B74, _xlfn.LAMBDA(_xlpm.party, SUMIFS(ledger!J:J, ledger!B:B, _xlpm.party, ledger!E:E, "<>*RD*", ledger!D:D, "Slub", ledger!C:C, "<>October Closing CF") ))} -> 0 | J74: {=_xlfn.BYROW(B74, _xlfn.LAMBDA(_xlpm.party, SUMIFS(ledger!J:J, ledger!B:B, _xlpm.party, ledger!E:E, "<>*RD*", ledger!D:D, "Satin", ledger!C:C, "<>October Closing CF") ))} -> 0 | K74: =G74+H74+I74+J74 -> 0 | L74: =SUMIF(Table14[Party], B74, Table14[Credit]) -> 0 | M74: =K74-L74 -> 0 | U74: Faizan | V74: 198235.19 | W74: 2378822.2
G75: {=(_xlfn.BYROW(B75,_xlfn.LAMBDA(_xlpm.party, (SUMIFS(ledger!J:J,ledger!B:B,_xlpm.party,ledger!E:E,"<>*RD*",ledger!D:D,"Chamki",ledger!C:C,"<>October Closing CF")+ SUMIFS(ledger!J:J,ledger!B:B,_xlpm.party,ledger!E:E,"<>*RD*",ledger!D:D,"Crinkle",ledger!C:C,"<>October Closing CF") ))))} -> 0 | H75: {=_xlfn.BYROW(B75, _xlfn.LAMBDA(_xlpm.party, SUMIFS(ledger!J:J, ledger!B:B, _xlpm.party, ledger!E:E, "<>*RD*", ledger!D:D, "Silky", ledger!C:C, "<>October Closing CF") ))} -> 0 | I75: {=_xlfn.BYROW(B75, _xlfn.LAMBDA(_xlpm.party, SUMIFS(ledger!J:J, ledger!B:B, _xlpm.party, ledger!E:E, "<>*RD*", ledger!D:D, "Slub", ledger!C:C, "<>October Closing CF") ))} -> 0 | J75: {=_xlfn.BYROW(B75, _xlfn.LAMBDA(_xlpm.party, SUMIFS(ledger!J:J, ledger!B:B, _xlpm.party, ledger!E:E, "<>*RD*", ledger!D:D, "Satin", ledger!C:C, "<>October Closing CF") ))} -> 0 | K75: =G75+H75+I75+J75 -> 0 | L75: =SUMIF(Table14[Party], B75, Table14[Credit]) -> 0 | M75: =K75-L75 -> 0 | U75: Grand Total | V75: 1221060.7 | W75: 13253683
G76: {=(_xlfn.BYROW(B76,_xlfn.LAMBDA(_xlpm.party, (SUMIFS(ledger!J:J,ledger!B:B,_xlpm.party,ledger!E:E,"<>*RD*",ledger!D:D,"Chamki",ledger!C:C,"<>October Closing CF")+ SUMIFS(ledger!J:J,ledger!B:B,_xlpm.party,ledger!E:E,"<>*RD*",ledger!D:D,"Crinkle",ledger!C:C,"<>October Closing CF") ))))} -> 0 | H76: {=_xlfn.BYROW(B76, _xlfn.LAMBDA(_xlpm.party, SUMIFS(ledger!J:J, ledger!B:B, _xlpm.party, ledger!E:E, "<>*RD*", ledger!D:D, "Silky", ledger!C:C, "<>October Closing CF") ))} -> 0 | I76: {=_xlfn.BYROW(B76, _xlfn.LAMBDA(_xlpm.party, SUMIFS(ledger!J:J, ledger!B:B, _xlpm.party, ledger!E:E, "<>*RD*", ledger!D:D, "Slub", ledger!C:C, "<>October Closing CF") ))} -> 0 | J76: {=_xlfn.BYROW(B76, _xlfn.LAMBDA(_xlpm.party, SUMIFS(ledger!J:J, ledger!B:B, _xlpm.party, ledger!E:E, "<>*RD*", ledger!D:D, "Satin", ledger!C:C, "<>October Closing CF") ))} -> 0 | K76: =G76+H76+I76+J76 -> 0 | L76: =SUMIF(Table14[Party], B76, Table14[Credit]) -> 0 | M76: =K76-L76 -> 0
G77: {=(_xlfn.BYROW(B77,_xlfn.LAMBDA(_xlpm.party, (SUMIFS(ledger!J:J,ledger!B:B,_xlpm.party,ledger!E:E,"<>*RD*",ledger!D:D,"Chamki",ledger!C:C,"<>October Closing CF")+ SUMIFS(ledger!J:J,ledger!B:B,_xlpm.party,ledger!E:E,"<>*RD*",ledger!D:D,"Crinkle",ledger!C:C,"<>October Closing CF") ))))} -> 0 | H77: {=_xlfn.BYROW(B77, _xlfn.LAMBDA(_xlpm.party, SUMIFS(ledger!J:J, ledger!B:B, _xlpm.party, ledger!E:E, "<>*RD*", ledger!D:D, "Silky", ledger!C:C, "<>October Closing CF") ))} -> 0 | I77: {=_xlfn.BYROW(B77, _xlfn.LAMBDA(_xlpm.party, SUMIFS(ledger!J:J, ledger!B:B, _xlpm.party, ledger!E:E, "<>*RD*", ledger!D:D, "Slub", ledger!C:C, "<>October Closing CF") ))} -> 0 | J77: {=_xlfn.BYROW(B77, _xlfn.LAMBDA(_xlpm.party, SUMIFS(ledger!J:J, ledger!B:B, _xlpm.party, ledger!E:E, "<>*RD*", ledger!D:D, "Satin", ledger!C:C, "<>October Closing CF") ))} -> 0 | K77: =G77+H77+I77+J77 -> 0 | L77: =SUMIF(Table14[Party], B77, Table14[Credit]) -> 0 | M77: =K77-L77 -> 0
G78: {=(_xlfn.BYROW(B78,_xlfn.LAMBDA(_xlpm.party, (SUMIFS(ledger!J:J,ledger!B:B,_xlpm.party,ledger!E:E,"<>*RD*",ledger!D:D,"Chamki",ledger!C:C,"<>October Closing CF")+ SUMIFS(ledger!J:J,ledger!B:B,_xlpm.party,ledger!E:E,"<>*RD*",ledger!D:D,"Crinkle",ledger!C:C,"<>October Closing CF") ))))} -> 0 | H78: {=_xlfn.BYROW(B78, _xlfn.LAMBDA(_xlpm.party, SUMIFS(ledger!J:J, ledger!B:B, _xlpm.party, ledger!E:E, "<>*RD*", ledger!D:D, "Silky", ledger!C:C, "<>October Closing CF") ))} -> 0 | I78: {=_xlfn.BYROW(B78, _xlfn.LAMBDA(_xlpm.party, SUMIFS(ledger!J:J, ledger!B:B, _xlpm.party, ledger!E:E, "<>*RD*", ledger!D:D, "Slub", ledger!C:C, "<>October Closing CF") ))} -> 0 | J78: {=_xlfn.BYROW(B78, _xlfn.LAMBDA(_xlpm.party, SUMIFS(ledger!J:J, ledger!B:B, _xlpm.party, ledger!E:E, "<>*RD*", ledger!D:D, "Satin", ledger!C:C, "<>October Closing CF") ))} -> 0 | K78: =G78+H78+I78+J78 -> 0 | L78: =SUMIF(Table14[Party], B78, Table14[Credit]) -> 0 | M78: =K78-L78 -> 0
B81: Billing (Previous)
B83: Parties: | C83: Gaz | D83: Total Metres | E83: Total Chamki | F83: Total Super Silky | G83: Billing (Chamki/Crinkle) | H83: Billing (Super Chamki) | K83: Adjusted Bill | L83: Amount Paid | M83: Balance | N83: Rate (Chamki) | O83: Rate (Super Silky)
B84: {=_xlfn.UNIQUE(Table1[Party Name])} -> BSC | C84: =_xlfn.XLOOKUP($B49,[1]Billing!$Q$5:$Q$29,[1]Billing!$R$5:$R$29) -> 2205408 | D84: =_xlfn.XLOOKUP($B49,[1]Billing!$Q$5:$Q$29,[1]Billing!$S$5:$S$29) -> 2016649.6 | E84: =_xlfn.XLOOKUP($B49,[1]Billing!$Q$5:$Q$29,[1]Billing!$T$5:$T$29) -> 1895402.3 | F84: =_xlfn.XLOOKUP($B49,[1]Billing!$Q$5:$Q$29,[1]Billing!$U$5:$U$29) -> 121247.26 | G84: =_xlfn.XLOOKUP($B49,[1]Billing!$Q$5:$Q$29,[1]Billing!$V$5:$V$29) -> 18954023 | H84: =_xlfn.XLOOKUP($B49,[1]Billing!$Q$5:$Q$29,[1]Billing!$W$5:$W$29) -> 1487858.4 | I84: =_xlfn.XLOOKUP($B49,[1]Billing!$Q$5:$Q$29,[1]Billing!$X$5:$X$29) -> 0 | J84: =_xlfn.XLOOKUP($B49,[1]Billing!$Q$5:$Q$29,[1]Billing!$Y$5:$Y$29) -> 0 | K84: =G84+H84+I84+J84 -> 20441882 | L84: =_xlfn.XLOOKUP($B49,[1]Billing!$Q$5:$Q$29,[1]Billing!$AA$5:$AA$29) -> 18411676 | M84: =K84-L84 -> 2030205.9 | N84: 10 | O84: 13
B85: Ejaz Sahab | C85: =_xlfn.XLOOKUP($B50,[1]Billing!$Q$5:$Q$29,[1]Billing!$R$5:$R$29) -> 277841 | D85: =_xlfn.XLOOKUP($B50,[1]Billing!$Q$5:$Q$29,[1]Billing!$S$5:$S$29) -> 254060.9 | E85: =_xlfn.XLOOKUP($B50,[1]Billing!$Q$5:$Q$29,[1]Billing!$T$5:$T$29) -> 148145.57 | F85: =_xlfn.XLOOKUP($B50,[1]Billing!$Q$5:$Q$29,[1]Billing!$U$5:$U$29) -> 105915.33 | G85: =_xlfn.XLOOKUP($B50,[1]Billing!$Q$5:$Q$29,[1]Billing!$V$5:$V$29) -> 1481455.7 | H85: =_xlfn.XLOOKUP($B50,[1]Billing!$Q$5:$Q$29,[1]Billing!$W$5:$W$29) -> 1317755.1 | I85: =_xlfn.XLOOKUP($B50,[1]Billing!$Q$5:$Q$29,[1]Billing!$X$5:$X$29) -> 0 | J85: =_xlfn.XLOOKUP($B50,[1]Billing!$Q$5:$Q$29,[1]Billing!$Y$5:$Y$29) -> 0 | K85: =G85+H85+I85+J85 -> 2799210.9 | L85: =_xlfn.XLOOKUP($B50,[1]Billing!$Q$5:$Q$29,[1]Billing!$AA$5:$AA$29) -> 3163904 | M85: =K85-L85 -> -364693.14 | N85: 10 | O85: 13
B86: Arshad | C86: =_xlfn.XLOOKUP($B51,[1]Billing!$Q$5:$Q$29,[1]Billing!$R$5:$R$29) -> 445506 | D86: =_xlfn.XLOOKUP($B51,[1]Billing!$Q$5:$Q$29,[1]Billing!$S$5:$S$29) -> 407375.64 | E86: =_xlfn.XLOOKUP($B51,[1]Billing!$Q$5:$Q$29,[1]Billing!$T$5:$T$29) -> 392581.38 | F86: =_xlfn.XLOOKUP($B51,[1]Billing!$Q$5:$Q$29,[1]Billing!$U$5:$U$29) -> 14794.257 | G86: =_xlfn.XLOOKUP($B51,[1]Billing!$Q$5:$Q$29,[1]Billing!$V$5:$V$29) -> 3925813.8 | H86: =_xlfn.XLOOKUP($B51,[1]Billing!$Q$5:$Q$29,[1]Billing!$W$5:$W$29) -> 177531.09 | I86: =_xlfn.XLOOKUP($B51,[1]Billing!$Q$5:$Q$29,[1]Billing!$X$5:$X$29) -> 0 | J86: =_xlfn.XLOOKUP($B51,[1]Billing!$Q$5:$Q$29,[1]Billing!$Y$5:$Y$29) -> 0 | K86: =G86+H86+I86+J86 -> 4103344.9 | L86: =_xlfn.XLOOKUP($B51,[1]Billing!$Q$5:$Q$29,[1]Billing!$AA$5:$AA$29) -> 4102935 | M86: =K86-L86 -> 409.91587 | N86: 10 | O86: 13
B87: Shehzad Kamoki | C87: =_xlfn.XLOOKUP($B52,[1]Billing!$Q$5:$Q$29,[1]Billing!$R$5:$R$29) -> 134607 | D87: =_xlfn.XLOOKUP($B52,[1]Billing!$Q$5:$Q$29,[1]Billing!$S$5:$S$29) -> 123086.14 | E87: =_xlfn.XLOOKUP($B52,[1]Billing!$Q$5:$Q$29,[1]Billing!$T$5:$T$29) -> 123086.14 | F87: =_xlfn.XLOOKUP($B52,[1]Billing!$Q$5:$Q$29,[1]Billing!$U$5:$U$29) -> 0 | G87: =_xlfn.XLOOKUP($B52,[1]Billing!$Q$5:$Q$29,[1]Billing!$V$5:$V$29) -> 1269270.3 | H87: =_xlfn.XLOOKUP($B52,[1]Billing!$Q$5:$Q$29,[1]Billing!$W$5:$W$29) -> 0 | I87: =_xlfn.XLOOKUP($B52,[1]Billing!$Q$5:$Q$29,[1]Billing!$X$5:$X$29) -> 0 | J87: =_xlfn.XLOOKUP($B52,[1]Billing!$Q$5:$Q$29,[1]Billing!$Y$5:$Y$29) -> 0 | K87: =G87+H87+I87+J87 -> 1269270.3 | L87: =_xlfn.XLOOKUP($B52,[1]Billing!$Q$5:$Q$29,[1]Billing!$AA$5:$AA$29) -> 1268740 | M87: =K87-L87 -> 530.34404 | N87: 10.5 | O87: 13
B88: Sufi Nawaz Sahab | C88: =_xlfn.XLOOKUP($B53,[1]Billing!$Q$5:$Q$29,[1]Billing!$R$5:$R$29) -> 1186725 | D88: =_xlfn.XLOOKUP($B53,[1]Billing!$Q$5:$Q$29,[1]Billing!$S$5:$S$29) -> 1085154.5 | E88: =_xlfn.XLOOKUP($B53,[1]Billing!$Q$5:$Q$29,[1]Billing!$T$5:$T$29) -> 599330.65 | F88: =_xlfn.XLOOKUP($B53,[1]Billing!$Q$5:$Q$29,[1]Billing!$U$5:$U$29) -> 485823.88 | G88: =_xlfn.XLOOKUP($B53,[1]Billing!$Q$5:$Q$29,[1]Billing!$V$5:$V$29) -> 5408917.9 | H88: =_xlfn.XLOOKUP($B53,[1]Billing!$Q$5:$Q$29,[1]Billing!$W$5:$W$29) -> 5829886.6 | I88: =_xlfn.XLOOKUP($B53,[1]Billing!$Q$5:$Q$29,[1]Billing!$X$5:$X$29) -> 0 | J88: =_xlfn.XLOOKUP($B53,[1]Billing!$Q$5:$Q$29,[1]Billing!$Y$5:$Y$29) -> 0 | K88: =G88+H88+I88+J88 -> 11238804 | L88: =_xlfn.XLOOKUP($B53,[1]Billing!$Q$5:$Q$29,[1]Billing!$AA$5:$AA$29) -> 10629100 | M88: =K88-L88 -> 609704.47 | N88: 10 | O88: 13
B89: Sajad Khan | C89: =_xlfn.XLOOKUP($B54,[1]Billing!$Q$5:$Q$29,[1]Billing!$R$5:$R$29) -> 604680 | D89: =_xlfn.XLOOKUP($B54,[1]Billing!$Q$5:$Q$29,[1]Billing!$S$5:$S$29) -> 552926.12 | E89: =_xlfn.XLOOKUP($B54,[1]Billing!$Q$5:$Q$29,[1]Billing!$T$5:$T$29) -> 547436.91 | F89: =_xlfn.XLOOKUP($B54,[1]Billing!$Q$5:$Q$29,[1]Billing!$U$5:$U$29) -> 0 | G89: =_xlfn.XLOOKUP($B54,[1]Billing!$Q$5:$Q$29,[1]Billing!$V$5:$V$29) -> 5474369.1 | H89: =_xlfn.XLOOKUP($B54,[1]Billing!$Q$5:$Q$29,[1]Billing!$W$5:$W$29) -> 0 | I89: =_xlfn.XLOOKUP($B54,[1]Billing!$Q$5:$Q$29,[1]Billing!$X$5:$X$29) -> 71359.729 | J89: =_xlfn.XLOOKUP($B54,[1]Billing!$Q$5:$Q$29,[1]Billing!$Y$5:$Y$29) -> 0 | K89: =G89+H89+I89+J89 -> 5545728.8 | L89: =_xlfn.XLOOKUP($B54,[1]Billing!$Q$5:$Q$29,[1]Billing!$AA$5:$AA$29) -> 5544810 | M89: =K89-L89 -> 918.78566 | N89: 10 | O89: 13
B90: Raaz Fabrics | C90: =_xlfn.XLOOKUP($B55,[1]Billing!$Q$5:$Q$29,[1]Billing!$R$5:$R$29) -> 100916 | D90: =_xlfn.XLOOKUP($B55,[1]Billing!$Q$5:$Q$29,[1]Billing!$S$5:$S$29) -> 92278.713 | E90: =_xlfn.XLOOKUP($B55,[1]Billing!$Q$5:$Q$29,[1]Billing!$T$5:$T$29) -> 92278.713 | F90: =_xlfn.XLOOKUP($B55,[1]Billing!$Q$5:$Q$29,[1]Billing!$U$5:$U$29) -> 0 | G90: =_xlfn.XLOOKUP($B55,[1]Billing!$Q$5:$Q$29,[1]Billing!$V$5:$V$29) -> 922787.13 | H90: =_xlfn.XLOOKUP($B55,[1]Billing!$Q$5:$Q$29,[1]Billing!$W$5:$W$29) -> 0 | I90: =_xlfn.XLOOKUP($B55,[1]Billing!$Q$5:$Q$29,[1]Billing!$X$5:$X$29) -> 0 | J90: =_xlfn.XLOOKUP($B55,[1]Billing!$Q$5:$Q$29,[1]Billing!$Y$5:$Y$29) -> 0 | K90: =G90+H90+I90+J90 -> 922787.13 | L90: =_xlfn.XLOOKUP($B55,[1]Billing!$Q$5:$Q$29,[1]Billing!$AA$5:$AA$29) -> 900000 | M90: =K90-L90 -> 22787.125 | N90: 10 | O90: 13
B91: Azam | C91: =_xlfn.XLOOKUP($B56,[1]Billing!$Q$5:$Q$29,[1]Billing!$R$5:$R$29) -> 204500 | D91: =_xlfn.XLOOKUP($B56,[1]Billing!$Q$5:$Q$29,[1]Billing!$S$5:$S$29) -> 186997.07 | E91: =_xlfn.XLOOKUP($B56,[1]Billing!$Q$5:$Q$29,[1]Billing!$T$5:$T$29) -> 161808.71 | F91: =_xlfn.XLOOKUP($B56,[1]Billing!$Q$5:$Q$29,[1]Billing!$U$5:$U$29) -> 25188.369 | G91: =_xlfn.XLOOKUP($B56,[1]Billing!$Q$5:$Q$29,[1]Billing!$V$5:$V$29) -> 1618087.1 | H91: =_xlfn.XLOOKUP($B56,[1]Billing!$Q$5:$Q$29,[1]Billing!$W$5:$W$29) -> 327448.79 | I91: =_xlfn.XLOOKUP($B56,[1]Billing!$Q$5:$Q$29,[1]Billing!$X$5:$X$29) -> 0 | J91: =_xlfn.XLOOKUP($B56,[1]Billing!$Q$5:$Q$29,[1]Billing!$Y$5:$Y$29) -> 0 | K91: =G91+H91+I91+J91 -> 1945535.8 | L91: =_xlfn.XLOOKUP($B56,[1]Billing!$Q$5:$Q$29,[1]Billing!$AA$5:$AA$29) -> 1617620 | M91: =K91-L91 -> 327915.84 | N91: 10 | O91: 13
B92: Ubaidullah | C92: =_xlfn.XLOOKUP($B57,[1]Billing!$Q$5:$Q$29,[1]Billing!$R$5:$R$29) -> 66850 | D92: =_xlfn.XLOOKUP($B57,[1]Billing!$Q$5:$Q$29,[1]Billing!$S$5:$S$29) -> 61128.383 | E92: =_xlfn.XLOOKUP($B57,[1]Billing!$Q$5:$Q$29,[1]Billing!$T$5:$T$29) -> 46132.955 | F92: =_xlfn.XLOOKUP($B57,[1]Billing!$Q$5:$Q$29,[1]Billing!$U$5:$U$29) -> 14995.428 | G92: =_xlfn.XLOOKUP($B57,[1]Billing!$Q$5:$Q$29,[1]Billing!$V$5:$V$29) -> 461329.55 | H92: =_xlfn.XLOOKUP($B57,[1]Billing!$Q$5:$Q$29,[1]Billing!$W$5:$W$29) -> 179945.14 | I92: =_xlfn.XLOOKUP($B57,[1]Billing!$Q$5:$Q$29,[1]Billing!$X$5:$X$29) -> 0 | J92: =_xlfn.XLOOKUP($B57,[1]Billing!$Q$5:$Q$29,[1]Billing!$Y$5:$Y$29) -> 0 | K92: =G92+H92+I92+J92 -> 641274.69 | L92: =_xlfn.XLOOKUP($B57,[1]Billing!$Q$5:$Q$29,[1]Billing!$AA$5:$AA$29) -> 630150 | M92: =K92-L92 -> 11124.689 | N92: 10 | O92: 13
B93: Ashraf Zia | C93: =_xlfn.XLOOKUP($B58,[1]Billing!$Q$5:$Q$29,[1]Billing!$R$5:$R$29) -> 23305 | D93: =_xlfn.XLOOKUP($B58,[1]Billing!$Q$5:$Q$29,[1]Billing!$S$5:$S$29) -> 21310.351 | E93: =_xlfn.XLOOKUP($B58,[1]Billing!$Q$5:$Q$29,[1]Billing!$T$5:$T$29) -> 21310.351 | F93: =_xlfn.XLOOKUP($B58,[1]Billing!$Q$5:$Q$29,[1]Billing!$U$5:$U$29) -> 0 | G93: =_xlfn.XLOOKUP($B58,[1]Billing!$Q$5:$Q$29,[1]Billing!$V$5:$V$29) -> 255724.21 | H93: =_xlfn.XLOOKUP($B58,[1]Billing!$Q$5:$Q$29,[1]Billing!$W$5:$W$29) -> 0 | I93: =_xlfn.XLOOKUP($B58,[1]Billing!$Q$5:$Q$29,[1]Billing!$X$5:$X$29) -> 0 | J93: =_xlfn.XLOOKUP($B58,[1]Billing!$Q$5:$Q$29,[1]Billing!$Y$5:$Y$29) -> 0 | K93: =G93+H93+I93+J93 -> 255724.21 | L93: =_xlfn.XLOOKUP($B58,[1]Billing!$Q$5:$Q$29,[1]Billing!$AA$5:$AA$29) -> 0 | M93: =K93-L93 -> 255724.21 | N93: 12 | O93: 13
B94: Hafiz Qureshi | C94: =_xlfn.XLOOKUP($B59,[1]Billing!$Q$5:$Q$29,[1]Billing!$R$5:$R$29) -> 132491 | D94: =_xlfn.XLOOKUP($B59,[1]Billing!$Q$5:$Q$29,[1]Billing!$S$5:$S$29) -> 121151.24 | E94: =_xlfn.XLOOKUP($B59,[1]Billing!$Q$5:$Q$29,[1]Billing!$T$5:$T$29) -> 121151.24 | F94: =_xlfn.XLOOKUP($B59,[1]Billing!$Q$5:$Q$29,[1]Billing!$U$5:$U$29) -> 0 | G94: =_xlfn.XLOOKUP($B59,[1]Billing!$Q$5:$Q$29,[1]Billing!$V$5:$V$29) -> 1211512.4 | H94: =_xlfn.XLOOKUP($B59,[1]Billing!$Q$5:$Q$29,[1]Billing!$W$5:$W$29) -> 0 | I94: =_xlfn.XLOOKUP($B59,[1]Billing!$Q$5:$Q$29,[1]Billing!$X$5:$X$29) -> 0 | J94: =_xlfn.XLOOKUP($B59,[1]Billing!$Q$5:$Q$29,[1]Billing!$Y$5:$Y$29) -> 0 | K94: =G94+H94+I94+J94 -> 1211512.4 | L94: =_xlfn.XLOOKUP($B59,[1]Billing!$Q$5:$Q$29,[1]Billing!$AA$5:$AA$29) -> 1200000 | M94: =K94-L94 -> 11512.436 | N94: 10 | O94: 13
B95: Badshah Fabrics | C95: =_xlfn.XLOOKUP($B60,[1]Billing!$Q$5:$Q$29,[1]Billing!$R$5:$R$29) -> 442848 | D95: =_xlfn.XLOOKUP($B60,[1]Billing!$Q$5:$Q$29,[1]Billing!$S$5:$S$29) -> 404945.14 | E95: =_xlfn.XLOOKUP($B60,[1]Billing!$Q$5:$Q$29,[1]Billing!$T$5:$T$29) -> 341790.42 | F95: =_xlfn.XLOOKUP($B60,[1]Billing!$Q$5:$Q$29,[1]Billing!$U$5:$U$29) -> 63154.718 | G95: =_xlfn.XLOOKUP($B60,[1]Billing!$Q$5:$Q$29,[1]Billing!$V$5:$V$29) -> 3417904.2 | H95: =_xlfn.XLOOKUP($B60,[1]Billing!$Q$5:$Q$29,[1]Billing!$W$5:$W$29) -> 757856.62 | I95: =_xlfn.XLOOKUP($B60,[1]Billing!$Q$5:$Q$29,[1]Billing!$X$5:$X$29) -> 0 | J95: =_xlfn.XLOOKUP($B60,[1]Billing!$Q$5:$Q$29,[1]Billing!$Y$5:$Y$29) -> 0 | K95: =G95+H95+I95+J95 -> 4175760.8 | L95: =_xlfn.XLOOKUP($B60,[1]Billing!$Q$5:$Q$29,[1]Billing!$AA$5:$AA$29) -> 4000544 | M95: =K95-L95 -> 175216.79 | N95: 10 | O95: 13
B96: Reject | C96: =_xlfn.XLOOKUP($B61,[1]Billing!$Q$5:$Q$29,[1]Billing!$R$5:$R$29) -> 0 | D96: =_xlfn.XLOOKUP($B61,[1]Billing!$Q$5:$Q$29,[1]Billing!$S$5:$S$29) -> 0 | E96: =_xlfn.XLOOKUP($B61,[1]Billing!$Q$5:$Q$29,[1]Billing!$T$5:$T$29) -> 0 | F96: =_xlfn.XLOOKUP($B61,[1]Billing!$Q$5:$Q$29,[1]Billing!$U$5:$U$29) -> 0 | G96: =_xlfn.XLOOKUP($B61,[1]Billing!$Q$5:$Q$29,[1]Billing!$V$5:$V$29) -> 0 | H96: =_xlfn.XLOOKUP($B61,[1]Billing!$Q$5:$Q$29,[1]Billing!$W$5:$W$29) -> 0 | I96: =_xlfn.XLOOKUP($B61,[1]Billing!$Q$5:$Q$29,[1]Billing!$X$5:$X$29) -> 0 | J96: =_xlfn.XLOOKUP($B61,[1]Billing!$Q$5:$Q$29,[1]Billing!$Y$5:$Y$29) -> 0 | K96: =G96+H96+I96+J96 -> 0 | L96: =_xlfn.XLOOKUP($B61,[1]Billing!$Q$5:$Q$29,[1]Billing!$AA$5:$AA$29) -> 0 | M96: =K96-L96 -> 0 | N96: 10 | O96: 13
... B103: Salman Zaffar | C103: =_xlfn.XLOOKUP($B68,[1]Billing!$Q$5:$Q$29,[1]Billing!$R$5:$R$29) -> 0 | D103: =_xlfn.XLOOKUP($B68,[1]Billing!$Q$5:$Q$29,[1]Billing!$S$5:$S$29) -> 0 | E103: =_xlfn.XLOOKUP($B68,[1]Billing!$Q$5:$Q$29,[1]Billing!$T$5:$T$29) -> 0 | F103: =_xlfn.XLOOKUP($B68,[1]Billing!$Q$5:$Q$29,[1]Billing!$U$5:$U$29) -> 0 | G103: =_xlfn.XLOOKUP($B68,[1]Billing!$Q$5:$Q$29,[1]Billing!$V$5:$V$29) -> 0 | H103: =_xlfn.XLOOKUP($B68,[1]Billing!$Q$5:$Q$29,[1]Billing!$W$5:$W$29) -> 0 | I103: =_xlfn.XLOOKUP($B68,[1]Billing!$Q$5:$Q$29,[1]Billing!$X$5:$X$29) -> 0 | J103: =_xlfn.XLOOKUP($B68,[1]Billing!$Q$5:$Q$29,[1]Billing!$Y$5:$Y$29) -> 0 | K103: =G103+H103+I103+J103 -> 0 | L103: =_xlfn.XLOOKUP($B68,[1]Billing!$Q$5:$Q$29,[1]Billing!$AA$5:$AA$29) -> 0 | M103: =K103-L103 -> 0 | N103: 10 | O103: 13
B104: Shahid Qasayi | C104: =_xlfn.XLOOKUP($B69,[1]Billing!$Q$5:$Q$29,[1]Billing!$R$5:$R$29) -> #N/A
B105: Hameed corporation
B106: ibraheem behraam
B107: Zia-ullah karachi

Sheet Bill Print
I4: Party Names: | J4: {=_xlfn.UNIQUE(Table1[Party Name])} -> BSC
J5: Ejaz Sahab
B6: Salman Zaffar | J6: Arshad
B7: Description | C7: Rate | D7: gazana | E7: sum | J7: Shehzad Kamoki
B8: Total Gazana/gaz | D8: {=_xlfn.XLOOKUP($B$6,_xlfn.ANCHORARRAY( Billing!Q5), INDEX(Billing!R5:R25, _xlfn.SEQUENCE(ROWS(_xlfn.ANCHORARRAY(Billing!$Q$5)))), "Not Found")} -> 55541 | J8: Sufi Nawaz Sahab
J9: Sajad Khan
B10: Gazana/meters | D10: {=_xlfn.XLOOKUP($B$6,_xlfn.ANCHORARRAY( Billing!$Q$5), INDEX(Billing!S5:S25, _xlfn.SEQUENCE(ROWS(_xlfn.ANCHORARRAY(Billing!$Q$5)))), "Not Found")} -> 50787.308 | J10: Raaz Fabrics
J11: Azam
B12: Total Chamki-crinkle/meters | C12: {=_xlfn.XLOOKUP($B$6,_xlfn.ANCHORARRAY( Billing!$B$49), OFFSET(Billing!N49, 0, 0, ROWS(_xlfn.ANCHORARRAY(Billing!$B$49))), "Not Found")} -> 10 | D12: {=_xlfn.XLOOKUP($B$6,_xlfn.ANCHORARRAY( Billing!$Q$5), INDEX(Billing!T5:T25, _xlfn.SEQUENCE(ROWS(_xlfn.ANCHORARRAY(Billing!$Q$5)))), "Not Found")} -> 14355.34 | E12: =Table21[[#This Row],[gazana]]*Table21[[#This Row],[Rate]] -> 143553.4 | J12: Ubaidullah
J13: Ashraf Zia
B14: Total Super Silky/meters | C14: {=_xlfn.XLOOKUP($B$6,_xlfn.ANCHORARRAY( Billing!$B$49), OFFSET(Billing!O49, 0, 0, ROWS(_xlfn.ANCHORARRAY(Billing!$B$49))), "Not Found")} -> 12 | D14: {=_xlfn.XLOOKUP($B$6,_xlfn.ANCHORARRAY( Billing!$Q$5), INDEX(Billing!U5:U25, _xlfn.SEQUENCE(ROWS(_xlfn.ANCHORARRAY(Billing!$Q$5)))), "Not Found")} -> 31409.108 | E14: =Table21[[#This Row],[gazana]]*Table21[[#This Row],[Rate]] -> 376909.29 | J14: Hafiz Qureshi
J15: Badshah Fabrics
B16: Total Billing | E16: =E12+E14 -> 520462.69 | J16: Reject
J17: Amjad 7up
B18: Total Paid | E18: {=_xlfn.XLOOKUP($B$6,_xlfn.ANCHORARRAY( Billing!Q5), OFFSET(Billing!AC5, 0, 0, ROWS(_xlfn.ANCHORARRAY(Billing!Q5))), "Not Found")} -> 0 | J18: Hazrat Khan
J19: Haseeb Shamsi
B20: Total Balance | E20: {=_xlfn.XLOOKUP($B$6,_xlfn.ANCHORARRAY( Billing!Q5), OFFSET(Billing!AD5, 0, 0, ROWS(_xlfn.ANCHORARRAY(Billing!Q5))), "Not Found")} -> 612146.12 | J20: Faizan
J21: Shafique Ansari
J22: Amjad sohail
J23: Salman Zaffar
J24: Shahid Qasayi
J25: Hameed corporation
J26: ibraheem behraam
J27: Zia-ullah karachi

Sheet Expenses
B1: Expenses
B3: Type | C3: Amount | D3: Description
B4: Wood | C4: =Wood!K6+(700*810) -> 5967000 | D4: 700*810
B5: Dyes/Chemical | C5: =SUM(Table8[Price])+Table2325[[#Totals],[total]] -> 1573020
B6: Finish | C6: =SUM(Table2[Price])+Finish!J30 -> 852000 | D6: 60 bags starch 3 bp26
B7: Misc | C7: =SUMIFS(Table14[Debit], Table14[Party],Table12[[#This Row],[Type]]) -> 29620
B8: Electricity | C8: =Electricity!E3 -> 0
B9: Salary | C9: =SUMIFS(Table14[Debit], Table14[Party],Table12[[#This Row],[Type]])+SUMIFS(Table14[Debit], Table14[Party],"Advance Salary") -> 812350
B10: Running Acc | C10: =Table5[[#Totals],[Amount]] -> 125170
B11: Transport | C11: =Table13[[#Totals],[Debit]] -> 160740
B12: Parts | C12: =Table15[[#Totals],[Amount]] -> 326064
C14: =SUM(Table12[Amount]) -> 9845964
B17: Stock (for next 15th)
B18: Stock | C18: quantity | D18: Column3
B19: Wood | C19: =388+236+100+288 -> 1012 | D19: mann
B20: Starch | C20: 100 | D20: Kg
B21: Pva | C21: 75 | D21: Kg
B22: Dyes | C22: Nil

Sheet Profit
B2: Column1 | C2: Column2
B3: Billing | C3: =Billing!C23 + SUMIFS(Table14[Credit], Table14[Party], "Transport") -> 17900753
B4: Expenses | C4: =Table12[[#Totals],[Amount]] -> 9845964
B5: Profit | C5: =C3-C4 -> 8054788.6
B10: Column1 | C10: Column2
B11: Billing | C11: =C3 -> 17900753
B12: Credit | C12: =SUM(Table14[Credit]) -> 15834740
B13: balance | C13: =(C11-C12) -> 2066012.6
B15: Expenses | C15: =C4 -> 9845964
B16: Debit | C16: =SUM(Table14[Debit]) -> 15806023
B17: Exp Balance | C17: =C15-C16 -> -5960059
B19: Cash in hand | C19: =Table18[[#Totals],[amount]] -> 30367
B21: Difference | C21: =(C13-C17)+C19 -> 8056438.6 | E21: My share: | F21: =C5*0.05 -> 402739.43

Sheet Transport
B2: Date | C2: Type | D2: Debit | E2: Credit | F2: Diff
B3: 45976 | D3: =SUMIFS(Table14[Debit], Table14[Date], Table13[[#This Row],[Date]], Table14[Party], "Transport") -> 0 | E3: =SUMIFS(Table14[Credit], Table14[Date], Table13[[#This Row],[Date]], Table14[Party], "Transport") -> 0
B4: 45977 | D4: =SUMIFS(Table14[Debit], Table14[Date], Table13[[#This Row],[Date]], Table14[Party], "Transport") -> 0 | E4: =SUMIFS(Table14[Credit], Table14[Date], Table13[[#This Row],[Date]], Table14[Party], "Transport") -> 0
B5: 45978 | D5: =SUMIFS(Table14[Debit], Table14[Date], Table13[[#This Row],[Date]], Table14[Party], "Transport") -> 0 | E5: =SUMIFS(Table14[Credit], Table14[Date], Table13[[#This Row],[Date]], Table14[Party], "Transport") -> 0
B6: 45979 | D6: =SUMIFS(Table14[Debit], Table14[Date], Table13[[#This Row],[Date]], Table14[Party], "Transport") -> 0 | E6: =SUMIFS(Table14[Credit], Table14[Date], Table13[[#This Row],[Date]], Table14[Party], "Transport") -> 0
B7: 45980 | D7: =SUMIFS(Table14[Debit], Table14[Date], Table13[[#This Row],[Date]], Table14[Party], "Transport") -> 10000 | E7: =SUMIFS(Table14[Credit], Table14[Date], Table13[[#This Row],[Date]], Table14[Party], "Transport") -> 0
B8: 45981 | D8: =SUMIFS(Table14[Debit], Table14[Date], Table13[[#This Row],[Date]], Table14[Party], "Transport") -> 500 | E8: =SUMIFS(Table14[Credit], Table14[Date], Table13[[#This Row],[Date]], Table14[Party], "Transport") -> 0
B9: 45982 | D9: =SUMIFS(Table14[Debit], Table14[Date], Table13[[#This Row],[Date]], Table14[Party], "Transport") -> 8008 | E9: =SUMIFS(Table14[Credit], Table14[Date], Table13[[#This Row],[Date]], Table14[Party], "Transport") -> 0
B10: 45983 | D10: =SUMIFS(Table14[Debit], Table14[Date], Table13[[#This Row],[Date]], Table14[Party], "Transport") -> 16040 | E10: =SUMIFS(Table14[Credit], Table14[Date], Table13[[#This Row],[Date]], Table14[Party], "Transport") -> 0
B11: 45984 | D11: =SUMIFS(Table14[Debit], Table14[Date], Table13[[#This Row],[Date]], Table14[Party], "Transport") -> 0 | E11: =SUMIFS(Table14[Credit], Table14[Date], Table13[[#This Row],[Date]], Table14[Party], "Transport") -> 0
B12: 45985 | D12: =SUMIFS(Table14[Debit], Table14[Date], Table13[[#This Row],[Date]], Table14[Party], "Transport") -> 12700 | E12: =SUMIFS(Table14[Credit], Table14[Date], Table13[[#This Row],[Date]], Table14[Party], "Transport") -> 0
B13: 45986 | D13: =SUMIFS(Table14[Debit], Table14[Date], Table13[[#This Row],[Date]], Table14[Party], "Transport") -> 10200 | E13: =SUMIFS(Table14[Credit], Table14[Date], Table13[[#This Row],[Date]], Table14[Party], "Transport") -> 0
B14: 45987 | D14: =SUMIFS(Table14[Debit], Table14[Date], Table13[[#This Row],[Date]], Table14[Party], "Transport") -> 3500 | E14: =SUMIFS(Table14[Credit], Table14[Date], Table13[[#This Row],[Date]], Table14[Party], "Transport") -> 0
... B37: 46010 | D37: =SUMIFS(Table14[Debit], Table14[Date], Table13[[#This Row],[Date]], Table14[Party], "Transport") -> 0 | E37: =SUMIFS(Table14[Credit], Table14[Date], Table13[[#This Row],[Date]], Table14[Party], "Transport") -> 0
D38: =SUBTOTAL(109,Table13[Debit]) -> 160740 | E38: =SUBTOTAL(109,Table13[Credit]) -> 0 | F38: =Table13[[#Totals],[Debit]]-Table13[[#Totals],[Credit]] -> 160740

Sheet ledger
A1: Date | B1: Party Name | C1: Bill Number | D1: Quality | E1: Shipment Number | F1: Kora/metre | G1: Tiyaar/gaz | H1: shortage % | I1: tiyar/meters | J1: billing | K1: Total Billing
A2: 45979 | B2: BSC | C2: October Closing CF | D2: Chamki | H2: =_xlfn.XLOOKUP(Table1[[#This Row],[Shipment Number]], 'pivot '!A:A,'pivot '!G:G, "NF") -> #DIV/0! | I2: =_xlfn.XLOOKUP(Table1[[#This Row],[Party Name]], [1]Billing!$Q$5:$Q$25, [1]Billing!$T$5:$T$25) -> 1895402.3 | J2: =_xlfn.XLOOKUP(Table1[[#This Row],[Party Name]], [1]Billing!$Q$5:$Q$25, [1]Billing!$V$5:$V$25) -> 18954023
A3: 45979 | B3: Ejaz Sahab | C3: October Closing CF | D3: Chamki | H3: =_xlfn.XLOOKUP(Table1[[#This Row],[Shipment Number]], 'pivot '!A:A,'pivot '!G:G, "NF") -> #DIV/0! | I3: =_xlfn.XLOOKUP(Table1[[#This Row],[Party Name]], [1]Billing!$Q$5:$Q$25, [1]Billing!$T$5:$T$25) -> 148145.57 | J3: =_xlfn.XLOOKUP(Table1[[#This Row],[Party Name]], [1]Billing!$Q$5:$Q$25, [1]Billing!$V$5:$V$25) -> 1481455.7
A4: 45979 | B4: Arshad | C4: October Closing CF | D4: Chamki | H4: =_xlfn.XLOOKUP(Table1[[#This Row],[Shipment Number]], 'pivot '!A:A,'pivot '!G:G, "NF") -> #DIV/0! | I4: =_xlfn.XLOOKUP(Table1[[#This Row],[Party Name]], [1]Billing!$Q$5:$Q$25, [1]Billing!$T$5:$T$25) -> 392581.38 | J4: =_xlfn.XLOOKUP(Table1[[#This Row],[Party Name]], [1]Billing!$Q$5:$Q$25, [1]Billing!$V$5:$V$25) -> 3925813.8
A5: 45979 | B5: Shehzad Kamoki | C5: October Closing CF | D5: Chamki | H5: =_xlfn.XLOOKUP(Table1[[#This Row],[Shipment Number]], 'pivot '!A:A,'pivot '!G:G, "NF") -> #DIV/0! | I5: =_xlfn.XLOOKUP(Table1[[#This Row],[Party Name]], [1]Billing!$Q$5:$Q$25, [1]Billing!$T$5:$T$25) -> 123086.14 | J5: =_xlfn.XLOOKUP(Table1[[#This Row],[Party Name]], [1]Billing!$Q$5:$Q$25, [1]Billing!$V$5:$V$25) -> 1269270.3
A6: 45979 | B6: Sufi Nawaz Sahab | C6: October Closing CF | D6: Chamki | H6: =_xlfn.XLOOKUP(Table1[[#This Row],[Shipment Number]], 'pivot '!A:A,'pivot '!G:G, "NF") -> #DIV/0! | I6: =_xlfn.XLOOKUP(Table1[[#This Row],[Party Name]], [1]Billing!$Q$5:$Q$25, [1]Billing!$T$5:$T$25) -> 599330.65 | J6: =_xlfn.XLOOKUP(Table1[[#This Row],[Party Name]], [1]Billing!$Q$5:$Q$25, [1]Billing!$V$5:$V$25) -> 5408917.9
A7: 45979 | B7: Sajad Khan | C7: October Closing CF | D7: Chamki | H7: =_xlfn.XLOOKUP(Table1[[#This Row],[Shipment Number]], 'pivot '!A:A,'pivot '!G:G, "NF") -> #DIV/0! | I7: =_xlfn.XLOOKUP(Table1[[#This Row],[Party Name]], [1]Billing!$Q$5:$Q$25, [1]Billing!$T$5:$T$25) -> 547436.91 | J7: =_xlfn.XLOOKUP(Table1[[#This Row],[Party Name]], [1]Billing!$Q$5:$Q$25, [1]Billing!$V$5:$V$25) -> 5474369.1
A8: 45979 | B8: Raaz Fabrics | C8: October Closing CF | D8: Chamki | H8: =_xlfn.XLOOKUP(Table1[[#This Row],[Shipment Number]], 'pivot '!A:A,'pivot '!G:G, "NF") -> #DIV/0! | I8: =_xlfn.XLOOKUP(Table1[[#This Row],[Party Name]], [1]Billing!$Q$5:$Q$25, [1]Billing!$T$5:$T$25) -> 92278.713 | J8: =_xlfn.XLOOKUP(Table1[[#This Row],[Party Name]], [1]Billing!$Q$5:$Q$25, [1]Billing!$V$5:$V$25) -> 922787.13
A9: 45979 | B9: Azam | C9: October Closing CF | D9: Chamki | H9: =_xlfn.XLOOKUP(Table1[[#This Row],[Shipment Number]], 'pivot '!A:A,'pivot '!G:G, "NF") -> #DIV/0! | I9: =_xlfn.XLOOKUP(Table1[[#This Row],[Party Name]], [1]Billing!$Q$5:$Q$25, [1]Billing!$T$5:$T$25) -> 161808.71 | J9: =_xlfn.XLOOKUP(Table1[[#This Row],[Party Name]], [1]Billing!$Q$5:$Q$25, [1]Billing!$V$5:$V$25) -> 1618087.1
A10: 45979 | B10: Ubaidullah | C10: October Closing CF | D10: Chamki | H10: =_xlfn.XLOOKUP(Table1[[#This Row],[Shipment Number]], 'pivot '!A:A,'pivot '!G:G, "NF") -> #DIV/0! | I10: =_xlfn.XLOOKUP(Table1[[#This Row],[Party Name]], [1]Billing!$Q$5:$Q$25, [1]Billing!$T$5:$T$25) -> 46132.955 | J10: =_xlfn.XLOOKUP(Table1[[#This Row],[Party Name]], [1]Billing!$Q$5:$Q$25, [1]Billing!$V$5:$V$25) -> 461329.55
A11: 45979 | B11: Ashraf Zia | C11: October Closing CF | D11: Crinkle | H11: =_xlfn.XLOOKUP(Table1[[#This Row],[Shipment Number]], 'pivot '!A:A,'pivot '!G:G, "NF") -> #DIV/0! | I11: =_xlfn.XLOOKUP(Table1[[#This Row],[Party Name]], [1]Billing!$Q$5:$Q$25, [1]Billing!$T$5:$T$25) -> 21310.351 | J11: =_xlfn.XLOOKUP(Table1[[#This Row],[Party Name]], [1]Billing!$Q$5:$Q$25, [1]Billing!$V$5:$V$25) -> 255724.21
A12: 45979 | B12: Hafiz Qureshi | C12: October Closing CF | D12: Chamki | H12: =_xlfn.XLOOKUP(Table1[[#This Row],[Shipment Number]], 'pivot '!A:A,'pivot '!G:G, "NF") -> #DIV/0! | I12: =_xlfn.XLOOKUP(Table1[[#This Row],[Party Name]], [1]Billing!$Q$5:$Q$25, [1]Billing!$T$5:$T$25) -> 121151.24 | J12: =_xlfn.XLOOKUP(Table1[[#This Row],[Party Name]], [1]Billing!$Q$5:$Q$25, [1]Billing!$V$5:$V$25) -> 1211512.4
A13: 45979 | B13: Badshah Fabrics | C13: October Closing CF | D13: Chamki | H13: =_xlfn.XLOOKUP(Table1[[#This Row],[Shipment Number]], 'pivot '!A:A,'pivot '!G:G, "NF") -> #DIV/0! | I13: =_xlfn.XLOOKUP(Table1[[#This Row],[Party Name]], [1]Billing!$Q$5:$Q$25, [1]Billing!$T$5:$T$25) -> 341790.42 | J13: =_xlfn.XLOOKUP(Table1[[#This Row],[Party Name]], [1]Billing!$Q$5:$Q$25, [1]Billing!$V$5:$V$25) -> 3417904.2
... A19: 45979 | B19: Shafique Ansari | C19: October Closing CF | D19: Chamki | H19: =_xlfn.XLOOKUP(Table1[[#This Row],[Shipment Number]], 'pivot '!A:A,'pivot '!G:G, "NF") -> #DIV/0! | I19: =_xlfn.XLOOKUP(Table1[[#This Row],[Party Name]], [1]Billing!$Q$5:$Q$25, [1]Billing!$T$5:$T$25) -> 64300.475 | J19: =_xlfn.XLOOKUP(Table1[[#This Row],[Party Name]], [1]Billing!$Q$5:$Q$25, [1]Billing!$V$5:$V$25) -> 643004.75
A20: 45979 | B20: Amjad sohail | C20: October Closing CF | D20: Chamki | H20: =_xlfn.XLOOKUP(Table1[[#This Row],[Shipment Number]], 'pivot '!A:A,'pivot '!G:G, "NF") -> #DIV/0! | I20: =_xlfn.XLOOKUP(Table1[[#This Row],[Party Name]], [1]Billing!$Q$5:$Q$25, [1]Billing!$U$5:$U$25) -> 43834.126 | J20: =_xlfn.XLOOKUP(Table1[[#This Row],[Party Name]], [1]Billing!$Q$5:$Q$25, [1]Billing!$V$5:$V$25) -> 552414.05
A21: 45979 | B21: Salman Zaffar | C21: October Closing CF | D21: Chamki | H21: =_xlfn.XLOOKUP(Table1[[#This Row],[Shipment Number]], 'pivot '!A:A,'pivot '!G:G, "NF") -> #DIV/0! | I21: =_xlfn.XLOOKUP(Table1[[#This Row],[Party Name]], [1]Billing!$Q$5:$Q$25, [1]Billing!$U$5:$U$25) -> 0 | J21: =_xlfn.XLOOKUP(Table1[[#This Row],[Party Name]], [1]Billing!$Q$5:$Q$25, [1]Billing!$V$5:$V$25) -> 0
A22: 45979 | B22: BSC | C22: October Closing CF | D22: Silky | H22: =_xlfn.XLOOKUP(Table1[[#This Row],[Shipment Number]], 'pivot '!A:A,'pivot '!G:G, "NF") -> #DIV/0! | I22: =_xlfn.XLOOKUP(Table1[[#This Row],[Party Name]], [1]Billing!$Q$5:$Q$25, [1]Billing!$U$5:$U$25) -> 121247.26 | J22: =_xlfn.XLOOKUP(Table1[[#This Row],[Party Name]], [1]Billing!$Q$5:$Q$25, [1]Billing!$W$5:$W$25) -> 1487858.4
A23: 45979 | B23: Ejaz Sahab | C23: October Closing CF | D23: Silky | H23: =_xlfn.XLOOKUP(Table1[[#This Row],[Shipment Number]], 'pivot '!A:A,'pivot '!G:G, "NF") -> #DIV/0! | I23: =_xlfn.XLOOKUP(Table1[[#This Row],[Party Name]], [1]Billing!$Q$5:$Q$25, [1]Billing!$U$5:$U$25) -> 105915.33 | J23: =_xlfn.XLOOKUP(Table1[[#This Row],[Party Name]], [1]Billing!$Q$5:$Q$25, [1]Billing!$W$5:$W$25) -> 1317755.1
A24: 45979 | B24: Arshad | C24: October Closing CF | D24: Silky | H24: =_xlfn.XLOOKUP(Table1[[#This Row],[Shipment Number]], 'pivot '!A:A,'pivot '!G:G, "NF") -> #DIV/0! | I24: =_xlfn.XLOOKUP(Table1[[#This Row],[Party Name]], [1]Billing!$Q$5:$Q$25, [1]Billing!$U$5:$U$25) -> 14794.257 | J24: =_xlfn.XLOOKUP(Table1[[#This Row],[Party Name]], [1]Billing!$Q$5:$Q$25, [1]Billing!$W$5:$W$25) -> 177531.09
A25: 45979 | B25: Shehzad Kamoki | C25: October Closing CF | D25: Silky | H25: =_xlfn.XLOOKUP(Table1[[#This Row],[Shipment Number]], 'pivot '!A:A,'pivot '!G:G, "NF") -> #DIV/0! | I25: =_xlfn.XLOOKUP(Table1[[#This Row],[Party Name]], [1]Billing!$Q$5:$Q$25, [1]Billing!$U$5:$U$25) -> 0 | J25: =_xlfn.XLOOKUP(Table1[[#This Row],[Party Name]], [1]Billing!$Q$5:$Q$25, [1]Billing!$W$5:$W$25) -> 0
A26: 45979 | B26: Sufi Nawaz Sahab | C26: October Closing CF | D26: Silky | H26: =_xlfn.XLOOKUP(Table1[[#This Row],[Shipment Number]], 'pivot '!A:A,'pivot '!G:G, "NF") -> #DIV/0! | I26: =_xlfn.XLOOKUP(Table1[[#This Row],[Party Name]], [1]Billing!$Q$5:$Q$25, [1]Billing!$U$5:$U$25) -> 485823.88 | J26: =_xlfn.XLOOKUP(Table1[[#This Row],[Party Name]], [1]Billing!$Q$5:$Q$25, [1]Billing!$W$5:$W$25) -> 5829886.6
A27: 45979 | B27: Sajad Khan | C27: October Closing CF | D27: Silky | H27: =_xlfn.XLOOKUP(Table1[[#This Row],[Shipment Number]], 'pivot '!A:A,'pivot '!G:G, "NF") -> #DIV/0! | I27: =_xlfn.XLOOKUP(Table1[[#This Row],[Party Name]], [1]Billing!$Q$5:$Q$25, [1]Billing!$U$5:$U$25) -> 0 | J27: =_xlfn.XLOOKUP(Table1[[#This Row],[Party Name]], [1]Billing!$Q$5:$Q$25, [1]Billing!$W$5:$W$25) -> 0
A28: 45979 | B28: Raaz Fabrics | C28: October Closing CF | D28: Silky | H28: =_xlfn.XLOOKUP(Table1[[#This Row],[Shipment Number]], 'pivot '!A:A,'pivot '!G:G, "NF") -> #DIV/0! | I28: =_xlfn.XLOOKUP(Table1[[#This Row],[Party Name]], [1]Billing!$Q$5:$Q$25, [1]Billing!$U$5:$U$25) -> 0 | J28: =_xlfn.XLOOKUP(Table1[[#This Row],[Party Name]], [1]Billing!$Q$5:$Q$25, [1]Billing!$W$5:$W$25) -> 0
A29: 45979 | B29: Azam | C29: October Closing CF | D29: Silky | H29: =_xlfn.XLOOKUP(Table1[[#This Row],[Shipment Number]], 'pivot '!A:A,'pivot '!G:G, "NF") -> #DIV/0! | I29: =_xlfn.XLOOKUP(Table1[[#This Row],[Party Name]], [1]Billing!$Q$5:$Q$25, [1]Billing!$U$5:$U$25) -> 25188.369 | J29: =_xlfn.XLOOKUP(Table1[[#This Row],[Party Name]], [1]Billing!$Q$5:$Q$25, [1]Billing!$W$5:$W$25) -> 327448.79
A30: 45979 | B30: Ubaidullah | C30: October Closing CF | D30: Silky | H30: =_xlfn.XLOOKUP(Table1[[#This Row],[Shipment Number]], 'pivot '!A:A,'pivot '!G:G, "NF") -> #DIV/0! | I30: =_xlfn.XLOOKUP(Table1[[#This Row],[Party Name]], [1]Billing!$Q$5:$Q$25, [1]Billing!$U$5:$U$25) -> 14995.428 | J30: =_xlfn.XLOOKUP(Table1[[#This Row],[Party Name]], [1]Billing!$Q$5:$Q$25, [1]Billing!$W$5:$W$25) -> 179945.14
A31: 45979 | B31: Ashraf Zia | C31: October Closing CF | D31: Silky | H31: =_xlfn.XLOOKUP(Table1[[#This Row],[Shipment Number]], 'pivot '!A:A,'pivot '!G:G, "NF") -> #DIV/0! | I31: =_xlfn.XLOOKUP(Table1[[#This Row],[Party Name]], [1]Billing!$Q$5:$Q$25, [1]Billing!$U$5:$U$25) -> 0 | J31: =_xlfn.XLOOKUP(Table1[[#This Row],[Party Name]], [1]Billing!$Q$5:$Q$25, [1]Billing!$W$5:$W$25) -> 0
A32: 45979 | B32: Hafiz Qureshi | C32: October Closing CF | D32: Silky | H32: =_xlfn.XLOOKUP(Table1[[#This Row],[Shipment Number]], 'pivot '!A:A,'pivot '!G:G, "NF") -> #DIV/0! | I32: =_xlfn.XLOOKUP(Table1[[#This Row],[Party Name]], [1]Billing!$Q$5:$Q$25, [1]Billing!$U$5:$U$25) -> 0 | J32: =_xlfn.XLOOKUP(Table1[[#This Row],[Party Name]], [1]Billing!$Q$5:$Q$25, [1]Billing!$W$5:$W$25) -> 0
A33: 45979 | B33: Badshah Fabrics | C33: October Closing CF | D33: Silky | H33: =_xlfn.XLOOKUP(Table1[[#This Row],[Shipment Number]], 'pivot '!A:A,'pivot '!G:G, "NF") -> #DIV/0! | I33: =_xlfn.XLOOKUP(Table1[[#This Row],[Party Name]], [1]Billing!$Q$5:$Q$25, [1]Billing!$U$5:$U$25) -> 63154.718 | J33: =_xlfn.XLOOKUP(Table1[[#This Row],[Party Name]], [1]Billing!$Q$5:$Q$25, [1]Billing!$W$5:$W$25) -> 757856.62
... A37: 45979 | B37: Haseeb Shamsi | C37: October Closing CF | D37: Silky | H37: =_xlfn.XLOOKUP(Table1[[#This Row],[Shipment Number]], 'pivot '!A:A,'pivot '!G:G, "NF") -> #DIV/0! | I37: =_xlfn.XLOOKUP(Table1[[#This Row],[Party Name]], [1]Billing!$Q$5:$Q$25, [1]Billing!$U$5:$U$25) -> 9232.8091 | J37: =_xlfn.XLOOKUP(Table1[[#This Row],[Party Name]], [1]Billing!$Q$5:$Q$25, [1]Billing!$W$5:$W$25) -> 120026.52
A38: 45979 | B38: Faizan | C38: October Closing CF | D38: Silky | I38: =_xlfn.XLOOKUP(Table1[[#This Row],[Party Name]], [1]Billing!$Q$5:$Q$25, [1]Billing!$U$5:$U$25) -> 200198.43 | J38: =_xlfn.XLOOKUP(Table1[[#This Row],[Party Name]], [1]Billing!$Q$5:$Q$25, [1]Billing!$W$5:$W$25) -> 2602579.6
A39: 45979 | B39: Shafique Ansari | C39: October Closing CF | D39: Silky | I39: =_xlfn.XLOOKUP(Table1[[#This Row],[Party Name]], [1]Billing!$Q$5:$Q$25, [1]Billing!$U$5:$U$25) -> 7565.8376 | J39: =_xlfn.XLOOKUP(Table1[[#This Row],[Party Name]], [1]Billing!$Q$5:$Q$25, [1]Billing!$W$5:$W$25) -> 98355.889
A40: 45979 | B40: Amjad sohail | C40: October Closing CF | D40: Silky | I40: =_xlfn.XLOOKUP(Table1[[#This Row],[Party Name]], [1]Billing!$Q$5:$Q$25, [1]Billing!$U$5:$U$25) -> 43834.126 | J40: =_xlfn.XLOOKUP(Table1[[#This Row],[Party Name]], [1]Billing!$Q$5:$Q$25, [1]Billing!$W$5:$W$25) -> 569843.64
A41: 45979 | B41: Salman Zaffar | C41: October Closing CF | D41: Silky | I41: =_xlfn.XLOOKUP(Table1[[#This Row],[Party Name]], [1]Billing!$Q$5:$Q$25, [1]Billing!$U$5:$U$25) -> 0 | J41: =_xlfn.XLOOKUP(Table1[[#This Row],[Party Name]], [1]Billing!$Q$5:$Q$25, [1]Billing!$W$5:$W$25) -> 0
A42: 45979 | B42: BSC | C42: October Closing CF | D42: Slub | J42: =_xlfn.XLOOKUP(Table1[[#This Row],[Party Name]], [1]Billing!$Q$5:$Q$25, [1]Billing!$X$5:$X$25) -> 0
A43: 45979 | B43: Ejaz Sahab | C43: October Closing CF | D43: Slub | J43: =_xlfn.XLOOKUP(Table1[[#This Row],[Party Name]], [1]Billing!$Q$5:$Q$25, [1]Billing!$X$5:$X$25) -> 0
A44: 45979 | B44: Arshad | C44: October Closing CF | D44: Slub | J44: =_xlfn.XLOOKUP(Table1[[#This Row],[Party Name]], [1]Billing!$Q$5:$Q$25, [1]Billing!$X$5:$X$25) -> 0
A45: 45979 | B45: Shehzad Kamoki | C45: October Closing CF | D45: Slub | J45: =_xlfn.XLOOKUP(Table1[[#This Row],[Party Name]], [1]Billing!$Q$5:$Q$25, [1]Billing!$X$5:$X$25) -> 0
A46: 45979 | B46: Sufi Nawaz Sahab | C46: October Closing CF | D46: Slub | H46: =_xlfn.XLOOKUP(Table1[[#This Row],[Shipment Number]], 'pivot '!A:A,'pivot '!G:G, "NF") -> #DIV/0! | J46: =_xlfn.XLOOKUP(Table1[[#This Row],[Party Name]], [1]Billing!$Q$5:$Q$25, [1]Billing!$X$5:$X$25) -> 0
A47: 45979 | B47: Sajad Khan | C47: October Closing CF | D47: Slub | H47: =_xlfn.XLOOKUP(Table1[[#This Row],[Shipment Number]], 'pivot '!A:A,'pivot '!G:G, "NF") -> #DIV/0! | J47: =_xlfn.XLOOKUP(Table1[[#This Row],[Party Name]], [1]Billing!$Q$5:$Q$25, [1]Billing!$X$5:$X$25) -> 71359.729
A48: 45979 | B48: Raaz Fabrics | C48: October Closing CF | D48: Slub | H48: =_xlfn.XLOOKUP(Table1[[#This Row],[Shipment Number]], 'pivot '!A:A,'pivot '!G:G, "NF") -> #DIV/0! | J48: =_xlfn.XLOOKUP(Table1[[#This Row],[Party Name]], [1]Billing!$Q$5:$Q$25, [1]Billing!$X$5:$X$25) -> 0
A49: 45979 | B49: Azam | C49: October Closing CF | D49: Slub | H49: =_xlfn.XLOOKUP(Table1[[#This Row],[Shipment Number]], 'pivot '!A:A,'pivot '!G:G, "NF") -> #DIV/0! | J49: =_xlfn.XLOOKUP(Table1[[#This Row],[Party Name]], [1]Billing!$Q$5:$Q$25, [1]Billing!$X$5:$X$25) -> 0
A50: 45979 | B50: Ubaidullah | C50: October Closing CF | D50: Slub | H50: =_xlfn.XLOOKUP(Table1[[#This Row],[Shipment Number]], 'pivot '!A:A,'pivot '!G:G, "NF") -> #DIV/0! | J50: =_xlfn.XLOOKUP(Table1[[#This Row],[Party Name]], [1]Billing!$Q$5:$Q$25, [1]Billing!$X$5:$X$25) -> 0
A51: 45979 | B51: Ashraf Zia | C51: October Closing CF | D51: Slub | H51: =_xlfn.XLOOKUP(Table1[[#This Row],[Shipment Number]], 'pivot '!A:A,'pivot '!G:G, "NF") -> #DIV/0! | J51: =_xlfn.XLOOKUP(Table1[[#This Row],[Party Name]], [1]Billing!$Q$5:$Q$25, [1]Billing!$X$5:$X$25) -> 0
A52: 45979 | B52: Hafiz Qureshi | C52: October Closing CF | D52: Slub | H52: =_xlfn.XLOOKUP(Table1[[#This Row],[Shipment Number]], 'pivot '!A:A,'pivot '!G:G, "NF") -> #DIV/0! | J52: =_xlfn.XLOOKUP(Table1[[#This Row],[Party Name]], [1]Billing!$Q$5:$Q$25, [1]Billing!$X$5:$X$25) -> 0
A53: 45979 | B53: Badshah Fabrics | C53: October Closing CF | D53: Slub | H53: =_xlfn.XLOOKUP(Table1[[#This Row],[Shipment Number]], 'pivot '!A:A,'pivot '!G:G, "NF") -> #DIV/0! | J53: =_xlfn.XLOOKUP(Table1[[#This Row],[Party Name]], [1]Billing!$Q$5:$Q$25, [1]Billing!$X$5:$X$25) -> 0
A54: 45979 | B54: Reject | C54: October Closing CF | D54: Slub | H54: =_xlfn.XLOOKUP(Table1[[#This Row],[Shipment Number]], 'pivot '!A:A,'pivot '!G:G, "NF") -> #DIV/0! | J54: =_xlfn.XLOOKUP(Table1[[#This Row],[Party Name]], [1]Billing!$Q$5:$Q$25, [1]Billing!$X$5:$X$25) -> 0
A55: 45979 | B55: Amjad 7up | C55: October Closing CF | D55: Slub | H55: =_xlfn.XLOOKUP(Table1[[#This Row],[Shipment Number]], 'pivot '!A:A,'pivot '!G:G, "NF") -> #DIV/0! | J55: =_xlfn.XLOOKUP(Table1[[#This Row],[Party Name]], [1]Billing!$Q$5:$Q$25, [1]Billing!$X$5:$X$25) -> 0
A56: 45979 | B56: Hazrat Khan | C56: October Closing CF | D56: Slub | H56: =_xlfn.XLOOKUP(Table1[[#This Row],[Shipment Number]], 'pivot '!A:A,'pivot '!G:G, "NF") -> #DIV/0! | J56: =_xlfn.XLOOKUP(Table1[[#This Row],[Party Name]], [1]Billing!$Q$5:$Q$25, [1]Billing!$X$5:$X$25) -> 0
A57: 45979 | B57: Haseeb Shamsi | C57: October Closing CF | D57: Slub | H57: =_xlfn.XLOOKUP(Table1[[#This Row],[Shipment Number]], 'pivot '!A:A,'pivot '!G:G, "NF") -> #DIV/0! | J57: =_xlfn.XLOOKUP(Table1[[#This Row],[Party Name]], [1]Billing!$Q$5:$Q$25, [1]Billing!$X$5:$X$25) -> 0
... A61: 45979 | B61: Salman Zaffar | C61: October Closing CF | D61: Slub | H61: =_xlfn.XLOOKUP(Table1[[#This Row],[Shipment Number]], 'pivot '!A:A,'pivot '!G:G, "NF") -> #DIV/0! | J61: =_xlfn.XLOOKUP(Table1[[#This Row],[Party Name]], [1]Billing!$Q$5:$Q$25, [1]Billing!$X$5:$X$25) -> 0
A62: 45979 | B62: BSC | C62: October Closing CF | D62: Satin | H62: =_xlfn.XLOOKUP(Table1[[#This Row],[Shipment Number]], 'pivot '!A:A,'pivot '!G:G, "NF") -> #DIV/0! | J62: =_xlfn.XLOOKUP(Table1[[#This Row],[Party Name]], [1]Billing!$Q$5:$Q$25, [1]Billing!$Y$5:$Y$25) -> 0
A63: 45979 | B63: Ejaz Sahab | C63: October Closing CF | D63: Satin | H63: =_xlfn.XLOOKUP(Table1[[#This Row],[Shipment Number]], 'pivot '!A:A,'pivot '!G:G, "NF") -> #DIV/0! | J63: =_xlfn.XLOOKUP(Table1[[#This Row],[Party Name]], [1]Billing!$Q$5:$Q$25, [1]Billing!$Y$5:$Y$25) -> 0
A64: 45979 | B64: Arshad | C64: October Closing CF | D64: Satin | H64: =_xlfn.XLOOKUP(Table1[[#This Row],[Shipment Number]], 'pivot '!A:A,'pivot '!G:G, "NF") -> #DIV/0! | J64: =_xlfn.XLOOKUP(Table1[[#This Row],[Party Name]], [1]Billing!$Q$5:$Q$25, [1]Billing!$Y$5:$Y$25) -> 0
A65: 45979 | B65: Shehzad Kamoki | C65: October Closing CF | D65: Satin | H65: =_xlfn.XLOOKUP(Table1[[#This Row],[Shipment Number]], 'pivot '!A:A,'pivot '!G:G, "NF") -> #DIV/0! | J65: =_xlfn.XLOOKUP(Table1[[#This Row],[Party Name]], [1]Billing!$Q$5:$Q$25, [1]Billing!$Y$5:$Y$25) -> 0
A66: 45979 | B66: Sufi Nawaz Sahab | C66: October Closing CF | D66: Satin | H66: =_xlfn.XLOOKUP(Table1[[#This Row],[Shipment Number]], 'pivot '!A:A,'pivot '!G:G, "NF") -> #DIV/0! | J66: =_xlfn.XLOOKUP(Table1[[#This Row],[Party Name]], [1]Billing!$Q$5:$Q$25, [1]Billing!$Y$5:$Y$25) -> 0
A67: 45979 | B67: Sajad Khan | C67: October Closing CF | D67: Satin | H67: =_xlfn.XLOOKUP(Table1[[#This Row],[Shipment Number]], 'pivot '!A:A,'pivot '!G:G, "NF") -> #DIV/0! | J67: =_xlfn.XLOOKUP(Table1[[#This Row],[Party Name]], [1]Billing!$Q$5:$Q$25, [1]Billing!$Y$5:$Y$25) -> 0
A68: 45979 | B68: Raaz Fabrics | C68: October Closing CF | D68: Satin | H68: =_xlfn.XLOOKUP(Table1[[#This Row],[Shipment Number]], 'pivot '!A:A,'pivot '!G:G, "NF") -> #DIV/0! | J68: =_xlfn.XLOOKUP(Table1[[#This Row],[Party Name]], [1]Billing!$Q$5:$Q$25, [1]Billing!$Y$5:$Y$25) -> 0
A69: 45979 | B69: Azam | C69: October Closing CF | D69: Satin | H69: =_xlfn.XLOOKUP(Table1[[#This Row],[Shipment Number]], 'pivot '!A:A,'pivot '!G:G, "NF") -> #DIV/0! | J69: =_xlfn.XLOOKUP(Table1[[#This Row],[Party Name]], [1]Billing!$Q$5:$Q$25, [1]Billing!$Y$5:$Y$25) -> 0
A70: 45979 | B70: Ubaidullah | C70: October Closing CF | D70: Satin | H70: =_xlfn.XLOOKUP(Table1[[#This Row],[Shipment Number]], 'pivot '!A:A,'pivot '!G:G, "NF") -> #DIV/0! | J70: =_xlfn.XLOOKUP(Table1[[#This Row],[Party Name]], [1]Billing!$Q$5:$Q$25, [1]Billing!$Y$5:$Y$25) -> 0
A71: 45979 | B71: Ashraf Zia | C71: October Closing CF | D71: Satin | H71: =_xlfn.XLOOKUP(Table1[[#This Row],[Shipment Number]], 'pivot '!A:A,'pivot '!G:G, "NF") -> #DIV/0! | J71: =_xlfn.XLOOKUP(Table1[[#This Row],[Party Name]], [1]Billing!$Q$5:$Q$25, [1]Billing!$Y$5:$Y$25) -> 0
A72: 45979 | B72: Hafiz Qureshi | C72: October Closing CF | D72: Satin | H72: =_xlfn.XLOOKUP(Table1[[#This Row],[Shipment Number]], 'pivot '!A:A,'pivot '!G:G, "NF") -> #DIV/0! | J72: =_xlfn.XLOOKUP(Table1[[#This Row],[Party Name]], [1]Billing!$Q$5:$Q$25, [1]Billing!$Y$5:$Y$25) -> 0
A73: 45979 | B73: Badshah Fabrics | C73: October Closing CF | D73: Satin | H73: =_xlfn.XLOOKUP(Table1[[#This Row],[Shipment Number]], 'pivot '!A:A,'pivot '!G:G, "NF") -> #DIV/0! | J73: =_xlfn.XLOOKUP(Table1[[#This Row],[Party Name]], [1]Billing!$Q$5:$Q$25, [1]Billing!$Y$5:$Y$25) -> 0
... A81: 45979 | B81: Salman Zaffar | C81: October Closing CF | D81: Satin | H81: =_xlfn.XLOOKUP(Table1[[#This Row],[Shipment Number]], 'pivot '!A:A,'pivot '!G:G, "NF") -> #DIV/0! | J81: =_xlfn.XLOOKUP(Table1[[#This Row],[Party Name]], [1]Billing!$Q$5:$Q$25, [1]Billing!$Y$5:$Y$25) -> 0
A82: 45979 | B82: Salman Zaffar | C82: 1091 | D82: Silky | E82: 1879 | F82: 15061 | G82: 8370 | H82: =_xlfn.XLOOKUP(Table1[[#This Row],[Shipment Number]], 'pivot '!A:A,'pivot '!G:G, "NF") -> 1.5221542 | I82: =Table1[[#This Row],[Tiyaar/gaz]]/1.0936 -> 7653.6211 | J82: {=_xlfn.IFS( AND(Table1[[#This Row],[Party Name]]="Faizan",Table1[[#This Row],[Quality]]="Silky"),Table1[[#This Row],[tiyar/meters]]*13, AND(Table1[[#This Row],[Party Name]]="Sajad Khan",Table1[[#This Row],[Quality]]="Slub"),Table1[[#This Row],[tiyar/meters]]*13, AND(Table1[[#This Row],[Party Name]]="Faizan",Table1[[#This Row],[Quality]]="Slub"),Table1[[#This Row],[tiyar/meters]]*15, AND(Table1[[#This Row],[Party Name]]="Shafique Ansari",Table1[[#This Row],[Quality]]="Satin"),Table1[[#This Row],[tiyar/meters]]*28, Table1[[#This Row],[Quality]]="Chamki",Table1[[#This Row],[tiyar/meters]]*10, Table1[[#This Row],[Quality]]="Silky",Table1[[#This Row],[tiyar/meters]]*13, Table1[[#This Row],[Quality]]="Crinkle",Table1[[#This Row],[tiyar/meters]]*10 )} -> 99497.074
A83: 45979 | B83: Ejaz Sahab | C83: 1092 | D83: Silky | E83: 1867 | F83: 15147 | G83: 16288 | H83: =_xlfn.XLOOKUP(Table1[[#This Row],[Shipment Number]], 'pivot '!A:A,'pivot '!G:G, "NF") -> 1.670771 | I83: =Table1[[#This Row],[Tiyaar/gaz]]/1.0936 -> 14893.928 | J83: {=_xlfn.IFS( AND(Table1[[#This Row],[Party Name]]="Faizan",Table1[[#This Row],[Quality]]="Silky"),Table1[[#This Row],[tiyar/meters]]*13, AND(Table1[[#This Row],[Party Name]]="Sajad Khan",Table1[[#This Row],[Quality]]="Slub"),Table1[[#This Row],[tiyar/meters]]*13, AND(Table1[[#This Row],[Party Name]]="Faizan",Table1[[#This Row],[Quality]]="Slub"),Table1[[#This Row],[tiyar/meters]]*15, AND(Table1[[#This Row],[Party Name]]="Shafique Ansari",Table1[[#This Row],[Quality]]="Satin"),Table1[[#This Row],[tiyar/meters]]*28, Table1[[#This Row],[Quality]]="Chamki",Table1[[#This Row],[tiyar/meters]]*10, Table1[[#This Row],[Quality]]="Silky",Table1[[#This Row],[tiyar/meters]]*13, Table1[[#This Row],[Quality]]="Crinkle",Table1[[#This Row],[tiyar/meters]]*10 )} -> 193621.07
A84: 45979 | B84: Salman Zaffar | C84: 1093 | D84: Silky | E84: 1879 | F84: 15061 | G84: 7850 | H84: =_xlfn.XLOOKUP(Table1[[#This Row],[Shipment Number]], 'pivot '!A:A,'pivot '!G:G, "NF") -> 1.5221542 | I84: =Table1[[#This Row],[Tiyaar/gaz]]/1.0936 -> 7178.1273 | J84: {=_xlfn.IFS( AND(Table1[[#This Row],[Party Name]]="Faizan",Table1[[#This Row],[Quality]]="Silky"),Table1[[#This Row],[tiyar/meters]]*13, AND(Table1[[#This Row],[Party Name]]="Sajad Khan",Table1[[#This Row],[Quality]]="Slub"),Table1[[#This Row],[tiyar/meters]]*13, AND(Table1[[#This Row],[Party Name]]="Faizan",Table1[[#This Row],[Quality]]="Slub"),Table1[[#This Row],[tiyar/meters]]*15, AND(Table1[[#This Row],[Party Name]]="Shafique Ansari",Table1[[#This Row],[Quality]]="Satin"),Table1[[#This Row],[tiyar/meters]]*28, Table1[[#This Row],[Quality]]="Chamki",Table1[[#This Row],[tiyar/meters]]*10, Table1[[#This Row],[Quality]]="Silky",Table1[[#This Row],[tiyar/meters]]*13, Table1[[#This Row],[Quality]]="Crinkle",Table1[[#This Row],[tiyar/meters]]*10 )} -> 93315.655
A85: 45979 | B85: Salman Zaffar | C85: 1094 | D85: Silky | E85: 1880+1885 | F85: 17020 | G85: 3280 | H85: =_xlfn.XLOOKUP(Table1[[#This Row],[Shipment Number]], 'pivot '!A:A,'pivot '!G:G, "NF") -> 2.6007099 | I85: =Table1[[#This Row],[Tiyaar/gaz]]/1.0936 -> 2999.2685 | J85: {=_xlfn.IFS( AND(Table1[[#This Row],[Party Name]]="Faizan",Table1[[#This Row],[Quality]]="Silky"),Table1[[#This Row],[tiyar/meters]]*13, AND(Table1[[#This Row],[Party Name]]="Sajad Khan",Table1[[#This Row],[Quality]]="Slub"),Table1[[#This Row],[tiyar/meters]]*13, AND(Table1[[#This Row],[Party Name]]="Faizan",Table1[[#This Row],[Quality]]="Slub"),Table1[[#This Row],[tiyar/meters]]*15, AND(Table1[[#This Row],[Party Name]]="Shafique Ansari",Table1[[#This Row],[Quality]]="Satin"),Table1[[#This Row],[tiyar/meters]]*28, Table1[[#This Row],[Quality]]="Chamki",Table1[[#This Row],[tiyar/meters]]*10, Table1[[#This Row],[Quality]]="Silky",Table1[[#This Row],[tiyar/meters]]*13, Table1[[#This Row],[Quality]]="Crinkle",Table1[[#This Row],[tiyar/meters]]*10 )} -> 38990.49
A86: 45979 | B86: Salman Zaffar | C86: 1095 | D86: Silky | E86: 1880+1885 | F86: 17020 | G86: 2238 | H86: =_xlfn.XLOOKUP(Table1[[#This Row],[Shipment Number]], 'pivot '!A:A,'pivot '!G:G, "NF") -> 2.6007099 | I86: =Table1[[#This Row],[Tiyaar/gaz]]/1.0936 -> 2046.4521 | J86: {=_xlfn.IFS( AND(Table1[[#This Row],[Party Name]]="Faizan",Table1[[#This Row],[Quality]]="Silky"),Table1[[#This Row],[tiyar/meters]]*13, AND(Table1[[#This Row],[Party Name]]="Sajad Khan",Table1[[#This Row],[Quality]]="Slub"),Table1[[#This Row],[tiyar/meters]]*13, AND(Table1[[#This Row],[Party Name]]="Faizan",Table1[[#This Row],[Quality]]="Slub"),Table1[[#This Row],[tiyar/meters]]*15, AND(Table1[[#This Row],[Party Name]]="Shafique Ansari",Table1[[#This Row],[Quality]]="Satin"),Table1[[#This Row],[tiyar/meters]]*28, Table1[[#This Row],[Quality]]="Chamki",Table1[[#This Row],[tiyar/meters]]*10, Table1[[#This Row],[Quality]]="Silky",Table1[[#This Row],[tiyar/meters]]*13, Table1[[#This Row],[Quality]]="Crinkle",Table1[[#This Row],[tiyar/meters]]*10 )} -> 26603.877
A87: 45979 | B87: Salman Zaffar | C87: 1096 | D87: Silky | E87: 1880+1885 | F87: 17020 | G87: 7449 | H87: =_xlfn.XLOOKUP(Table1[[#This Row],[Shipment Number]], 'pivot '!A:A,'pivot '!G:G, "NF") -> 2.6007099 | I87: =Table1[[#This Row],[Tiyaar/gaz]]/1.0936 -> 6811.4484 | J87: {=_xlfn.IFS( AND(Table1[[#This Row],[Party Name]]="Faizan",Table1[[#This Row],[Quality]]="Silky"),Table1[[#This Row],[tiyar/meters]]*13, AND(Table1[[#This Row],[Party Name]]="Sajad Khan",Table1[[#This Row],[Quality]]="Slub"),Table1[[#This Row],[tiyar/meters]]*13, AND(Table1[[#This Row],[Party Name]]="Faizan",Table1[[#This Row],[Quality]]="Slub"),Table1[[#This Row],[tiyar/meters]]*15, AND(Table1[[#This Row],[Party Name]]="Shafique Ansari",Table1[[#This Row],[Quality]]="Satin"),Table1[[#This Row],[tiyar/meters]]*28, Table1[[#This Row],[Quality]]="Chamki",Table1[[#This Row],[tiyar/meters]]*10, Table1[[#This Row],[Quality]]="Silky",Table1[[#This Row],[tiyar/meters]]*13, Table1[[#This Row],[Quality]]="Crinkle",Table1[[#This Row],[tiyar/meters]]*10 )} -> 88548.83
A88: 45979 | B88: Salman Zaffar | C88: 1097 | D88: Silky | E88: 1880+1885 | F88: 17020 | G88: 5162 | H88: =_xlfn.XLOOKUP(Table1[[#This Row],[Shipment Number]], 'pivot '!A:A,'pivot '!G:G, "NF") -> 2.6007099 | I88: =Table1[[#This Row],[Tiyaar/gaz]]/1.0936 -> 4720.1902 | J88: {=_xlfn.IFS( AND(Table1[[#This Row],[Party Name]]="Faizan",Table1[[#This Row],[Quality]]="Silky"),Table1[[#This Row],[tiyar/meters]]*13, AND(Table1[[#This Row],[Party Name]]="Sajad Khan",Table1[[#This Row],[Quality]]="Slub"),Table1[[#This Row],[tiyar/meters]]*13, AND(Table1[[#This Row],[Party Name]]="Faizan",Table1[[#This Row],[Quality]]="Slub"),Table1[[#This Row],[tiyar/meters]]*15, AND(Table1[[#This Row],[Party Name]]="Shafique Ansari",Table1[[#This Row],[Quality]]="Satin"),Table1[[#This Row],[tiyar/meters]]*28, Table1[[#This Row],[Quality]]="Chamki",Table1[[#This Row],[tiyar/meters]]*10, Table1[[#This Row],[Quality]]="Silky",Table1[[#This Row],[tiyar/meters]]*13, Table1[[#This Row],[Quality]]="Crinkle",Table1[[#This Row],[tiyar/meters]]*10 )} -> 61362.473
A89: 45980 | B89: Arshad | C89: 1098 | D89: Silky | E89: 1878 | F89: 25021 | G89: 26629 | H89: =_xlfn.XLOOKUP(Table1[[#This Row],[Shipment Number]], 'pivot '!A:A,'pivot '!G:G, "NF") -> 2.6823321 | I89: =Table1[[#This Row],[Tiyaar/gaz]]/1.0936 -> 24349.854 | J89: {=_xlfn.IFS( AND(Table1[[#This Row],[Party Name]]="Faizan",Table1[[#This Row],[Quality]]="Silky"),Table1[[#This Row],[tiyar/meters]]*13, AND(Table1[[#This Row],[Party Name]]="Sajad Khan",Table1[[#This Row],[Quality]]="Slub"),Table1[[#This Row],[tiyar/meters]]*13, AND(Table1[[#This Row],[Party Name]]="Faizan",Table1[[#This Row],[Quality]]="Slub"),Table1[[#This Row],[tiyar/meters]]*15, AND(Table1[[#This Row],[Party Name]]="Shafique Ansari",Table1[[#This Row],[Quality]]="Satin"),Table1[[#This Row],[tiyar/meters]]*28, Table1[[#This Row],[Quality]]="Chamki",Table1[[#This Row],[tiyar/meters]]*10, Table1[[#This Row],[Quality]]="Silky",Table1[[#This Row],[tiyar/meters]]*13, Table1[[#This Row],[Quality]]="Crinkle",Table1[[#This Row],[tiyar/meters]]*10 )} -> 316548.1
A90: 45980 | B90: BSC | C90: 1099 | D90: Silky | E90: 1897 | F90: 11127 | G90: 11819 | H90: =_xlfn.XLOOKUP(Table1[[#This Row],[Shipment Number]], 'pivot '!A:A,'pivot '!G:G, "NF") -> 2.8720678 | I90: =Table1[[#This Row],[Tiyaar/gaz]]/1.0936 -> 10807.425 | J90: {=_xlfn.IFS( AND(Table1[[#This Row],[Party Name]]="Faizan",Table1[[#This Row],[Quality]]="Silky"),Table1[[#This Row],[tiyar/meters]]*13, AND(Table1[[#This Row],[Party Name]]="Sajad Khan",Table1[[#This Row],[Quality]]="Slub"),Table1[[#This Row],[tiyar/meters]]*13, AND(Table1[[#This Row],[Party Name]]="Faizan",Table1[[#This Row],[Quality]]="Slub"),Table1[[#This Row],[tiyar/meters]]*15, AND(Table1[[#This Row],[Party Name]]="Shafique Ansari",Table1[[#This Row],[Quality]]="Satin"),Table1[[#This Row],[tiyar/meters]]*28, Table1[[#This Row],[Quality]]="Chamki",Table1[[#This Row],[tiyar/meters]]*10, Table1[[#This Row],[Quality]]="Silky",Table1[[#This Row],[tiyar/meters]]*13, Table1[[#This Row],[Quality]]="Crinkle",Table1[[#This Row],[tiyar/meters]]*10 )} -> 140496.53
A91: 45980 | B91: BSC | C91: 1100 | D91: Silky | E91: 1920 | F91: 12000 | G91: 6508 | H91: =_xlfn.XLOOKUP(Table1[[#This Row],[Shipment Number]], 'pivot '!A:A,'pivot '!G:G, "NF") -> 1.4645818 | I91: =Table1[[#This Row],[Tiyaar/gaz]]/1.0936 -> 5950.9876 | J91: {=_xlfn.IFS( AND(Table1[[#This Row],[Party Name]]="Faizan",Table1[[#This Row],[Quality]]="Silky"),Table1[[#This Row],[tiyar/meters]]*13, AND(Table1[[#This Row],[Party Name]]="Sajad Khan",Table1[[#This Row],[Quality]]="Slub"),Table1[[#This Row],[tiyar/meters]]*13, AND(Table1[[#This Row],[Party Name]]="Faizan",Table1[[#This Row],[Quality]]="Slub"),Table1[[#This Row],[tiyar/meters]]*15, AND(Table1[[#This Row],[Party Name]]="Shafique Ansari",Table1[[#This Row],[Quality]]="Satin"),Table1[[#This Row],[tiyar/meters]]*28, Table1[[#This Row],[Quality]]="Chamki",Table1[[#This Row],[tiyar/meters]]*10, Table1[[#This Row],[Quality]]="Silky",Table1[[#This Row],[tiyar/meters]]*13, Table1[[#This Row],[Quality]]="Crinkle",Table1[[#This Row],[tiyar/meters]]*10 )} -> 77362.838
A92: 45980 | B92: BSC | C92: 1101 | D92: Silky | E92: 1898 | F92: 8003 | G92: 5167 | H92: =_xlfn.XLOOKUP(Table1[[#This Row],[Shipment Number]], 'pivot '!A:A,'pivot '!G:G, "NF") -> 2.5031853 | I92: =Table1[[#This Row],[Tiyaar/gaz]]/1.0936 -> 4724.7623 | J92: {=_xlfn.IFS( AND(Table1[[#This Row],[Party Name]]="Faizan",Table1[[#This Row],[Quality]]="Silky"),Table1[[#This Row],[tiyar/meters]]*13, AND(Table1[[#This Row],[Party Name]]="Sajad Khan",Table1[[#This Row],[Quality]]="Slub"),Table1[[#This Row],[tiyar/meters]]*13, AND(Table1[[#This Row],[Party Name]]="Faizan",Table1[[#This Row],[Quality]]="Slub"),Table1[[#This Row],[tiyar/meters]]*15, AND(Table1[[#This Row],[Party Name]]="Shafique Ansari",Table1[[#This Row],[Quality]]="Satin"),Table1[[#This Row],[tiyar/meters]]*28, Table1[[#This Row],[Quality]]="Chamki",Table1[[#This Row],[tiyar/meters]]*10, Table1[[#This Row],[Quality]]="Silky",Table1[[#This Row],[tiyar/meters]]*13, Table1[[#This Row],[Quality]]="Crinkle",Table1[[#This Row],[tiyar/meters]]*10 )} -> 61421.909
A93: 45980 | B93: BSC | C93: 1102 | D93: Silky | E93: 1898 | F93: 8003 | G93: 3366 | H93: =_xlfn.XLOOKUP(Table1[[#This Row],[Shipment Number]], 'pivot '!A:A,'pivot '!G:G, "NF") -> 2.5031853 | I93: =Table1[[#This Row],[Tiyaar/gaz]]/1.0936 -> 3077.9078 | J93: {=_xlfn.IFS( AND(Table1[[#This Row],[Party Name]]="Faizan",Table1[[#This Row],[Quality]]="Silky"),Table1[[#This Row],[tiyar/meters]]*13, AND(Table1[[#This Row],[Party Name]]="Sajad Khan",Table1[[#This Row],[Quality]]="Slub"),Table1[[#This Row],[tiyar/meters]]*13, AND(Table1[[#This Row],[Party Name]]="Faizan",Table1[[#This Row],[Quality]]="Slub"),Table1[[#This Row],[tiyar/meters]]*15, AND(Table1[[#This Row],[Party Name]]="Shafique Ansari",Table1[[#This Row],[Quality]]="Satin"),Table1[[#This Row],[tiyar/meters]]*28, Table1[[#This Row],[Quality]]="Chamki",Table1[[#This Row],[tiyar/meters]]*10, Table1[[#This Row],[Quality]]="Silky",Table1[[#This Row],[tiyar/meters]]*13, Table1[[#This Row],[Quality]]="Crinkle",Table1[[#This Row],[tiyar/meters]]*10 )} -> 40012.802
A94: 45980 | B94: BSC | C94: 1103 | D94: Silky | E94: 1920 | F94: 12000 | G94: 6423 | H94: =_xlfn.XLOOKUP(Table1[[#This Row],[Shipment Number]], 'pivot '!A:A,'pivot '!G:G, "NF") -> 1.4645818 | I94: =Table1[[#This Row],[Tiyaar/gaz]]/1.0936 -> 5873.2626 | J94: {=_xlfn.IFS( AND(Table1[[#This Row],[Party Name]]="Faizan",Table1[[#This Row],[Quality]]="Silky"),Table1[[#This Row],[tiyar/meters]]*13, AND(Table1[[#This Row],[Party Name]]="Sajad Khan",Table1[[#This Row],[Quality]]="Slub"),Table1[[#This Row],[tiyar/meters]]*13, AND(Table1[[#This Row],[Party Name]]="Faizan",Table1[[#This Row],[Quality]]="Slub"),Table1[[#This Row],[tiyar/meters]]*15, AND(Table1[[#This Row],[Party Name]]="Shafique Ansari",Table1[[#This Row],[Quality]]="Satin"),Table1[[#This Row],[tiyar/meters]]*28, Table1[[#This Row],[Quality]]="Chamki",Table1[[#This Row],[tiyar/meters]]*10, Table1[[#This Row],[Quality]]="Silky",Table1[[#This Row],[tiyar/meters]]*13, Table1[[#This Row],[Quality]]="Crinkle",Table1[[#This Row],[tiyar/meters]]*10 )} -> 76352.414
A95: 45980 | B95: BSC | C95: 1104 | D95: Silky | E95: 1875 | F95: 8051 | G95: 8739 | H95: =_xlfn.XLOOKUP(Table1[[#This Row],[Shipment Number]], 'pivot '!A:A,'pivot '!G:G, "NF") -> 0.74476747 | I95: =Table1[[#This Row],[Tiyaar/gaz]]/1.0936 -> 7991.0388 | J95: {=_xlfn.IFS( AND(Table1[[#This Row],[Party Name]]="Faizan",Table1[[#This Row],[Quality]]="Silky"),Table1[[#This Row],[tiyar/meters]]*13, AND(Table1[[#This Row],[Party Name]]="Sajad Khan",Table1[[#This Row],[Quality]]="Slub"),Table1[[#This Row],[tiyar/meters]]*13, AND(Table1[[#This Row],[Party Name]]="Faizan",Table1[[#This Row],[Quality]]="Slub"),Table1[[#This Row],[tiyar/meters]]*15, AND(Table1[[#This Row],[Party Name]]="Shafique Ansari",Table1[[#This Row],[Quality]]="Satin"),Table1[[#This Row],[tiyar/meters]]*28, Table1[[#This Row],[Quality]]="Chamki",Table1[[#This Row],[tiyar/meters]]*10, Table1[[#This Row],[Quality]]="Silky",Table1[[#This Row],[tiyar/meters]]*13, Table1[[#This Row],[Quality]]="Crinkle",Table1[[#This Row],[tiyar/meters]]*10 )} -> 103883.5
A96: 45980 | B96: BSC | C96: 1105 | D96: Silky | E96: 1918 | F96: 24516 | G96: 6876 | H96: =_xlfn.XLOOKUP(Table1[[#This Row],[Shipment Number]], 'pivot '!A:A,'pivot '!G:G, "NF") -> 2.0092636 | I96: =Table1[[#This Row],[Tiyaar/gaz]]/1.0936 -> 6287.4909 | J96: {=_xlfn.IFS( AND(Table1[[#This Row],[Party Name]]="Faizan",Table1[[#This Row],[Quality]]="Silky"),Table1[[#This Row],[tiyar/meters]]*13, AND(Table1[[#This Row],[Party Name]]="Sajad Khan",Table1[[#This Row],[Quality]]="Slub"),Table1[[#This Row],[tiyar/meters]]*13, AND(Table1[[#This Row],[Party Name]]="Faizan",Table1[[#This Row],[Quality]]="Slub"),Table1[[#This Row],[tiyar/meters]]*15, AND(Table1[[#This Row],[Party Name]]="Shafique Ansari",Table1[[#This Row],[Quality]]="Satin"),Table1[[#This Row],[tiyar/meters]]*28, Table1[[#This Row],[Quality]]="Chamki",Table1[[#This Row],[tiyar/meters]]*10, Table1[[#This Row],[Quality]]="Silky",Table1[[#This Row],[tiyar/meters]]*13, Table1[[#This Row],[Quality]]="Crinkle",Table1[[#This Row],[tiyar/meters]]*10 )} -> 81737.381
A97: 45981 | B97: Faizan | C97: 1106 | D97: Silky | E97: 1906 | F97: 36489 | G97: 27661 | H97: =_xlfn.XLOOKUP(Table1[[#This Row],[Shipment Number]], 'pivot '!A:A,'pivot '!G:G, "NF") -> 1.9756493 | I97: =Table1[[#This Row],[Tiyaar/gaz]]/1.0936 -> 25293.526 | J97: {=_xlfn.IFS( AND(Table1[[#This Row],[Party Name]]="Faizan",Table1[[#This Row],[Quality]]="Silky"),Table1[[#This Row],[tiyar/meters]]*13, AND(Table1[[#This Row],[Party Name]]="Sajad Khan",Table1[[#This Row],[Quality]]="Slub"),Table1[[#This Row],[tiyar/meters]]*13, AND(Table1[[#This Row],[Party Name]]="Faizan",Table1[[#This Row],[Quality]]="Slub"),Table1[[#This Row],[tiyar/meters]]*15, AND(Table1[[#This Row],[Party Name]]="Shafique Ansari",Table1[[#This Row],[Quality]]="Satin"),Table1[[#This Row],[tiyar/meters]]*28, Table1[[#This Row],[Quality]]="Chamki",Table1[[#This Row],[tiyar/meters]]*10, Table1[[#This Row],[Quality]]="Silky",Table1[[#This Row],[tiyar/meters]]*13, Table1[[#This Row],[Quality]]="Crinkle",Table1[[#This Row],[tiyar/meters]]*10 )} -> 328815.84
A98: 45981 | B98: Faizan | C98: 1107 | D98: Silky | E98: 1873 | F98: 42762 | G98: 835 | H98: =_xlfn.XLOOKUP(Table1[[#This Row],[Shipment Number]], 'pivot '!A:A,'pivot '!G:G, "NF") -> 98.214458 | I98: =Table1[[#This Row],[Tiyaar/gaz]]/1.0936 -> 763.53328 | J98: {=_xlfn.IFS( AND(Table1[[#This Row],[Party Name]]="Faizan",Table1[[#This Row],[Quality]]="Silky"),Table1[[#This Row],[tiyar/meters]]*13, AND(Table1[[#This Row],[Party Name]]="Sajad Khan",Table1[[#This Row],[Quality]]="Slub"),Table1[[#This Row],[tiyar/meters]]*13, AND(Table1[[#This Row],[Party Name]]="Faizan",Table1[[#This Row],[Quality]]="Slub"),Table1[[#This Row],[tiyar/meters]]*15, AND(Table1[[#This Row],[Party Name]]="Shafique Ansari",Table1[[#This Row],[Quality]]="Satin"),Table1[[#This Row],[tiyar/meters]]*28, Table1[[#This Row],[Quality]]="Chamki",Table1[[#This Row],[tiyar/meters]]*10, Table1[[#This Row],[Quality]]="Silky",Table1[[#This Row],[tiyar/meters]]*13, Table1[[#This Row],[Quality]]="Crinkle",Table1[[#This Row],[tiyar/meters]]*10 )} -> 9925.9327
A99: 45981 | B99: Faizan | C99: 1108 | D99: Silky | E99: 1883 | F99: 8030 | G99: 1819 | H99: =_xlfn.XLOOKUP(Table1[[#This Row],[Shipment Number]], 'pivot '!A:A,'pivot '!G:G, "NF") -> 2.5804841 | I99: =Table1[[#This Row],[Tiyaar/gaz]]/1.0936 -> 1663.3138 | J99: {=_xlfn.IFS( AND(Table1[[#This Row],[Party Name]]="Faizan",Table1[[#This Row],[Quality]]="Silky"),Table1[[#This Row],[tiyar/meters]]*13, AND(Table1[[#This Row],[Party Name]]="Sajad Khan",Table1[[#This Row],[Quality]]="Slub"),Table1[[#This Row],[tiyar/meters]]*13, AND(Table1[[#This Row],[Party Name]]="Faizan",Table1[[#This Row],[Quality]]="Slub"),Table1[[#This Row],[tiyar/meters]]*15, AND(Table1[[#This Row],[Party Name]]="Shafique Ansari",Table1[[#This Row],[Quality]]="Satin"),Table1[[#This Row],[tiyar/meters]]*28, Table1[[#This Row],[Quality]]="Chamki",Table1[[#This Row],[tiyar/meters]]*10, Table1[[#This Row],[Quality]]="Silky",Table1[[#This Row],[tiyar/meters]]*13, Table1[[#This Row],[Quality]]="Crinkle",Table1[[#This Row],[tiyar/meters]]*10 )} -> 21623.08
A100: 45981 | B100: BSC | C100: 1109 | D100: Silky | E100: 1918 | F100: 24116 | G100: 6626 | H100: =_xlfn.XLOOKUP(Table1[[#This Row],[Shipment Number]], 'pivot '!A:A,'pivot '!G:G, "NF") -> 2.0092636 | I100: =Table1[[#This Row],[Tiyaar/gaz]]/1.0936 -> 6058.8881 | J100: {=_xlfn.IFS( AND(Table1[[#This Row],[Party Name]]="Faizan",Table1[[#This Row],[Quality]]="Silky"),Table1[[#This Row],[tiyar/meters]]*13, AND(Table1[[#This Row],[Party Name]]="Sajad Khan",Table1[[#This Row],[Quality]]="Slub"),Table1[[#This Row],[tiyar/meters]]*13, AND(Table1[[#This Row],[Party Name]]="Faizan",Table1[[#This Row],[Quality]]="Slub"),Table1[[#This Row],[tiyar/meters]]*15, AND(Table1[[#This Row],[Party Name]]="Shafique Ansari",Table1[[#This Row],[Quality]]="Satin"),Table1[[#This Row],[tiyar/meters]]*28, Table1[[#This Row],[Quality]]="Chamki",Table1[[#This Row],[tiyar/meters]]*10, Table1[[#This Row],[Quality]]="Silky",Table1[[#This Row],[tiyar/meters]]*13, Table1[[#This Row],[Quality]]="Crinkle",Table1[[#This Row],[tiyar/meters]]*10 )} -> 78765.545
... A105: 45982 | B105: Sajad Khan | C105: 1114 | D105: Chamki | E105: 1887 | F105: 53910 | G105: 19686 | H105: =_xlfn.XLOOKUP(Table1[[#This Row],[Shipment Number]], 'pivot '!A:A,'pivot '!G:G, "NF") -> 2.2914997 | I105: =Table1[[#This Row],[Tiyaar/gaz]]/1.0936 -> 18001.097 | J105: {=_xlfn.IFS( AND(Table1[[#This Row],[Party Name]]="Faizan",Table1[[#This Row],[Quality]]="Silky"),Table1[[#This Row],[tiyar/meters]]*13, AND(Table1[[#This Row],[Party Name]]="Sajad Khan",Table1[[#This Row],[Quality]]="Slub"),Table1[[#This Row],[tiyar/meters]]*13, AND(Table1[[#This Row],[Party Name]]="Faizan",Table1[[#This Row],[Quality]]="Slub"),Table1[[#This Row],[tiyar/meters]]*15, AND(Table1[[#This Row],[Party Name]]="Shafique Ansari",Table1[[#This Row],[Quality]]="Satin"),Table1[[#This Row],[tiyar/meters]]*28, Table1[[#This Row],[Quality]]="Chamki",Table1[[#This Row],[tiyar/meters]]*10, Table1[[#This Row],[Quality]]="Silky",Table1[[#This Row],[tiyar/meters]]*13, Table1[[#This Row],[Quality]]="Crinkle",Table1[[#This Row],[tiyar/meters]]*10 )} -> 180010.97
A106: 45982 | B106: Raaz Fabrics | C106: 1115 | D106: Chamki | E106: 1670+1671 | F106: 24227 | G106: 25825 | H106: =_xlfn.XLOOKUP(Table1[[#This Row],[Shipment Number]], 'pivot '!A:A,'pivot '!G:G, "NF") -> 2.5274811 | I106: =Table1[[#This Row],[Tiyaar/gaz]]/1.0936 -> 23614.667 | J106: {=_xlfn.IFS( AND(Table1[[#This Row],[Party Name]]="Faizan",Table1[[#This Row],[Quality]]="Silky"),Table1[[#This Row],[tiyar/meters]]*13, AND(Table1[[#This Row],[Party Name]]="Sajad Khan",Table1[[#This Row],[Quality]]="Slub"),Table1[[#This Row],[tiyar/meters]]*13, AND(Table1[[#This Row],[Party Name]]="Faizan",Table1[[#This Row],[Quality]]="Slub"),Table1[[#This Row],[tiyar/meters]]*15, AND(Table1[[#This Row],[Party Name]]="Shafique Ansari",Table1[[#This Row],[Quality]]="Satin"),Table1[[#This Row],[tiyar/meters]]*28, Table1[[#This Row],[Quality]]="Chamki",Table1[[#This Row],[tiyar/meters]]*10, Table1[[#This Row],[Quality]]="Silky",Table1[[#This Row],[tiyar/meters]]*13, Table1[[#This Row],[Quality]]="Crinkle",Table1[[#This Row],[tiyar/meters]]*10 )} -> 236146.67
A107: 45982 | B107: Azam | C107: 1116 | D107: Chamki | E107: 1882 | F107: 26019 | G107: 4064 | H107: =_xlfn.XLOOKUP(Table1[[#This Row],[Shipment Number]], 'pivot '!A:A,'pivot '!G:G, "NF") -> 3.0061398 | I107: =Table1[[#This Row],[Tiyaar/gaz]]/1.0936 -> 3716.1668 | J107: {=_xlfn.IFS( AND(Table1[[#This Row],[Party Name]]="Faizan",Table1[[#This Row],[Quality]]="Silky"),Table1[[#This Row],[tiyar/meters]]*13, AND(Table1[[#This Row],[Party Name]]="Sajad Khan",Table1[[#This Row],[Quality]]="Slub"),Table1[[#This Row],[tiyar/meters]]*13, AND(Table1[[#This Row],[Party Name]]="Faizan",Table1[[#This Row],[Quality]]="Slub"),Table1[[#This Row],[tiyar/meters]]*15, AND(Table1[[#This Row],[Party Name]]="Shafique Ansari",Table1[[#This Row],[Quality]]="Satin"),Table1[[#This Row],[tiyar/meters]]*28, Table1[[#This Row],[Quality]]="Chamki",Table1[[#This Row],[tiyar/meters]]*10, Table1[[#This Row],[Quality]]="Silky",Table1[[#This Row],[tiyar/meters]]*13, Table1[[#This Row],[Quality]]="Crinkle",Table1[[#This Row],[tiyar/meters]]*10 )} -> 37161.668
A108: 45983 | B108: Sajad Khan | C108: 1117 | D108: Chamki | E108: 1887 | F108: 53910 | G108: 33096 | H108: =_xlfn.XLOOKUP(Table1[[#This Row],[Shipment Number]], 'pivot '!A:A,'pivot '!G:G, "NF") -> 2.2914997 | I108: =Table1[[#This Row],[Tiyaar/gaz]]/1.0936 -> 30263.35 | J108: {=_xlfn.IFS( AND(Table1[[#This Row],[Party Name]]="Faizan",Table1[[#This Row],[Quality]]="Silky"),Table1[[#This Row],[tiyar/meters]]*13, AND(Table1[[#This Row],[Party Name]]="Sajad Khan",Table1[[#This Row],[Quality]]="Slub"),Table1[[#This Row],[tiyar/meters]]*13, AND(Table1[[#This Row],[Party Name]]="Faizan",Table1[[#This Row],[Quality]]="Slub"),Table1[[#This Row],[tiyar/meters]]*15, AND(Table1[[#This Row],[Party Name]]="Shafique Ansari",Table1[[#This Row],[Quality]]="Satin"),Table1[[#This Row],[tiyar/meters]]*28, Table1[[#This Row],[Quality]]="Chamki",Table1[[#This Row],[tiyar/meters]]*10, Table1[[#This Row],[Quality]]="Silky",Table1[[#This Row],[tiyar/meters]]*13, Table1[[#This Row],[Quality]]="Crinkle",Table1[[#This Row],[tiyar/meters]]*10 )} -> 302633.5
A109: 45983 | B109: Sajad Khan | C109: 1118 | D109: Chamki | E109: 1890 | F109: 24030 | G109: 8374 | H109: =_xlfn.XLOOKUP(Table1[[#This Row],[Shipment Number]], 'pivot '!A:A,'pivot '!G:G, "NF") -> 2.80529 | I109: =Table1[[#This Row],[Tiyaar/gaz]]/1.0936 -> 7657.2787 | J109: {=_xlfn.IFS( AND(Table1[[#This Row],[Party Name]]="Faizan",Table1[[#This Row],[Quality]]="Silky"),Table1[[#This Row],[tiyar/meters]]*13, AND(Table1[[#This Row],[Party Name]]="Sajad Khan",Table1[[#This Row],[Quality]]="Slub"),Table1[[#This Row],[tiyar/meters]]*13, AND(Table1[[#This Row],[Party Name]]="Faizan",Table1[[#This Row],[Quality]]="Slub"),Table1[[#This Row],[tiyar/meters]]*15, AND(Table1[[#This Row],[Party Name]]="Shafique Ansari",Table1[[#This Row],[Quality]]="Satin"),Table1[[#This Row],[tiyar/meters]]*28, Table1[[#This Row],[Quality]]="Chamki",Table1[[#This Row],[tiyar/meters]]*10, Table1[[#This Row],[Quality]]="Silky",Table1[[#This Row],[tiyar/meters]]*13, Table1[[#This Row],[Quality]]="Crinkle",Table1[[#This Row],[tiyar/meters]]*10 )} -> 76572.787
A110: 45983 | B110: Sajad Khan | C110: 1119 | D110: Chamki | E110: 1890 | F110: 24030 | G110: 17168 | H110: =_xlfn.XLOOKUP(Table1[[#This Row],[Shipment Number]], 'pivot '!A:A,'pivot '!G:G, "NF") -> 2.80529 | I110: =Table1[[#This Row],[Tiyaar/gaz]]/1.0936 -> 15698.61 | J110: {=_xlfn.IFS( AND(Table1[[#This Row],[Party Name]]="Faizan",Table1[[#This Row],[Quality]]="Silky"),Table1[[#This Row],[tiyar/meters]]*13, AND(Table1[[#This Row],[Party Name]]="Sajad Khan",Table1[[#This Row],[Quality]]="Slub"),Table1[[#This Row],[tiyar/meters]]*13, AND(Table1[[#This Row],[Party Name]]="Faizan",Table1[[#This Row],[Quality]]="Slub"),Table1[[#This Row],[tiyar/meters]]*15, AND(Table1[[#This Row],[Party Name]]="Shafique Ansari",Table1[[#This Row],[Quality]]="Satin"),Table1[[#This Row],[tiyar/meters]]*28, Table1[[#This Row],[Quality]]="Chamki",Table1[[#This Row],[tiyar/meters]]*10, Table1[[#This Row],[Quality]]="Silky",Table1[[#This Row],[tiyar/meters]]*13, Table1[[#This Row],[Quality]]="Crinkle",Table1[[#This Row],[tiyar/meters]]*10 )} -> 156986.1
A111: 45983 | B111: Sajad Khan | C111: 1120 | D111: Chamki | E111: 1877 | F111: 25519 | G111: 27328 | H111: =_xlfn.XLOOKUP(Table1[[#This Row],[Shipment Number]], 'pivot '!A:A,'pivot '!G:G, "NF") -> 2.0767778 | I111: =Table1[[#This Row],[Tiyaar/gaz]]/1.0936 -> 24989.027 | J111: {=_xlfn.IFS( AND(Table1[[#This Row],[Party Name]]="Faizan",Table1[[#This Row],[Quality]]="Silky"),Table1[[#This Row],[tiyar/meters]]*13, AND(Table1[[#This Row],[Party Name]]="Sajad Khan",Table1[[#This Row],[Quality]]="Slub"),Table1[[#This Row],[tiyar/meters]]*13, AND(Table1[[#This Row],[Party Name]]="Faizan",Table1[[#This Row],[Quality]]="Slub"),Table1[[#This Row],[tiyar/meters]]*15, AND(Table1[[#This Row],[Party Name]]="Shafique Ansari",Table1[[#This Row],[Quality]]="Satin"),Table1[[#This Row],[tiyar/meters]]*28, Table1[[#This Row],[Quality]]="Chamki",Table1[[#This Row],[tiyar/meters]]*10, Table1[[#This Row],[Quality]]="Silky",Table1[[#This Row],[tiyar/meters]]*13, Table1[[#This Row],[Quality]]="Crinkle",Table1[[#This Row],[tiyar/meters]]*10 )} -> 249890.27
A112: 45983 | B112: Sajad Khan | C112: 1121 | D112: Chamki | E112: 1887 | F112: 53910 | G112: 2234 | H112: =_xlfn.XLOOKUP(Table1[[#This Row],[Shipment Number]], 'pivot '!A:A,'pivot '!G:G, "NF") -> 2.2914997 | I112: =Table1[[#This Row],[Tiyaar/gaz]]/1.0936 -> 2042.7944 | J112: {=_xlfn.IFS( AND(Table1[[#This Row],[Party Name]]="Faizan",Table1[[#This Row],[Quality]]="Silky"),Table1[[#This Row],[tiyar/meters]]*13, AND(Table1[[#This Row],[Party Name]]="Sajad Khan",Table1[[#This Row],[Quality]]="Slub"),Table1[[#This Row],[tiyar/meters]]*13, AND(Table1[[#This Row],[Party Name]]="Faizan",Table1[[#This Row],[Quality]]="Slub"),Table1[[#This Row],[tiyar/meters]]*15, AND(Table1[[#This Row],[Party Name]]="Shafique Ansari",Table1[[#This Row],[Quality]]="Satin"),Table1[[#This Row],[tiyar/meters]]*28, Table1[[#This Row],[Quality]]="Chamki",Table1[[#This Row],[tiyar/meters]]*10, Table1[[#This Row],[Quality]]="Silky",Table1[[#This Row],[tiyar/meters]]*13, Table1[[#This Row],[Quality]]="Crinkle",Table1[[#This Row],[tiyar/meters]]*10 )} -> 20427.944
A113: 45983 | B113: Azam | C113: 1122 | D113: Chamki | E113: 1882 | F113: 26019 | G113: 23535 | H113: =_xlfn.XLOOKUP(Table1[[#This Row],[Shipment Number]], 'pivot '!A:A,'pivot '!G:G, "NF") -> 3.0061398 | I113: =Table1[[#This Row],[Tiyaar/gaz]]/1.0936 -> 21520.666 | J113: {=_xlfn.IFS( AND(Table1[[#This Row],[Party Name]]="Faizan",Table1[[#This Row],[Quality]]="Silky"),Table1[[#This Row],[tiyar/meters]]*13, AND(Table1[[#This Row],[Party Name]]="Sajad Khan",Table1[[#This Row],[Quality]]="Slub"),Table1[[#This Row],[tiyar/meters]]*13, AND(Table1[[#This Row],[Party Name]]="Faizan",Table1[[#This Row],[Quality]]="Slub"),Table1[[#This Row],[tiyar/meters]]*15, AND(Table1[[#This Row],[Party Name]]="Shafique Ansari",Table1[[#This Row],[Quality]]="Satin"),Table1[[#This Row],[tiyar/meters]]*28, Table1[[#This Row],[Quality]]="Chamki",Table1[[#This Row],[tiyar/meters]]*10, Table1[[#This Row],[Quality]]="Silky",Table1[[#This Row],[tiyar/meters]]*13, Table1[[#This Row],[Quality]]="Crinkle",Table1[[#This Row],[tiyar/meters]]*10 )} -> 215206.66
A114: 45983 | B114: Azam | C114: 1123 | D114: Chamki | E114: 1853 | F114: 40243 | G114: 25269 | H114: =_xlfn.XLOOKUP(Table1[[#This Row],[Shipment Number]], 'pivot '!A:A,'pivot '!G:G, "NF") -> 2.1693941 | I114: =Table1[[#This Row],[Tiyaar/gaz]]/1.0936 -> 23106.255 | J114: {=_xlfn.IFS( AND(Table1[[#This Row],[Party Name]]="Faizan",Table1[[#This Row],[Quality]]="Silky"),Table1[[#This Row],[tiyar/meters]]*13, AND(Table1[[#This Row],[Party Name]]="Sajad Khan",Table1[[#This Row],[Quality]]="Slub"),Table1[[#This Row],[tiyar/meters]]*13, AND(Table1[[#This Row],[Party Name]]="Faizan",Table1[[#This Row],[Quality]]="Slub"),Table1[[#This Row],[tiyar/meters]]*15, AND(Table1[[#This Row],[Party Name]]="Shafique Ansari",Table1[[#This Row],[Quality]]="Satin"),Table1[[#This Row],[tiyar/meters]]*28, Table1[[#This Row],[Quality]]="Chamki",Table1[[#This Row],[tiyar/meters]]*10, Table1[[#This Row],[Quality]]="Silky",Table1[[#This Row],[tiyar/meters]]*13, Table1[[#This Row],[Quality]]="Crinkle",Table1[[#This Row],[tiyar/meters]]*10 )} -> 231062.55
A115: 45983 | B115: Azam | C115: 1124 | D115: Chamki | E115: 1853 | F115: 40243 | G115: 17786 | H115: =_xlfn.XLOOKUP(Table1[[#This Row],[Shipment Number]], 'pivot '!A:A,'pivot '!G:G, "NF") -> 2.1693941 | I115: =Table1[[#This Row],[Tiyaar/gaz]]/1.0936 -> 16263.716 | J115: {=_xlfn.IFS( AND(Table1[[#This Row],[Party Name]]="Faizan",Table1[[#This Row],[Quality]]="Silky"),Table1[[#This Row],[tiyar/meters]]*13, AND(Table1[[#This Row],[Party Name]]="Sajad Khan",Table1[[#This Row],[Quality]]="Slub"),Table1[[#This Row],[tiyar/meters]]*13, AND(Table1[[#This Row],[Party Name]]="Faizan",Table1[[#This Row],[Quality]]="Slub"),Table1[[#This Row],[tiyar/meters]]*15, AND(Table1[[#This Row],[Party Name]]="Shafique Ansari",Table1[[#This Row],[Quality]]="Satin"),Table1[[#This Row],[tiyar/meters]]*28, Table1[[#This Row],[Quality]]="Chamki",Table1[[#This Row],[tiyar/meters]]*10, Table1[[#This Row],[Quality]]="Silky",Table1[[#This Row],[tiyar/meters]]*13, Table1[[#This Row],[Quality]]="Crinkle",Table1[[#This Row],[tiyar/meters]]*10 )} -> 162637.16
A116: 45985 | B116: Sajad Khan | C116: 1125 | D116: Chamki | E116: 1889 | F116: 35271 | G116: 32780 | H116: =_xlfn.XLOOKUP(Table1[[#This Row],[Shipment Number]], 'pivot '!A:A,'pivot '!G:G, "NF") -> 2.7905097 | I116: =Table1[[#This Row],[Tiyaar/gaz]]/1.0936 -> 29974.396 | J116: {=_xlfn.IFS( AND(Table1[[#This Row],[Party Name]]="Faizan",Table1[[#This Row],[Quality]]="Silky"),Table1[[#This Row],[tiyar/meters]]*13, AND(Table1[[#This Row],[Party Name]]="Sajad Khan",Table1[[#This Row],[Quality]]="Slub"),Table1[[#This Row],[tiyar/meters]]*13, AND(Table1[[#This Row],[Party Name]]="Faizan",Table1[[#This Row],[Quality]]="Slub"),Table1[[#This Row],[tiyar/meters]]*15, AND(Table1[[#This Row],[Party Name]]="Shafique Ansari",Table1[[#This Row],[Quality]]="Satin"),Table1[[#This Row],[tiyar/meters]]*28, Table1[[#This Row],[Quality]]="Chamki",Table1[[#This Row],[tiyar/meters]]*10, Table1[[#This Row],[Quality]]="Silky",Table1[[#This Row],[tiyar/meters]]*13, Table1[[#This Row],[Quality]]="Crinkle",Table1[[#This Row],[tiyar/meters]]*10 )} -> 299743.96
A117: 45985 | B117: Sajad Khan | C117: 1126 | D117: Chamki | E117: 1887 | F117: 53910 | G117: 2589 | H117: =_xlfn.XLOOKUP(Table1[[#This Row],[Shipment Number]], 'pivot '!A:A,'pivot '!G:G, "NF") -> 2.2914997 | I117: =Table1[[#This Row],[Tiyaar/gaz]]/1.0936 -> 2367.4104 | J117: {=_xlfn.IFS( AND(Table1[[#This Row],[Party Name]]="Faizan",Table1[[#This Row],[Quality]]="Silky"),Table1[[#This Row],[tiyar/meters]]*13, AND(Table1[[#This Row],[Party Name]]="Sajad Khan",Table1[[#This Row],[Quality]]="Slub"),Table1[[#This Row],[tiyar/meters]]*13, AND(Table1[[#This Row],[Party Name]]="Faizan",Table1[[#This Row],[Quality]]="Slub"),Table1[[#This Row],[tiyar/meters]]*15, AND(Table1[[#This Row],[Party Name]]="Shafique Ansari",Table1[[#This Row],[Quality]]="Satin"),Table1[[#This Row],[tiyar/meters]]*28, Table1[[#This Row],[Quality]]="Chamki",Table1[[#This Row],[tiyar/meters]]*10, Table1[[#This Row],[Quality]]="Silky",Table1[[#This Row],[tiyar/meters]]*13, Table1[[#This Row],[Quality]]="Crinkle",Table1[[#This Row],[tiyar/meters]]*10 )} -> 23674.104
A118: 45985 | B118: Badshah Fabrics | C118: 1127 | D118: Chamki | E118: 1822+1823 | F118: 69241 | G118: 6844 | H118: =_xlfn.XLOOKUP(Table1[[#This Row],[Shipment Number]], 'pivot '!A:A,'pivot '!G:G, "NF") -> 79.608293 | I118: =Table1[[#This Row],[Tiyaar/gaz]]/1.0936 -> 6258.2297 | J118: {=_xlfn.IFS( AND(Table1[[#This Row],[Party Name]]="Faizan",Table1[[#This Row],[Quality]]="Silky"),Table1[[#This Row],[tiyar/meters]]*13, AND(Table1[[#This Row],[Party Name]]="Sajad Khan",Table1[[#This Row],[Quality]]="Slub"),Table1[[#This Row],[tiyar/meters]]*13, AND(Table1[[#This Row],[Party Name]]="Faizan",Table1[[#This Row],[Quality]]="Slub"),Table1[[#This Row],[tiyar/meters]]*15, AND(Table1[[#This Row],[Party Name]]="Shafique Ansari",Table1[[#This Row],[Quality]]="Satin"),Table1[[#This Row],[tiyar/meters]]*28, Table1[[#This Row],[Quality]]="Chamki",Table1[[#This Row],[tiyar/meters]]*10, Table1[[#This Row],[Quality]]="Silky",Table1[[#This Row],[tiyar/meters]]*13, Table1[[#This Row],[Quality]]="Crinkle",Table1[[#This Row],[tiyar/meters]]*10 )} -> 62582.297
A119: 45985 | B119: Amjad sohail | C119: 1128 | D119: Chamki | E119: 1884 | F119: 34783 | G119: 37340 | H119: =_xlfn.XLOOKUP(Table1[[#This Row],[Shipment Number]], 'pivot '!A:A,'pivot '!G:G, "NF") -> 1.8367847 | I119: =Table1[[#This Row],[Tiyaar/gaz]]/1.0936 -> 34144.111 | J119: {=_xlfn.IFS( AND(Table1[[#This Row],[Party Name]]="Faizan",Table1[[#This Row],[Quality]]="Silky"),Table1[[#This Row],[tiyar/meters]]*13, AND(Table1[[#This Row],[Party Name]]="Sajad Khan",Table1[[#This Row],[Quality]]="Slub"),Table1[[#This Row],[tiyar/meters]]*13, AND(Table1[[#This Row],[Party Name]]="Faizan",Table1[[#This Row],[Quality]]="Slub"),Table1[[#This Row],[tiyar/meters]]*15, AND(Table1[[#This Row],[Party Name]]="Shafique Ansari",Table1[[#This Row],[Quality]]="Satin"),Table1[[#This Row],[tiyar/meters]]*28, Table1[[#This Row],[Quality]]="Chamki",Table1[[#This Row],[tiyar/meters]]*10, Table1[[#This Row],[Quality]]="Silky",Table1[[#This Row],[tiyar/meters]]*13, Table1[[#This Row],[Quality]]="Crinkle",Table1[[#This Row],[tiyar/meters]]*10 )} -> 341441.11
A120: 45985 | B120: Amjad sohail | C120: 1129 | D120: Chamki | E120: 1926 | F120: 79388 | G120: 21877 | H120: =_xlfn.XLOOKUP(Table1[[#This Row],[Shipment Number]], 'pivot '!A:A,'pivot '!G:G, "NF") -> 2.8492898 | I120: =Table1[[#This Row],[Tiyaar/gaz]]/1.0936 -> 20004.572 | J120: {=_xlfn.IFS( AND(Table1[[#This Row],[Party Name]]="Faizan",Table1[[#This Row],[Quality]]="Silky"),Table1[[#This Row],[tiyar/meters]]*13, AND(Table1[[#This Row],[Party Name]]="Sajad Khan",Table1[[#This Row],[Quality]]="Slub"),Table1[[#This Row],[tiyar/meters]]*13, AND(Table1[[#This Row],[Party Name]]="Faizan",Table1[[#This Row],[Quality]]="Slub"),Table1[[#This Row],[tiyar/meters]]*15, AND(Table1[[#This Row],[Party Name]]="Shafique Ansari",Table1[[#This Row],[Quality]]="Satin"),Table1[[#This Row],[tiyar/meters]]*28, Table1[[#This Row],[Quality]]="Chamki",Table1[[#This Row],[tiyar/meters]]*10, Table1[[#This Row],[Quality]]="Silky",Table1[[#This Row],[tiyar/meters]]*13, Table1[[#This Row],[Quality]]="Crinkle",Table1[[#This Row],[tiyar/meters]]*10 )} -> 200045.72
A121: 45985 | B121: Sajad Khan | C121: 1130 | D121: Chamki | E121: 1889 | F121: 35271 | G121: 4716 | H121: =_xlfn.XLOOKUP(Table1[[#This Row],[Shipment Number]], 'pivot '!A:A,'pivot '!G:G, "NF") -> 2.7905097 | I121: =Table1[[#This Row],[Tiyaar/gaz]]/1.0936 -> 4312.3628 | J121: {=_xlfn.IFS( AND(Table1[[#This Row],[Party Name]]="Faizan",Table1[[#This Row],[Quality]]="Silky"),Table1[[#This Row],[tiyar/meters]]*13, AND(Table1[[#This Row],[Party Name]]="Sajad Khan",Table1[[#This Row],[Quality]]="Slub"),Table1[[#This Row],[tiyar/meters]]*13, AND(Table1[[#This Row],[Party Name]]="Faizan",Table1[[#This Row],[Quality]]="Slub"),Table1[[#This Row],[tiyar/meters]]*15, AND(Table1[[#This Row],[Party Name]]="Shafique Ansari",Table1[[#This Row],[Quality]]="Satin"),Table1[[#This Row],[tiyar/meters]]*28, Table1[[#This Row],[Quality]]="Chamki",Table1[[#This Row],[tiyar/meters]]*10, Table1[[#This Row],[Quality]]="Silky",Table1[[#This Row],[tiyar/meters]]*13, Table1[[#This Row],[Quality]]="Crinkle",Table1[[#This Row],[tiyar/meters]]*10 )} -> 43123.628
A122: 45985 | B122: Badshah Fabrics | C122: 1131 | D122: Chamki | E122: 1822+1823 | F122: 69241 | G122: 8597 | H122: =_xlfn.XLOOKUP(Table1[[#This Row],[Shipment Number]], 'pivot '!A:A,'pivot '!G:G, "NF") -> 79.608293 | I122: =Table1[[#This Row],[Tiyaar/gaz]]/1.0936 -> 7861.1924 | J122: {=_xlfn.IFS( AND(Table1[[#This Row],[Party Name]]="Faizan",Table1[[#This Row],[Quality]]="Silky"),Table1[[#This Row],[tiyar/meters]]*13, AND(Table1[[#This Row],[Party Name]]="Sajad Khan",Table1[[#This Row],[Quality]]="Slub"),Table1[[#This Row],[tiyar/meters]]*13, AND(Table1[[#This Row],[Party Name]]="Faizan",Table1[[#This Row],[Quality]]="Slub"),Table1[[#This Row],[tiyar/meters]]*15, AND(Table1[[#This Row],[Party Name]]="Shafique Ansari",Table1[[#This Row],[Quality]]="Satin"),Table1[[#This Row],[tiyar/meters]]*28, Table1[[#This Row],[Quality]]="Chamki",Table1[[#This Row],[tiyar/meters]]*10, Table1[[#This Row],[Quality]]="Silky",Table1[[#This Row],[tiyar/meters]]*13, Table1[[#This Row],[Quality]]="Crinkle",Table1[[#This Row],[tiyar/meters]]*10 )} -> 78611.924
...

Sheet Wood
A1: Date | B1: Party Name | C1: Vehicle Number | D1: Weight | E1: Rate | F1: Rent | G1: Total | H1: Paid | I1: balance
A2: 45947 | B2: Malik Zaheer | C2: Closing Balance CF | G2: =D2*E2 -> 0 | I2: 2567858
A3: 45947 | B3: Aqib | C3: Closing Balance CF | G3: =D3*E3 -> 0 | H3: 0 | I3: 0
A4: 45947 | B4: Rafaqat | C4: Closing Balance CF | G4: =D4*E4 -> 0 | H4: 0 | I4: 76420
A5: 45947 | B5: Kaleem ullah | C5: Closing Balance CF | G5: =D5*E5 -> 0 | I5: 350775
A6: 45947 | B6: Ishaq | C6: Closing Balance CF | G6: =D6*E6 -> 0 | I6: -1000 | K6: =SUM(Table3[Total]) -> 5400000 | L6: Party Name | M6: (All)
A7: 45979 | B7: Aurangzeb | C7: Closing Balance CF | G7: =D7*E7 -> 0 | I7: 330400
A8: 45980 | B8: Malik Zaheer | G8: =D8*E8 -> 0 | H8: =SUMIFS(Table14[Debit], Table14[Date], Table3[[#This Row],[Date]], Table14[Party], Table3[[#This Row],[Party Name]]) -> 408012 | I8: =(D8*E8)-Table3[[#This Row],[Paid]] -> -408012 | L8: Gari # | M8: Sum of Weight | N8: Sum of total | O8: Sum of Paid | P8: Sum of balance
A9: 45980 | B9: Kaleem ullah | G9: =D9*E9 -> 0 | H9: =SUMIFS(Table14[Debit], Table14[Date], Table3[[#This Row],[Date]], Table14[Party], Table3[[#This Row],[Party Name]]) -> 2000 | I9: =(D9*E9)-Table3[[#This Row],[Paid]] -> -2000 | L9: 45947 | N9: 0 | O9: 0 | P9: 2994053
A10: 45980 | B10: Aurangzeb | G10: =D10*E10 -> 0 | H10: =SUMIFS(Table14[Debit], Table14[Date], Table3[[#This Row],[Date]], Table14[Party], Table3[[#This Row],[Party Name]]) -> 4000 | I10: =(D10*E10)-Table3[[#This Row],[Paid]] -> -4000 | L10: Closing Balance CF | N10: 0 | O10: 0 | P10: 2994053
A11: 45981 | B11: Malik Zaheer | C11: TKL 364 | D11: 456 | E11: 810 | F11: 80300 | G11: =D11*E11 -> 369360 | H11: =SUMIFS(Table14[Debit], Table14[Date], Table3[[#This Row],[Date]], Table14[Party], Table3[[#This Row],[Party Name]]) -> 80300 | I11: =(D11*E11)-Table3[[#This Row],[Paid]] -> 289060 | L11: 45979 | N11: 0 | P11: 330400
A12: 45982 | B12: Malik Zaheer | G12: =D12*E12 -> 0 | H12: =SUMIFS(Table14[Debit], Table14[Date], Table3[[#This Row],[Date]], Table14[Party], Table3[[#This Row],[Party Name]]) -> 300152 | I12: =(D12*E12)-Table3[[#This Row],[Paid]] -> -300152 | L12: Closing Balance CF | N12: 0 | P12: 330400
A13: 45984 | B13: Malik Zaheer | C13: TKL 364 | D13: 394 | E13: 810 | F13: 67500 | G13: =D13*E13 -> 319140 | H13: =SUMIFS(Table14[Debit], Table14[Date], Table3[[#This Row],[Date]], Table14[Party], Table3[[#This Row],[Party Name]]) -> 200068 | I13: =(D13*E13)-Table3[[#This Row],[Paid]] -> 119072 | L13: 45982 | N13: 0 | O13: 300152 | P13: -300152
A14: 45985 | B14: Malik Zaheer | G14: =D14*E14 -> 0 | H14: =SUMIFS(Table14[Debit], Table14[Date], Table3[[#This Row],[Date]], Table14[Party], Table3[[#This Row],[Party Name]]) -> 67500 | I14: =(D14*E14)-Table3[[#This Row],[Paid]] -> -67500 | L14: (blank) | N14: 0 | O14: 300152 | P14: -300152
A15: 45984 | B15: Kaleem ullah | C15: 9662 | D15: 152 | E15: 775 | G15: =D15*E15 -> 117800 | H15: =SUMIFS(Table14[Debit], Table14[Date], Table3[[#This Row],[Date]], Table14[Party], Table3[[#This Row],[Party Name]]) -> 0 | I15: =(D15*E15)-Table3[[#This Row],[Paid]] -> 117800 | L15: 45980 | N15: 0 | O15: 414012 | P15: -414012
A16: 45984 | B16: Rafaqat | C16: APL | D16: 30 | E16: 580 | G16: =D16*E16 -> 17400 | H16: =SUMIFS(Table14[Debit], Table14[Date], Table3[[#This Row],[Date]], Table14[Party], Table3[[#This Row],[Party Name]]) -> 0 | I16: =(D16*E16)-Table3[[#This Row],[Paid]] -> 17400 | L16: (blank) | N16: 0 | O16: 414012 | P16: -414012
A17: 45985 | B17: Rafaqat | C17: APL | D17: 152 | E17: 580 | G17: =D17*E17 -> 88160 | H17: =SUMIFS(Table14[Debit], Table14[Date], Table3[[#This Row],[Date]], Table14[Party], Table3[[#This Row],[Party Name]]) -> 40000 | I17: =(D17*E17)-Table3[[#This Row],[Paid]] -> 48160 | L17: 45981 | M17: 456 | N17: 369360 | O17: 80300 | P17: 289060
A18: 45986 | B18: Malik Zaheer | C18: C 8947 | D18: 470 | E18: 810 | F18: 72800 | G18: =D18*E18 -> 380700 | H18: =SUMIFS(Table14[Debit], Table14[Date], Table3[[#This Row],[Date]], Table14[Party], Table3[[#This Row],[Party Name]]) -> 107800 | I18: =(D18*E18)-Table3[[#This Row],[Paid]] -> 272900 | L18: TKL 364 | M18: 456 | N18: 369360 | O18: 80300 | P18: 289060
A19: 45986 | B19: Malik Zaheer | C19: E 3229 | D19: 206 | E19: 765 | F19: 35000 | G19: =D19*E19 -> 157590 | I19: =(D19*E19)-Table3[[#This Row],[Paid]] -> 157590 | L19: 45984 | M19: 576 | N19: 454340 | O19: 200068 | P19: 254272
A20: 45987 | B20: Malik Zaheer | C20: E 9399 | D20: 281 | E20: 810 | F20: 45700 | G20: =D20*E20 -> 227610 | H20: =SUMIFS(Table14[Debit], Table14[Date], Table3[[#This Row],[Date]], Table14[Party], Table3[[#This Row],[Party Name]]) -> 347823 | I20: =(D20*E20)-Table3[[#This Row],[Paid]] -> -120213 | L20: TKL 364 | M20: 394 | N20: 319140 | O20: 200068 | P20: 119072
A21: 45987 | B21: Ishaq | C21: TAD 290 | D21: 384 | E21: 780 | F21: 100000 | G21: =D21*E21 -> 299520 | H21: =SUMIFS(Table14[Debit], Table14[Date], Table3[[#This Row],[Date]], Table14[Party], Table3[[#This Row],[Party Name]]) -> 100000 | I21: =(D21*E21)-Table3[[#This Row],[Paid]] -> 199520 | L21: 9662 | M21: 152 | N21: 117800 | O21: 0 | P21: 117800
A22: 45988 | B22: Malik Zaheer | C22: NAD 668 | D22: 496 | E22: 810 | F22: 106000 | G22: =D22*E22 -> 401760 | H22: =SUMIFS(Table14[Debit], Table14[Date], Table3[[#This Row],[Date]], Table14[Party], Table3[[#This Row],[Party Name]]) -> 106000 | I22: =(D22*E22)-Table3[[#This Row],[Paid]] -> 295760 | L22: APL | M22: 30 | N22: 17400 | O22: 0 | P22: 17400
A23: 45988 | B23: Kaleem ullah | G23: =D23*E23 -> 0 | H23: =SUMIFS(Table14[Debit], Table14[Date], Table3[[#This Row],[Date]], Table14[Party], Table3[[#This Row],[Party Name]]) -> 175000 | I23: =(D23*E23)-Table3[[#This Row],[Paid]] -> -175000 | L23: 45985 | M23: 152 | N23: 88160 | O23: 107500 | P23: -19340
A24: 45989 | B24: Malik Zaheer | C24: CAR 6957 | D24: 287 | E24: 810 | F24: 46100 | G24: =D24*E24 -> 232470 | H24: =SUMIFS(Table14[Debit], Table14[Date], Table3[[#This Row],[Date]], Table14[Party], Table3[[#This Row],[Party Name]]) -> 46100 | I24: =(D24*E24)-Table3[[#This Row],[Paid]] -> 186370 | L24: (blank) | N24: 0 | O24: 67500 | P24: -67500
A25: 45990 | B25: Malik Zaheer | G25: =D25*E25 -> 0 | H25: =SUMIFS(Table14[Debit], Table14[Date], Table3[[#This Row],[Date]], Table14[Party], Table3[[#This Row],[Party Name]]) -> 400338 | I25: =(D25*E25)-Table3[[#This Row],[Paid]] -> -400338 | L25: APL | M25: 152 | N25: 88160 | O25: 40000 | P25: 48160
A26: 45992 | B26: Malik Zaheer | C26: TKL 364 | D26: 433 | E26: 810 | F26: 74400 | G26: =D26*E26 -> 350730 | H26: =SUMIFS(Table14[Debit], Table14[Date], Table3[[#This Row],[Date]], Table14[Party], Table3[[#This Row],[Party Name]]) -> 300204 | I26: =(D26*E26)-Table3[[#This Row],[Paid]] -> 50526 | L26: 45986 | M26: 676 | N26: 538290 | O26: 107800 | P26: 430490
A27: 45993 | B27: Malik Zaheer | G27: =D27*E27 -> 0 | H27: =SUMIFS(Table14[Debit], Table14[Date], Table3[[#This Row],[Date]], Table14[Party], Table3[[#This Row],[Party Name]]) -> 274600 | I27: =(D27*E27)-Table3[[#This Row],[Paid]] -> -274600 | L27: C 8947 | M27: 470 | N27: 380700 | O27: 107800 | P27: 272900
A28: 45994 | B28: Malik Zaheer | G28: =D28*E28 -> 0 | H28: =SUMIFS(Table14[Debit], Table14[Date], Table3[[#This Row],[Date]], Table14[Party], Table3[[#This Row],[Party Name]]) -> 250768 | I28: =(D28*E28)-Table3[[#This Row],[Paid]] -> -250768 | L28: E 3229 | M28: 206 | N28: 157590 | P28: 157590
A29: 45994 | B29: Irfan Punjabi | C29: LES 8294 | D29: 225 | E29: 830 | F29: 50000 | G29: =D29*E29 -> 186750 | H29: =SUMIFS(Table14[Debit], Table14[Date], Table3[[#This Row],[Date]], Table14[Party], Table3[[#This Row],[Party Name]]) -> 50000 | I29: =(D29*E29)-Table3[[#This Row],[Paid]] -> 136750 | L29: 45987 | M29: 665 | N29: 527130 | O29: 447823 | P29: 79307
A30: 45995 | B30: Irfan Punjabi | C30: LEI 2223 | D30: 195 | E30: 830 | G30: =D30*E30 -> 161850 | H30: =SUMIFS(Table14[Debit], Table14[Date], Table3[[#This Row],[Date]], Table14[Party], Table3[[#This Row],[Party Name]]) -> 170000 | I30: =(D30*E30)-Table3[[#This Row],[Paid]] -> -8150 | L30: E 9399 | M30: 281 | N30: 227610 | O30: 347823 | P30: -120213
A31: 45995 | B31: Malik Zaheer | C31: C 1605 | D31: 471 | E31: 810 | F31: 118000 | G31: =D31*E31 -> 381510 | H31: =SUMIFS(Table14[Debit], Table14[Date], Table3[[#This Row],[Date]], Table14[Party], Table3[[#This Row],[Party Name]]) -> 418188 | I31: =(D31*E31)-Table3[[#This Row],[Paid]] -> -36678 | L31: TAD 290 | M31: 384 | N31: 299520 | O31: 100000 | P31: 199520
A32: 45996 | B32: Irfan Punjabi | C32: JU 4472 | D32: 215 | E32: 810 | F32: 40450 | G32: =D32*E32 -> 174150 | H32: =SUMIFS(Table14[Debit], Table14[Date], Table3[[#This Row],[Date]], Table14[Party], Table3[[#This Row],[Party Name]]) -> 40450 | I32: =(D32*E32)-Table3[[#This Row],[Paid]] -> 133700 | L32: 45988 | M32: 496 | N32: 401760 | O32: 281000 | P32: 120760
A33: 45997 | B33: Malik Zaheer | C33: TKT 364 | D33: 61 | E33: 810 | G33: =D33*E33 -> 49410 | H33: =SUMIFS(Table14[Debit], Table14[Date], Table3[[#This Row],[Date]], Table14[Party], Table3[[#This Row],[Party Name]]) -> 200510 | I33: =(D33*E33)-Table3[[#This Row],[Paid]] -> -151100 | L33: (blank) | N33: 0 | O33: 175000 | P33: -175000
A34: 45997 | B34: Irfan Punjabi | C34: LEI 2223 | D34: 188 | E34: 810 | G34: =D34*E34 -> 152280 | H34: =SUMIFS(Table14[Debit], Table14[Date], Table3[[#This Row],[Date]], Table14[Party], Table3[[#This Row],[Party Name]]) -> 128500 | I34: =(D34*E34)-Table3[[#This Row],[Paid]] -> 23780 | L34: NAD 668 | M34: 496 | N34: 401760 | O34: 106000 | P34: 295760
A35: 45997 | B35: Kaleem ullah | C35: LEI 9662 | D35: 134 | E35: 580 | G35: =D35*E35 -> 77720 | H35: =SUMIFS(Table14[Debit], Table14[Date], Table3[[#This Row],[Date]], Table14[Party], Table3[[#This Row],[Party Name]]) -> 150000 | I35: =(D35*E35)-Table3[[#This Row],[Paid]] -> -72280 | L35: 45989 | M35: 287 | N35: 232470 | O35: 46100 | P35: 186370
A36: 45997 | B36: Rafaqat | G36: =D36*E36 -> 0 | H36: =SUMIFS(Table14[Debit], Table14[Date], Table3[[#This Row],[Date]], Table14[Party], Table3[[#This Row],[Party Name]]) -> 50000 | I36: =(D36*E36)-Table3[[#This Row],[Paid]] -> -50000 | L36: CAR 6957 | M36: 287 | N36: 232470 | O36: 46100 | P36: 186370
A37: 45997 | B37: Amjad wood | C37: 8618 | D37: 182 | E37: 720 | G37: =D37*E37 -> 131040 | H37: =SUMIFS(Table14[Debit], Table14[Date], Table3[[#This Row],[Date]], Table14[Party], Table3[[#This Row],[Party Name]]) -> 100000 | I37: =(D37*E37)-Table3[[#This Row],[Paid]] -> 31040 | L37: 45990 | N37: 0 | O37: 400338 | P37: -400338
A38: 45996 | B38: Amjad wood | C38: 8618 | D38: 227 | E38: 720 | G38: =D38*E38 -> 163440 | H38: =SUMIFS(Table14[Debit], Table14[Date], Table3[[#This Row],[Date]], Table14[Party], Table3[[#This Row],[Party Name]]) -> 0 | I38: =(D38*E38)-Table3[[#This Row],[Paid]] -> 163440 | L38: (blank) | N38: 0 | O38: 400338 | P38: -400338
A39: 45997 | B39: Amjad wood | C39: 8618 | D39: 135 | E39: 720 | G39: =D39*E39 -> 97200 | I39: =(D39*E39)-Table3[[#This Row],[Paid]] -> 97200 | L39: 45992 | M39: 433 | N39: 350730 | O39: 300204 | P39: 50526
A40: 45996 | B40: Kaleem ullah | C40: LEJ 9662 | D40: 139 | E40: 580 | G40: =D40*E40 -> 80620 | I40: =(D40*E40)-Table3[[#This Row],[Paid]] -> 80620 | L40: TKL 364 | M40: 433 | N40: 350730 | O40: 300204 | P40: 50526
A41: 45997 | B41: Kaleem ullah | C41: - | D41: 128 | E41: 580 | G41: =D41*E41 -> 74240 | I41: =(D41*E41)-Table3[[#This Row],[Paid]] -> 74240 | L41: 45993 | N41: 0 | O41: 274600 | P41: -274600
A42: 45998 | B42: Kaleem ullah | C42: - | D42: 146 | E42: 580 | G42: =D42*E42 -> 84680 | I42: =(D42*E42)-Table3[[#This Row],[Paid]] -> 84680 | L42: (blank) | N42: 0 | O42: 274600 | P42: -274600
A43: 45998 | B43: Irfan Punjabi | C43: LES 3785 | D43: 191 | E43: 810 | G43: =D43*E43 -> 154710 | I43: =(D43*E43)-Table3[[#This Row],[Paid]] -> 154710 | L43: 45994 | M43: 225 | N43: 186750 | O43: 300768 | P43: -114018
A44: 45999 | B44: Amjad wood | C44: 8618 | D44: 172 | E44: 580 | G44: =D44*E44 -> 99760 | H44: =SUMIFS(Table14[Debit], Table14[Date], Table3[[#This Row],[Date]], Table14[Party], Table3[[#This Row],[Party Name]]) -> 120000 | I44: =(D44*E44)-Table3[[#This Row],[Paid]] -> -20240 | L44: (blank) | N44: 0 | O44: 250768 | P44: -250768
A45: 46000 | B45: Malik Zaheer | G45: =D45*E45 -> 0 | H45: =SUMIFS(Table14[Debit], Table14[Date], Table3[[#This Row],[Date]], Table14[Party], Table3[[#This Row],[Party Name]]) -> 200050 | I45: =(D45*E45)-Table3[[#This Row],[Paid]] -> -200050 | L45: LES 8294 | M45: 225 | N45: 186750 | O45: 50000 | P45: 136750
A46: 46000 | B46: Amjad wood | G46: =D46*E46 -> 0 | H46: =SUMIFS(Table14[Debit], Table14[Date], Table3[[#This Row],[Date]], Table14[Party], Table3[[#This Row],[Party Name]]) -> 70000 | I46: =(D46*E46)-Table3[[#This Row],[Paid]] -> -70000 | L46: 45995 | M46: 666 | N46: 543360 | O46: 588188 | P46: -44828
A47: 46000 | B47: Ishaq | G47: =D47*E47 -> 0 | H47: =SUMIFS(Table14[Debit], Table14[Date], Table3[[#This Row],[Date]], Table14[Party], Table3[[#This Row],[Party Name]]) -> 100000 | I47: =(D47*E47)-Table3[[#This Row],[Paid]] -> -100000 | L47: C 1605 | M47: 471 | N47: 381510 | O47: 418188 | P47: -36678
